Workbook
Name Scenario: Drivers!$B$6
Name iPhone_Units_Growth_Active: Drivers!$G$10
Name iPhone_ASP_YoY_Active: Drivers!$G$11
Name iPhone_ASP_Active: Drivers!$G$12
Name Mac_Units_Growth_Active: Drivers!$G$13
Name Mac_ASP_YoY_Active: Drivers!$G$14
Name Mac_ASP_Active: Drivers!$G$15
Name iPad_Units_Growth_Active: Drivers!$G$16
Name iPad_ASP_YoY_Active: Drivers!$G$17
Name iPad_ASP_Active: Drivers!$G$18
Name Wearables_Home_and_Accessories_Units_Growth_Active: Drivers!$G$19
Name Wearables_Home_and_Accessories_ASP_YoY_Active: Drivers!$G$20
Name Wearables_Home_and_Accessories_ASP_Active: Drivers!$G$21
Name Services_InstalledBase_Growth_Active: Drivers!$G$24
Name Services_ARPU_YoY_Active: Drivers!$G$25
Name Services_ARPU_Active: Drivers!$G$26
Name FX_Impact_Active: Drivers!$G$29
Name Mix_Impact_Active: Drivers!$G$30
Name Products_GM_Active: Drivers!$G$33
Name Services_GM_Active: Drivers!$G$34
Name SGA_Pct_Rev_Active: Drivers!$G$37
Name RD_Pct_Rev_Active: Drivers!$G$38
Name DSO_Active: Drivers!$G$41
Name DIO_Active: Drivers!$G$42
Name DPO_Active: Drivers!$G$43
Name CapEx_Pct_Rev_Active: Drivers!$G$46
Name Buyback_Pct_FCF_Active: Drivers!$G$47
Name Dividend_Payout_Active: Drivers!$G$48
Name Tax_Rate_Active: Drivers!$G$49
Name Debt_Roll_Active: Drivers!$G$50

Sheet Read Me
A1: README
A2: Prepared by: Mengru Shi | Status: Portfolio case study | Last updated: August 2026
A3: Independent case study using public information. Not an internal Apple document.
A5: Purpose
A6: Driver-based forecast model for a public-company FP&A case study. The workbook supports variance review, reforecasting, bridge analysis, sensitivity testing, and planning recommendations.
A8: Assumptions
A9: Forecasts are reconstructed from public data and explicit driver assumptions. Scenario outputs are model estimates.
A10: Public data does not include internal shipment, pricing, treasury, regional, installed-base, or management inputs.
A12: How to Navigate
A13: Start with Read Me, then review Drivers for assumptions, IS/BS/CF for forecast mechanics, Forecast Bridge for variance logic, Sensitivity for cases, and Output for dashboard source tables.
A15: Model Structure
A16: History -> source public financial data and historical actuals.
... A38: Review Q3 results before changing the Base case. Validate AI investment and subscription attachment assumptions with later public disclosures.

Sheet Drivers
A1: Apple Inc. -- Driver-Based Rolling Forecast Model: DRIVERS
A2: All Base/Bull/Bear inputs are annual run-rate assumptions used by every downstream IS/BS/CF/Bridge/Sensitivity tab in this workbook (Tasks 12-20).
A3: Downstream formulas must reference the ACTIVE column (never Base/Bull/Bear directly) so the entire model recalculates from the single Scenario switch below.
A4: Historical Reference values are sourced from '02 Historical Financial Database.xlsx' (Annual / Segment Detail tabs) and, where Apple does not disclose a figure (all unit/ASP volumes since FY2018, FX/Mix bridge points, installed base outside two earnings-call data points), from the implied-estimate method documented in data/business_memo_source_notes.md's Revenue Driver Tree section. Every such implied/estimated figure is labeled in the Source/Notes column.
A6: SCENARIO SWITCH (drives every Active column below): | B6: Base | C6: <- choose Base / Bull / Bear here (data-validation dropdown)
A8: Driver | B8: Unit | C8: Historical Reference | D8: Base | E8: Bull | F8: Bear | G8: Active | H8: Source / Notes
A9: SEGMENT REVENUE DRIVERS -- UNITS x ASP (iPhone / Mac / iPad / Wearables)
A10: iPhone -- Units Growth % | B10: % | C10: 0.042 | D10: 0.015 | E10: 0.035 | F10: -0.01 | G10: =INDEX(D10:F10,MATCH($B$6,$D$8:$F$8,0)) -> 0.015 | H10: FY2025 real revenue growth +4.2% (10-K, sourced). Base/Bull/Bear units growth is this agent's judgmental decomposition of revenue growth into units vs. ASP components (row below), reflecting IDC/Counterpoint commentary of roughly flat-to-low-single-digit iPhone unit shipments with revenue growth driven more by Pro/Pro Max mix-shift (ASP) than volume. Labeled as an implied estimate per the FY2018 unit-disclosure caveat.
A11: iPhone -- ASP YoY Change % | B11: % | D11: 0.02 | E11: 0.03 | F11: 0.005 | G11: =INDEX(D11:F11,MATCH($B$6,$D$8:$F$8,0)) -> 0.02 | H11: Judgmental split of the segment's historical revenue growth into a units component (row above) and an ASP/mix component (this row); see Source/Notes method note.
A12: iPhone -- ASP $ (implied) | B12: $/unit | C12: 900 | D12: =$C12*(1+D11) -> 918 | E12: =$C12*(1+E11) -> 927 | F12: =$C12*(1+F11) -> 904.5 | G12: =INDEX(D12:F12,MATCH($B$6,$D$8:$F$8,0)) -> 918 | H12: Implied ASP anchor $900 = midpoint of Business Memo's iPhone ASP benchmark range ($850-950, IDC/Counterpoint-style estimate; Apple has not disclosed iPhone unit shipments since FY2018 -- see Revenue Driver Tree Step 1 caveat). Implied FY2025 units at this anchor = $209,586M / $900 = ~232.9M units (estimate, not disclosed).
A13: Mac -- Units Growth % | B13: % | C13: 0.124 | D13: 0.04 | E13: 0.07 | F13: 0 | G13: =INDEX(D13:F13,MATCH($B$6,$D$8:$F$8,0)) -> 0.04 | H13: FY2025 real revenue growth +12.4% (10-K, sourced; M4 chip refresh cycle), but 5-yr history is highly volatile (+14.2%/-26.9%/+2.1%/+12.4%). Base moderates toward a normalized post-refresh growth rate rather than extrapolating the FY2025 spike, per task guidance. Units/ASP split is this agent's judgmental estimate, not disclosed.
A14: Mac -- ASP YoY Change % | B14: % | D14: 0.02 | E14: 0.03 | F14: 0 | G14: =INDEX(D14:F14,MATCH($B$6,$D$8:$F$8,0)) -> 0.02 | H14: Judgmental split of the segment's historical revenue growth into a units component (row above) and an ASP/mix component (this row); see Source/Notes method note.
A15: Mac -- ASP $ (implied) | B15: $/unit | C15: 1400 | D15: =$C15*(1+D14) -> 1428 | E15: =$C15*(1+E14) -> 1442 | F15: =$C15*(1+F14) -> 1400 | G15: =INDEX(D15:F15,MATCH($B$6,$D$8:$F$8,0)) -> 1428 | H15: Implied ASP anchor $1,400 -- market-research-style MacBook ASP benchmark (Apple does not disclose Mac unit shipments; estimate, analogous method to iPhone). Implied FY2025 units = $33,708M / $1,400 = ~24.1M units (estimate).
A16: iPad -- Units Growth % | B16: % | C16: 0.05 | D16: 0.01 | E16: 0.04 | F16: -0.04 | G16: =INDEX(D16:F16,MATCH($B$6,$D$8:$F$8,0)) -> 0.01 | H16: FY2025 revenue +5.0% (10-K, sourced) followed 3 consecutive down years (-8.1%/-3.4%/-5.7% FY22-24) -- weakest segment historically. Base case is cautious (does not extrapolate the FY2025 rebound); Bear resumes the multi-year decline pattern. Units/ASP split is judgmental, not disclosed.
A17: iPad -- ASP YoY Change % | B17: % | D17: 0.015 | E17: 0.02 | F17: 0 | G17: =INDEX(D17:F17,MATCH($B$6,$D$8:$F$8,0)) -> 0.015 | H17: Judgmental split of the segment's historical revenue growth into a units component (row above) and an ASP/mix component (this row); see Source/Notes method note.
A18: iPad -- ASP $ (implied) | B18: $/unit | C18: 475 | D18: =$C18*(1+D17) -> 482.125 | E18: =$C18*(1+E17) -> 484.5 | F18: =$C18*(1+F17) -> 475 | G18: =INDEX(D18:F18,MATCH($B$6,$D$8:$F$8,0)) -> 482.125 | H18: Implied ASP anchor $475 -- market-research-style iPad ASP benchmark (Apple does not disclose iPad unit shipments; estimate). Implied FY2025 units = $28,023M / $475 = ~59.0M units (estimate).
A19: Wearables, Home and Accessories -- Units Growth % | B19: % | C19: -0.036 | D19: -0.01 | E19: 0.03 | F19: -0.05 | G19: =INDEX(D19:F19,MATCH($B$6,$D$8:$F$8,0)) -> -0.01 | H19: Revenue declined 3 straight years (FY23 -3.4%, FY24 -7.1%, FY25 -3.6%) after FY22's +7.5%. Base assumes stabilization (near-flat blended growth); Bear continues the observed decline trend. Units/ASP split is judgmental, not disclosed.
A20: Wearables, Home and Accessories -- ASP YoY Change % | B20: % | D20: 0.01 | E20: 0.02 | F20: 0 | G20: =INDEX(D20:F20,MATCH($B$6,$D$8:$F$8,0)) -> 0.01 | H20: Judgmental split of the segment's historical revenue growth into a units component (row above) and an ASP/mix component (this row); see Source/Notes method note.
A21: Wearables, Home and Accessories -- ASP $ (implied) | B21: $/unit | C21: 165 | D21: =$C21*(1+D20) -> 166.65 | E21: =$C21*(1+E20) -> 168.3 | F21: =$C21*(1+F20) -> 165 | G21: =INDEX(D21:F21,MATCH($B$6,$D$8:$F$8,0)) -> 166.65 | H21: Implied ASP anchor $165 -- market-research-style blended ASP across AirPods/Watch/Accessories (Apple does not disclose unit shipments; estimate). Implied FY2025 units = $35,686M / $165 = ~216.3M units (estimate).
A23: SERVICES DRIVERS -- INSTALLED BASE x ARPU
A24: Services -- Installed Base Growth % | B24: % | C24: 0.0817 | D24: 0.075 | E24: 0.09 | F24: 0.06 | G24: =INDEX(D24:F24,MATCH($B$6,$D$8:$F$8,0)) -> 0.075 | H24: Historical Reference 8.17% = CAGR implied by Apple management's two public disclosures: >2.0B active devices (Jan 2023 earnings call) to >2.35B active devices (Jan 2025 earnings call) -- (2.35/2.00)^(1/2)-1. Not a 10-K disclosure (10-K contains no installed-base figure at all, per Business Memo notes); sourced from Apple management's public earnings-call commentary, per the Installed Base section's recommendation.
A25: Services -- ARPU YoY Change % | B25: % | D25: 0.05 | E25: 0.07 | F25: 0.03 | G25: =INDEX(D25:F25,MATCH($B$6,$D$8:$F$8,0)) -> 0.05 | H25: Implied historical ARPU growth ~4-6%/yr, derived from Services revenue growth (14.2%/9.1%/12.9%/13.5% FY22-25, 10-K sourced) less installed-base growth (row above). ARPU itself is not an Apple-disclosed metric -- it is computed as Services Revenue / Installed Base, both components estimated/sourced as noted.
A26: Services -- ARPU $ (implied, annual) | B26: $/device/yr | C26: 46.45 | D26: =$C26*(1+D25) -> 48.7725 | E26: =$C26*(1+E25) -> 49.7015 | F26: =$C26*(1+F25) -> 47.8435 | G26: =INDEX(D26:F26,MATCH($B$6,$D$8:$F$8,0)) -> 48.7725 | H26: Historical Reference $46.45 = FY2025 Services net sales $109,158M / 2.35B installed base (both sourced per notes above). Implied estimate, not an Apple-disclosed figure.
A28: OVERLAY ADJUSTMENTS -- FX & MIX (applied on top of Units x ASP / Installed Base x ARPU, per Revenue Driver Tree Step 3)
A29: FX Impact on Revenue % | B29: % | D29: 0 | E29: 0.01 | F29: -0.015 | G29: =INDEX(D29:F29,MATCH($B$6,$D$8:$F$8,0)) -> 0 | H29: No FX revenue bridge is disclosed in the FY2023-FY2025 10-Ks captured in the Historical Database / source notes (the MD&A tables extracted do not quantify an FX point-impact). Base case is therefore set to a neutral 0% (no assumed FX tailwind/headwind). Bull/Bear illustrate a directionally typical swing for a USD-weakens / USD-strengthens scenario and are explicitly labeled as this agent's assumption, not a sourced figure.
A30: Mix Impact on Revenue % | B30: % | D30: 0 | E30: 0.005 | F30: -0.005 | G30: =INDEX(D30:F30,MATCH($B$6,$D$8:$F$8,0)) -> 0 | H30: Residual product/regional/channel mix effect not already captured by the explicit segment ASP and Services ARPU trajectories above. No disclosed mix-bridge figure exists; Base is neutral (0%), Bull/Bear are this agent's illustrative assumption, explicitly labeled as such, kept separate from ASP/ARPU per the Revenue Driver Tree's Step 3 instruction (FX and Mix must not be folded into ASP).
A32: GROSS MARGIN DRIVERS (Products and Services split -- never a single blended GM%)
A33: Products Gross Margin % | B33: % | C33: 0.368 | D33: 0.37 | E33: 0.38 | F33: 0.355 | G33: =INDEX(D33:F33,MATCH($B$6,$D$8:$F$8,0)) -> 0.37 | H33: Historical Reference 36.8% = FY2025 actual (10-K, sourced). 5-yr avg 36.4%, 3-yr avg 36.8% -- stable range. Base holds near the recent average; Bear reflects tariff cost pressure (FY2025 MD&A: 'Products gross margin percentage decreased ... primarily due to a different mix of products and tariff costs').
A34: Services Gross Margin % | B34: % | C34: 0.754 | D34: 0.755 | E34: 0.77 | F34: 0.735 | G34: =INDEX(D34:F34,MATCH($B$6,$D$8:$F$8,0)) -> 0.755 | H34: Historical Reference 75.4% = FY2025 actual (10-K, sourced). 5-yr trend is a steady climb (69.7/71.7/70.8/73.9/75.4), 3-yr avg 73.4%. Base assumes continued modest expansion consistent with the trend; Bear reverts toward the 3-yr average.
A36: OPERATING EXPENSE DRIVERS (% of total revenue)
A37: SG&A (% of Revenue) | B37: % | C37: 0.0663 | D37: 0.066 | E37: 0.062 | F37: 0.072 | G37: =INDEX(D37:F37,MATCH($B$6,$D$8:$F$8,0)) -> 0.066 | H37: Historical Reference 6.63% = FY2025 actual (10-K, sourced: SG&A $27,601M / Revenue $416,161M). 5-yr trend 6.01/6.36/6.50/6.67/6.63% -- rising then plateauing. Bull = LOWER cost ratio (operating use); Bear = higher cost ratio (cost inflation).
A38: R&D (% of Revenue) | B38: % | C38: 0.083 | D38: 0.083 | E38: 0.078 | F38: 0.09 | G38: =INDEX(D38:F38,MATCH($B$6,$D$8:$F$8,0)) -> 0.083 | H38: Historical Reference 8.30% = FY2025 actual (10-K, sourced: R&D $34,550M / Revenue $416,161M). 5-yr trend is a steady climb (5.99/6.66/7.80/8.02/8.30%), consistent with the Business Memo's AI Strategy commentary on rising R&D intensity. Bull = LOWER cost ratio (revenue outgrows R&D spend); Bear = continued heavy AI investment without proportional revenue growth.
A40: WORKING CAPITAL DRIVERS (days; AR via DSO, Inventory via DIO, AP via DPO)
A41: Days Sales Outstanding (DSO) | B41: days | C41: 29.3 | D41: 33 | E41: 29 | F41: 37 | G41: =INDEX(D41:F41,MATCH($B$6,$D$8:$F$8,0)) -> 33 | H41: Historical Reference 29.3 days = 5-yr average of (AR / Total Revenue x 365) computed from the Historical Database Annual tab: 26.2/26.1/28.1/31.2/34.9 days FY21-25 -- a clear, steady rising trend (slower collections). Base (33.0) sits near the FY2025 actual (34.9) with slight mean-reversion; Bull = LOWER DSO (faster collection, favorable); Bear = continued deterioration along the observed trend.
A42: Days Inventory Outstanding (DIO) | B42: days | C42: 10.4 | D42: 10 | E42: 8 | F42: 13 | G42: =INDEX(D42:F42,MATCH($B$6,$D$8:$F$8,0)) -> 10 | H42: Historical Reference 10.4 days = 5-yr average of (Inventory / implied COGS x 365) computed from the Historical Database Annual tab (implied COGS = Total Revenue - Total Gross Margin): 11.3/8.1/10.8/12.6/9.4 days FY21-25 -- volatile, no clear trend. Bull = LOWER DIO (tighter inventory management, favorable); Bear = looser inventory control / supply-chain slippage.
A43: Days Payable Outstanding (DPO) | B43: days | C43: 108.1 | D43: 115 | E43: 122 | F43: 105 | G43: =INDEX(D43:F43,MATCH($B$6,$D$8:$F$8,0)) -> 115 | H43: Historical Reference 108.1 days = 5-yr average of (AP / implied COGS x 365) computed from the Historical Database Annual tab: 93.9/104.7/106.7/119.7/115.4 days FY21-25 -- a clear rising trend, leveling near 115-120 in FY24-25. Base sits near the recent level; Bull = HIGHER DPO (extended payables, favorable for cash conversion); Bear = payables tighten (less favorable).
A45: CAPITAL STRUCTURE DRIVERS
A46: CapEx (% of Revenue) | B46: % | C46: 0.0306 | D46: 0.03 | E46: 0.026 | F46: 0.038 | G46: =INDEX(D46:F46,MATCH($B$6,$D$8:$F$8,0)) -> 0.03 | H46: Historical Reference 3.06% = FY2025 actual (10-K, sourced: CapEx $12,715M / Revenue $416,161M). 5-yr trend 3.03/2.72/2.86/2.42/3.06% -- FY2025 spike reflects AI infrastructure buildout. Base continues at the elevated FY2025 level; Bull = LOWER CapEx ratio (capital efficiency, more FCF); Bear = further accelerated AI infra spend.
A47: Buyback ($ as % of Trailing FCF) | B47: % | C47: 0.918 | D47: 0.9 | E47: 1 | F47: 0.75 | G47: =INDEX(D47:F47,MATCH($B$6,$D$8:$F$8,0)) -> 0.9 | H47: Historical Reference 91.8% = FY2025 actual (10-K, sourced: Repurchases $90,711M / FCF $98,767M, where FCF = OCF $111,482M - CapEx $12,715M per the Business Memo's Free Cash Flow KPI formula). 5-yr trend 92.5/80.2/77.9/87.3/91.8%. Bull = MORE aggressive capital return (higher %); Bear = more conservative / capital preservation.
A48: Dividend Payout (% of Net Income) | B48: % | C48: 0.1377 | D48: 0.15 | E48: 0.16 | F48: 0.14 | G48: =INDEX(D48:F48,MATCH($B$6,$D$8:$F$8,0)) -> 0.15 | H48: Historical Reference 13.77% = FY2025 actual (10-K, sourced: Dividends paid $15,421M / Net income $112,010M). 5-yr trend 15.28/14.87/15.49/16.25/13.77% -- fairly stable ~14-16% band (FY2025's dip driven by the NI spike, not a payout cut). Base sits mid-band; Bull = higher payout (dividend growth); Bear = lower payout.
A49: Effective Tax Rate % | B49: % | C49: 0.1561 | D49: 0.16 | E49: 0.15 | F49: 0.18 | G49: =INDEX(D49:F49,MATCH($B$6,$D$8:$F$8,0)) -> 0.16 | H49: Historical Reference 15.61% = FY2025 actual (10-K, sourced: Tax provision $20,719M / pretax income $132,729M). 5-yr trend 13.3/16.2/14.7/24.1/15.6% -- FY2024's 24.1% spike is a one-time item (EU State Aid ruling-related charge), excluded from the Base anchor. Base assumes modest upward pressure from global minimum tax (OECD Pillar Two) rules vs. FY2025's rate; Bull = lower/favorable; Bear = adverse tax legislation.
A50: Debt Roll -- Net New Issuance/(Repayment) ($M) | B50: $M | D50: 0 | E50: 0 | F50: 0 | G50: =INDEX(D50:F50,MATCH($B$6,$D$8:$F$8,0)) -> 0 | H50: Held FLAT ($0 net financing) per task instruction: 'assume flat unless a specific maturity is known from the 10-K debt schedule.' The Historical Database / Sources notes extracted term-debt current/non-current BALANCES only (Annual tab rows 48/50) -- no maturity-by-tranche schedule was captured in Phase 2, so no specific future maturity is known. FY2025 actual net financing was Term debt issued $4,481M - Repaid $10,932M = -$6,451M net repayment (10-K, sourced) for reference only; not used as the forward assumption per the flat-unless-known rule.
A52: Color legend: blue = hardcoded scenario input; black on light green = Active output formula (INDEX/MATCH against the Scenario switch cell above); italic black = Historical Reference (sourced/derived, not itself scenario-dependent). Every Active cell also has a workbook-level defined name (e.g. iPhone_Units_Growth_Active) for well-supported reference by downstream tabs.

Sheet IS
A1: Apple Inc. -- Driver-Based Rolling Forecast Model: INCOME STATEMENT (IS)
A2: Historical actuals (FY24 Q1 - FY26 Q2, columns B:K) are pulled directly, unmodified, from '02 Historical Financial Database.xlsx' Quarterly tab -- real disclosed/XBRL-derived figures, not re-derived. Segment/product-line revenue is not available at quarterly grain in that source (see Segment Detail tab note), so historical columns show consolidated IS lines only.
A3: FY2026 Approved AOP (columns L:P) is the first vintage in the rolling-forecast chain (Project Spec): built entirely from real Excel formulas referencing the Drivers tab's Active column (Base/Bull/Bear switch at Drivers!B6) applied to FY2025 actual segment/Services revenue anchors, split into quarters via FY2024-FY2025 average seasonality weights (rows 8-13). Simplifications: Other income/(expense) is treated as immaterial (Tax_Rate_Active applied directly to Operating Income, not a separately-driven pretax line); diluted share count is held flat at the FY26 Q2 actual implied count (buyback-driven share-count reduction is a Balance Sheet/Cash Flow mechanic for a later task, not modeled in this IS tab). Later tasks add further vintage column blocks (Q1 Update, Q3 Reforecast, FY2027 AOP) to the right of this tab -- this FY2026 Approved AOP block is never overwritten.
B5: HISTORICAL ACTUALS -- Source: 02 Historical Financial Database.xlsx, Quarterly tab (real values, not re-derived) | L5: FY2026 Approved AOP -- first rolling-forecast vintage (Drivers tab Active column; Base/Bull/Bear scenario switch at Drivers!B6) | Q5: Q1 FY2026 ACTUAL vs. APPROVED AOP VARIANCE -- Actual = mirror of historical col J (real data); Variance = Actual - Approved AOP Q1 (col L) | T5: Q1 FORECAST UPDATE -- second rolling-forecast vintage (Q1 FY2026 actual reported; Q2-Q4 FY2026 reforecast using the Drivers tab Active column PLUS the Q1-actual driver adjustments in rows 63-78 below, in place of reverting to the original AOP assumptions where the Q1 variance was material) | X5: NOTES | Y5: Q2 FY2026 ACTUAL vs. Q1 FORECAST UPDATE VARIANCE -- Actual = mirror of historical col K (real data); Variance = Actual - Q1 Forecast Update's own Q2 column (T) | AB5: Q3 REFORECAST -- third rolling-forecast vintage, and the CURRENT / LIVE forecast in this project's story (Q1 and Q2 FY2026 are now both real actuals; Q3-Q4 reforecast using the Q1 Forecast Update's own Annual Build PLUS the Q2-actual driver adjustments in rows 84-99 below, in place of reverting to the Q1 Forecast Update's own assumptions where the Q2 variance was material) | AE5: NOTES | AF5: FY2027 AOP -- fifth and FINAL rolling-forecast vintage: next year's Annual Operating Plan, built off the Q3 Reforecast's Q4 FY2026 EXIT run-rate (col AC de-seasonalized by dividing by the Q4 weight, row 12 col E -- NOT a naive x4, and NOT the Q3 Reforecast's FY26 Total), grown one more year via the Drivers tab's Active assumptions (Base/Bull/Bear switch at Drivers!B6). Fresh forward plan -- no Driver Adjustment Log (see row 125). | AK5: NOTES
A6: Line Item | B6: FY24 Q1 | C6: FY24 Q2 | D6: FY24 Q3 | E6: FY24 Q4 | F6: FY25 Q1 | G6: FY25 Q2 | H6: FY25 Q3 | I6: FY25 Q4 | J6: FY26 Q1 (Actual) | K6: FY26 Q2 (Actual) | L6: Q1 -- FY2026 Approved AOP | M6: Q2 -- FY2026 Approved AOP | N6: Q3 -- FY2026 Approved AOP | O6: Q4 -- FY2026 Approved AOP | P6: FY26 Total -- FY2026 Approved AOP | Q6: Q1 FY2026 Actual | R6: Q1 vs AOP Variance ($) | S6: Q1 vs AOP Variance (%) | T6: Q2 -- Q1 Forecast Update | U6: Q3 -- Q1 Forecast Update | V6: Q4 -- Q1 Forecast Update | W6: FY26 Total -- Q1 Forecast Update | X6: Notes -- Q1 Forecast Update Rationale | Y6: Q2 FY2026 Actual | Z6: Q2 vs Q1 FU Variance ($) | AA6: Q2 vs Q1 FU Variance (%) | AB6: Q3 -- Q3 Reforecast | AC6: Q4 -- Q3 Reforecast | AD6: FY26 Total -- Q3 Reforecast | AE6: Notes -- Q3 Reforecast Rationale | AF6: Q1 -- FY2027 AOP | AG6: Q2 -- FY2027 AOP | AH6: Q3 -- FY2027 AOP | AI6: Q4 -- FY2027 AOP | AJ6: FY27 Total -- FY2027 AOP | AK6: Notes -- FY2027 AOP Rationale
A8: SEASONALITY WEIGHTS -- average of FY2024 & FY2025 quarterly Net Sales as % of that FY's total (columns B:E in THIS block only = Q1..Q4, not fiscal years)
A9: Quarter | B9: Q1 | C9: Q2 | D9: Q3 | E9: Q4
A10: FY2024 Net Sales % of FY2024 Total | B10: =B41/SUM($B$41:$E$41) -> 0.30579104 | C10: =C41/SUM($B$41:$E$41) -> 0.23208408 | D10: =D41/SUM($B$41:$E$41) -> 0.21935888 | E10: =E41/SUM($B$41:$E$41) -> 0.24276599
A11: FY2025 Net Sales % of FY2025 Total | B11: =F41/SUM($F$41:$I$41) -> 0.29868248 | C11: =G41/SUM($F$41:$I$41) -> 0.22913968 | D11: =H41/SUM($F$41:$I$41) -> 0.22596063 | E11: =I41/SUM($F$41:$I$41) -> 0.24621721
A12: Average Seasonality Weight (applied to AOP annual $) | B12: =AVERAGE(B10,B11) -> 0.30223676 | C12: =AVERAGE(C10,C11) -> 0.23061188 | D12: =AVERAGE(D10,D11) -> 0.22265975 | E12: =AVERAGE(E10,E11) -> 0.2444916
A13: Check: weights sum to 100% | B13: =SUM(B12:E12) -> 1
A15: FY2026 APPROVED AOP -- ANNUAL BUILD (helper: Drivers Active column x FY2025 actual anchors -> full-year AOP revenue, before the seasonality quarterly split above)
A16: iPhone: FY2025 Actual Revenue anchor ($M) | B16: 209586 | C16: Real FY2025 actual, sourced from 02 Historical Financial Database.xlsx Segment Detail tab (10-K disclosed).
A17: iPhone: Implied FY2025 Units (M) | B17: =B16/Drivers!$C$12 -> 232.87333 | C17: FY2025 anchor revenue divided by Drivers!C12 (Historical Reference ASP/ARPU $; not scenario-dependent).
A18: iPhone: FY2026 AOP Annual Revenue ($M) | B18: =B17*(1+iPhone_Units_Growth_Active)*iPhone_ASP_Active*(1+FX_Impact_Active)*(1+Mix_Impact_Active) -> 216984.39 | C18: Implied units/base x (1+iPhone_Units_Growth_Active) x iPhone_ASP_Active x (1+FX_Impact_Active) x (1+Mix_Impact_Active).
A19: Mac: FY2025 Actual Revenue anchor ($M) | B19: 33708 | C19: Real FY2025 actual, sourced from 02 Historical Financial Database.xlsx Segment Detail tab (10-K disclosed).
A20: Mac: Implied FY2025 Units (M) | B20: =B19/Drivers!$C$15 -> 24.077143 | C20: FY2025 anchor revenue divided by Drivers!C15 (Historical Reference ASP/ARPU $; not scenario-dependent).
A21: Mac: FY2026 AOP Annual Revenue ($M) | B21: =B20*(1+Mac_Units_Growth_Active)*Mac_ASP_Active*(1+FX_Impact_Active)*(1+Mix_Impact_Active) -> 35757.446 | C21: Implied units/base x (1+Mac_Units_Growth_Active) x Mac_ASP_Active x (1+FX_Impact_Active) x (1+Mix_Impact_Active).
A22: iPad: FY2025 Actual Revenue anchor ($M) | B22: 28023 | C22: Real FY2025 actual, sourced from 02 Historical Financial Database.xlsx Segment Detail tab (10-K disclosed).
A23: iPad: Implied FY2025 Units (M) | B23: =B22/Drivers!$C$18 -> 58.995789 | C23: FY2025 anchor revenue divided by Drivers!C18 (Historical Reference ASP/ARPU $; not scenario-dependent).
A24: iPad: FY2026 AOP Annual Revenue ($M) | B24: =B23*(1+iPad_Units_Growth_Active)*iPad_ASP_Active*(1+FX_Impact_Active)*(1+Mix_Impact_Active) -> 28727.778 | C24: Implied units/base x (1+iPad_Units_Growth_Active) x iPad_ASP_Active x (1+FX_Impact_Active) x (1+Mix_Impact_Active).
A25: Wearables, Home and Accessories: FY2025 Actual Revenue anchor ($M) | B25: 35686 | C25: Real FY2025 actual, sourced from 02 Historical Financial Database.xlsx Segment Detail tab (10-K disclosed).
A26: Wearables, Home and Accessories: Implied FY2025 Units (M) | B26: =B25/Drivers!$C$21 -> 216.27879 | C26: FY2025 anchor revenue divided by Drivers!C21 (Historical Reference ASP/ARPU $; not scenario-dependent).
A27: Wearables, Home and Accessories: FY2026 AOP Annual Revenue ($M) | B27: =B26*(1+Wearables_Home_and_Accessories_Units_Growth_Active)*Wearables_Home_and_Accessories_ASP_Active*(1+FX_Impact_Active)*(1+Mix_Impact_Active) -> 35682.431 | C27: Implied units/base x (1+Wearables_Home_and_Accessories_Units_Growth_Active) x Wearables_Home_and_Accessories_ASP_Active x (1+FX_Impact_Active) x (1+Mix_Impact_Active).
A28: Services: FY2025 Actual Revenue anchor ($M) | B28: 109158 | C28: Real FY2025 actual, sourced from 02 Historical Financial Database.xlsx Segment Detail tab (10-K disclosed).
A29: Services: Implied FY2025 Installed Base (M devices) | B29: =B28/Drivers!$C$26 -> 2350.0108 | C29: FY2025 anchor revenue divided by Drivers!C26 (Historical Reference ASP/ARPU $; not scenario-dependent).
A30: Services: FY2026 AOP Annual Revenue ($M) | B30: =B29*(1+Services_InstalledBase_Growth_Active)*Services_ARPU_Active*(1+FX_Impact_Active)*(1+Mix_Impact_Active) -> 123212.09 | C30: Implied units/base x (1+Services_InstalledBase_Growth_Active) x Services_ARPU_Active x (1+FX_Impact_Active) x (1+Mix_Impact_Active).
A31: Total FY2026 AOP Annual Revenue ($M) | B31: =B18+B21+B24+B27+B30 -> 440364.13
A33: INCOME STATEMENT
A34: =A6 -> Line Item | B34: =B6 -> FY24 Q1 | C34: =C6 -> FY24 Q2 | D34: =D6 -> FY24 Q3 | E34: =E6 -> FY24 Q4 | F34: =F6 -> FY25 Q1 | G34: =G6 -> FY25 Q2 | H34: =H6 -> FY25 Q3 | ... AK34: =AK6 -> Notes -- FY2027 AOP Rationale
A35: iPhone Revenue ($M) | B35: n/a | C35: n/a | D35: n/a | E35: n/a | F35: n/a | G35: n/a | H35: n/a | I35: n/a | J35: n/a | K35: n/a | L35: =$B$18*$B$12 -> 65580.658 | M35: =$B$18*$C$12 -> 50039.178 | N35: =$B$18*$D$12 -> 48313.69 | O35: =$B$18*$E$12 -> 53050.86 | P35: =SUM(L35:O35) -> 216984.39 | Q35: =J35 -> n/a | R35: n/a | S35: n/a | T35: =$B$73*$C$12 -> 51250.69 | U35: =$B$73*$D$12 -> 49483.425 | V35: =$B$73*$E$12 -> 54335.288 | W35: =SUM(Q35,T35:V35) -> 155069.4 | Y35: =K35 -> n/a | Z35: n/a | AA35: n/a | AB35: =$B$94*$D$12 -> 50270.294 | AC35: =$B$94*$E$12 -> 55199.31 | AD35: =SUM(Q35,Y35,AB35:AC35) -> 105469.6 | AF35: =$B$109*$B$12 -> 69260.087 | AG35: =$B$109*$C$12 -> 52846.646 | AH35: =$B$109*$D$12 -> 51024.349 | AI35: =$B$109*$E$12 -> 56027.3 | AJ35: =SUM(AF35:AI35) -> 229158.38
A36: Mac Revenue ($M) | B36: n/a | C36: n/a | D36: n/a | E36: n/a | F36: n/a | G36: n/a | H36: n/a | I36: n/a | J36: n/a | K36: n/a | L36: =$B$21*$B$12 -> 10807.215 | M36: =$B$21*$C$12 -> 8246.0921 | N36: =$B$21*$D$12 -> 7961.7442 | O36: =$B$21*$E$12 -> 8742.3953 | P36: =SUM(L36:O36) -> 35757.446 | Q36: =J36 -> n/a | R36: n/a | S36: n/a | T36: =$B$74*$C$12 -> 8445.7404 | U36: =$B$74*$D$12 -> 8154.508 | V36: =$B$74*$E$12 -> 8954.0597 | W36: =SUM(Q36,T36:V36) -> 25554.308 | Y36: =K36 -> n/a | Z36: n/a | AA36: n/a | AB36: =$B$95*$D$12 -> 8284.1784 | AC36: =$B$95*$E$12 -> 9096.4442 | AD36: =SUM(Q36,Y36,AB36:AC36) -> 17380.623 | AF36: =$B$112*$B$12 -> 11694.68 | AG36: =$B$112*$C$12 -> 8923.2434 | AH36: =$B$112*$D$12 -> 8615.5455 | AI36: =$B$112*$E$12 -> 9460.302 | AJ36: =SUM(AF36:AI36) -> 38693.771
A37: iPad Revenue ($M) | B37: n/a | C37: n/a | D37: n/a | E37: n/a | F37: n/a | G37: n/a | H37: n/a | I37: n/a | J37: n/a | K37: n/a | L37: =$B$24*$B$12 -> 8682.5907 | M37: =$B$24*$C$12 -> 6624.9671 | N37: =$B$24*$D$12 -> 6396.5201 | O37: =$B$24*$E$12 -> 7023.7005 | P37: =SUM(L37:O37) -> 28727.778 | Q37: =J37 -> n/a | R37: n/a | S37: n/a | T37: =$B$75*$C$12 -> 6785.3659 | U37: =$B$75*$D$12 -> 6551.3879 | V37: =$B$75*$E$12 -> 7193.7532 | W37: =SUM(Q37,T37:V37) -> 20530.507 | Y37: =K37 -> n/a | Z37: n/a | AA37: n/a | AB37: =$B$96*$D$12 -> 6655.5659 | AC37: =$B$96*$E$12 -> 7308.1459 | AD37: =SUM(Q37,Y37,AB37:AC37) -> 13963.712 | AF37: =$B$115*$B$12 -> 9124.5599 | AG37: =$B$115*$C$12 -> 6962.1972 | AH37: =$B$115*$D$12 -> 6722.1216 | AI37: =$B$115*$E$12 -> 7381.2273 | AJ37: =SUM(AF37:AI37) -> 30190.106
A38: Wearables, Home and Accessories Revenue ($M) | B38: n/a | C38: n/a | D38: n/a | E38: n/a | F38: n/a | G38: n/a | H38: n/a | I38: n/a | J38: n/a | K38: n/a | L38: =$B$27*$B$12 -> 10784.543 | M38: =$B$27*$C$12 -> 8228.7927 | N38: =$B$27*$D$12 -> 7945.0414 | O38: =$B$27*$E$12 -> 8724.0548 | P38: =SUM(L38:O38) -> 35682.431 | Q38: =J38 -> n/a | R38: n/a | S38: n/a | T38: =$B$76*$C$12 -> 8428.0222 | U38: =$B$76*$D$12 -> 8137.4008 | V38: =$B$76*$E$12 -> 8935.2751 | W38: =SUM(Q38,T38:V38) -> 25500.698 | Y38: =K38 -> n/a | Z38: n/a | AA38: n/a | AB38: =$B$97*$D$12 -> 8266.7991 | AC38: =$B$97*$E$12 -> 9077.361 | AD38: =SUM(Q38,Y38,AB38:AC38) -> 17344.16 | AF38: =$B$118*$B$12 -> 11109.081 | AG38: =$B$118*$C$12 -> 8476.4214 | AH38: =$B$118*$D$12 -> 8184.1311 | AI38: =$B$118*$E$12 -> 8986.5873 | AJ38: =SUM(AF38:AI38) -> 36756.221
A39: Products Revenue Subtotal ($M) | B39: n/a | C39: n/a | D39: n/a | E39: n/a | F39: n/a | G39: n/a | H39: n/a | I39: n/a | J39: n/a | K39: n/a | L39: =SUM(L35:L38) -> 95855.006 | M39: =SUM(M35:M38) -> 73139.03 | N39: =SUM(N35:N38) -> 70616.995 | O39: =SUM(O35:O38) -> 77541.011 | P39: =SUM(P35:P38) -> 317152.04 | Q39: =J39 -> n/a | R39: n/a | S39: n/a | T39: =SUM(T35:T38) -> 74909.818 | U39: =SUM(U35:U38) -> 72326.722 | V39: =SUM(V35:V38) -> 79418.376 | W39: =SUM(Q39,T39:V39) -> 226654.92 | Y39: =K39 -> n/a | Z39: n/a | AA39: n/a | AB39: =SUM(AB35:AB38) -> 73476.838 | AC39: =SUM(AC35:AC38) -> 80681.261 | AD39: =SUM(Q39,Y39,AB39:AC39) -> 154158.1 | AF39: =SUM(AF35:AF38) -> 101188.41 | AG39: =SUM(AG35:AG38) -> 77208.508 | AH39: =SUM(AH35:AH38) -> 74546.147 | AI39: =SUM(AI35:AI38) -> 81855.416 | AJ39: =SUM(AJ35:AJ38) -> 334798.48
A40: Services Revenue ($M) | B40: n/a | C40: n/a | D40: n/a | E40: n/a | F40: n/a | G40: n/a | H40: n/a | I40: n/a | J40: n/a | K40: n/a | L40: =$B$30*$B$12 -> 37239.224 | M40: =$B$30*$C$12 -> 28414.173 | N40: =$B$30*$D$12 -> 27434.374 | O40: =$B$30*$E$12 -> 30124.322 | P40: =SUM(L40:O40) -> 123212.09 | Q40: =J40 -> n/a | R40: n/a | S40: n/a | T40: =$B$77*$C$12 -> 29102.116 | U40: =$B$77*$D$12 -> 28098.595 | V40: =$B$77*$E$12 -> 30853.67 | W40: =SUM(Q40,T40:V40) -> 88054.38 | Y40: =K40 -> n/a | Z40: n/a | AA40: n/a | AB40: =$B$98*$D$12 -> 28545.41 | AC40: =$B$98*$E$12 -> 31344.294 | AD40: =SUM(Q40,Y40,AB40:AC40) -> 59889.704 | AF40: =$B$121*$B$12 -> 41653.385 | AG40: =$B$121*$C$12 -> 31782.255 | AH40: =$B$121*$D$12 -> 30686.315 | AI40: =$B$121*$E$12 -> 33695.117 | AJ40: =SUM(AF40:AI40) -> 137817.07
A41: Net sales / Total Revenue ($M) | B41: 119575 | C41: 90753 | D41: 85777 | E41: 94930 | F41: 124300 | G41: 95359 | H41: 94036 | I41: 102466 | J41: 143756 | K41: 111184 | L41: =L39+L40 -> 133094.23 | M41: =M39+M40 -> 101553.2 | N41: =N39+N40 -> 98051.37 | O41: =O39+O40 -> 107665.33 | P41: =P39+P40 -> 440364.13 | Q41: =J41 -> 143756 | R41: =Q41-L41 -> 10661.77 | S41: =R41/ABS(L41) -> 0.08010693 | T41: =T39+T40 -> 104011.93 | U41: =U39+U40 -> 100425.32 | V41: =V39+V40 -> 110272.05 | W41: =SUM(Q41,T41:V41) -> 458465.3 | X41: Q2-Q4 FU revenue is built off each segment's AOP annual revenue grossed up by the Q1 blended revenue-growth-surprise factor (+~8.0%; see Driver Adjustment Log row 65 and Annual Build rows 73-78) -- carried forward because Q1 actual net sales materially beat the AOP Q1 assumption, rather than reverting to the original AOP units/ASP growth path for the rest of the year. | Y41: =K41 -> 111184 | Z41: =Y41-T41 -> 7172.0663 | AA41: =Z41/ABS(T41) -> 0.068954263 | AB41: =AB39+AB40 -> 102022.25 | AC41: =AC39+AC40 -> 112025.56 | AD41: =SUM(Q41,Y41,AB41:AC41) -> 468987.8 | AE41: Q3-Q4 Reforecast revenue is built off each segment's Q1 Forecast Update annual revenue grossed up by the Q2 blended revenue-growth-surprise factor (+~1.6% of Q1 FU Annual Total; see Driver Adjustment Log row 86 and Annual Build rows 94-98) -- carried forward because Q2 actual net sales materially beat the Q1 Forecast Update's own Q2 assumption, rather than reverting to the Q1 FU's unmodified Q3-Q4 path. | AF41: =AF39+AF40 -> 142841.79 | AG41: =AG39+AG40 -> 108990.76 | AH41: =AH39+AH40 -> 105232.46 | AI41: =AI39+AI40 -> 115550.53 | AJ41: =AJ39+AJ40 -> 472615.55 | AK41: FY2027 AOP revenue is built off each segment's FY2026 Exit Run-Rate Annualized Revenue (Q3 Reforecast's Q4 FY2026 revenue, col AC, de-seasonalized by dividing by the Q4 weight, row 12 col E -- rows 107-121), NOT a naive x4 (which would understate the anchor by assuming an even 25% quarterly share) and NOT the Q3 Reforecast's FY26 Total (which blends in the already-reported Q1/Q2 actuals), then grown one more year via Drivers Active Units/ASP/InstalledBase/ARPU/FX/Mix -- same formula shape as Task 12's original AOP build, one year later.
A43: Cost of sales ($M) | B43: 64720 | C43: 48482 | D43: 46099 | E43: 51051 | F43: 66025 | G43: 50492 | H43: 50318 | I43: 54125 | J43: 74525 | K43: 56403 | L43: =L41-L44 -> 69512.264 | M43: =M41-M44 -> 53039.061 | N43: =N41-N44 -> 51210.129 | O43: =O41-O44 -> 56231.295 | P43: =SUM(L43:O43) -> 229992.75 | Q43: =J43 -> 74525 | R43: =Q43-L43 -> 5012.7364 | S43: =R43/ABS(L43) -> 0.072112978 | T43: =T41-T44 -> 54323.204 | U43: =U41-U44 -> 52449.99 | V43: =V41-V44 -> 57592.726 | W43: =SUM(Q43,T43:V43) -> 238890.92 | Y43: =K43 -> 56403 | Z43: =Y43-T43 -> 2079.7963 | AA43: =Z43/ABS(T43) -> 0.038285597 | AB43: =AB41-AB44 -> 51755.296 | AC43: =AC41-AC44 -> 56829.916 | AD43: =SUM(Q43,Y43,AB43:AC43) -> 239513.21 | AF43: =AF41-AF44 -> 73953.777 | AG43: =AG41-AG44 -> 56428.013 | AH43: =AH41-AH44 -> 54482.22 | AI43: =AI41-AI44 -> 59824.216 | AJ43: =SUM(AF43:AI43) -> 244688.22
A44: Gross margin ($M) | B44: 54855 | C44: 42271 | D44: 39678 | E44: 43879 | F44: 58275 | G44: 44867 | H44: 43718 | I44: 48341 | J44: 69231 | K44: 54781 | L44: =L39*Products_GM_Active+L40*Services_GM_Active -> 63581.966 | M44: =M39*Products_GM_Active+M40*Services_GM_Active -> 48514.142 | N44: =N39*Products_GM_Active+N40*Services_GM_Active -> 46841.241 | O44: =O39*Products_GM_Active+O40*Services_GM_Active -> 51434.037 | P44: =SUM(L44:O44) -> 210371.39 | Q44: =J44 -> 69231 | R44: =Q44-L44 -> 5649.0338 | S44: =R44/ABS(L44) -> 0.088846478 | T44: =T39*Products_GM_Active+T40*Services_GM_Active -> 49688.73 | U44: =U39*Products_GM_Active+U40*Services_GM_Active -> 47975.326 | V44: =V39*Products_GM_Active+V40*Services_GM_Active -> 52679.32 | W44: =SUM(Q44,T44:V44) -> 219574.38 | Y44: =K44 -> 54781 | Z44: =Y44-T44 -> 5092.27 | AA44: =Z44/ABS(T44) -> 0.1024834 | AB44: =AB41*$G$87 -> 50266.951 | AC44: =AC41*$G$87 -> 55195.639 | AD44: =SUM(Q44,Y44,AB44:AC44) -> 229474.59 | AF44: =AF39*Products_GM_Active+AF40*Services_GM_Active -> 68888.017 | AG44: =AG39*Products_GM_Active+AG40*Services_GM_Active -> 52562.75 | AH44: =AH39*Products_GM_Active+AH40*Services_GM_Active -> 50750.242 | AI44: =AI39*Products_GM_Active+AI40*Services_GM_Active -> 55726.317 | AJ44: =SUM(AF44:AI44) -> 227927.33
A45: Gross margin % | B45: =B44/B41 -> 0.45874974 | C45: =C44/C41 -> 0.46578075 | D45: =D44/D41 -> 0.46257155 | E45: =E44/E41 -> 0.4622248 | F45: =F44/F41 -> 0.46882542 | G45: =G44/G41 -> 0.47050619 | H45: =H44/H41 -> 0.46490706 | I45: =I44/I41 -> 0.471776 | ... P45: =P44/P41 -> 0.47772143 | Q45: =J45 -> 0.48158686 | R45: =Q45-L45 -> 0.0038654225 | S45: n/a (pp diff shown at left) | T45: =T44/T41 -> 0.47772143 | U45: =U44/U41 -> 0.47772143 | V45: =V44/V41 -> 0.47772143 | W45: =SUM(Q45,T45:V45) -> 1.9147512 | X45: Unchanged from AOP -- Q1 GM% variance was immaterial (+0.8% relative, below the 3% threshold; row 66). Q2-Q4 FU still uses Products_GM_Active / Services_GM_Active exactly as the AOP did. | Y45: =K45 -> 0.49270579 | Z45: =Y45-T45 -> 0.014984352 | AA45: n/a (pp diff shown at left) | AB45: =AB44/AB41 -> 0.49270579 | AC45: =AC44/AC41 -> 0.49270579 | AD45: =SUM(Q45,Y45,AB45:AC45) -> 1.9597042 | AE45: Q3-Q4 Reforecast GM% uses the Q2 actual blended GM% (~49.3%), not the Q1 Forecast Update's own Q2 assumption (~47.8%, itself Products_GM_Active/Services_GM_Active-based) -- a +3.1% relative variance, just above the 3% threshold (row 87); a borderline call, flagged explicitly in the log rationale. | AF45: =AF44/AF41 -> 0.48226794 | AG45: =AG44/AG41 -> 0.48226794 | AH45: =AH44/AH41 -> 0.48226794 | AI45: =AI44/AI41 -> 0.48226794 | AJ45: =AJ44/AJ41 -> 0.48226794 | AK45: Uses Drivers!Products_GM_Active / Services_GM_Active directly (NOT the Q3 Reforecast's Q2-actual-pinned GM% override, row 87) -- FY2027 is a fresh forward plan, not a reforecast of FY2026 execution reality.
A47: Research and development ($M) | B47: 7696 | C47: 7903 | D47: 8006 | E47: 7765 | F47: 8268 | G47: 8550 | H47: 8866 | I47: 8866 | J47: 10887 | K47: 11419 | L47: =L41*RD_Pct_Rev_Active -> 11046.821 | M47: =M41*RD_Pct_Rev_Active -> 8428.9158 | N47: =N41*RD_Pct_Rev_Active -> 8138.2637 | O47: =O41*RD_Pct_Rev_Active -> 8936.2226 | P47: =SUM(L47:O47) -> 36550.223 | Q47: =J47 -> 10887 | R47: =Q47-L47 -> -159.82108 | S47: =R47/ABS(L47) -> -0.014467608 | T47: =T41*$G$67 -> 7877.0829 | U47: =U41*$G$67 -> 7605.4594 | V47: =V41*$G$67 -> 8351.1767 | W47: =Q47+T47+U47+V47 -> 34720.719 | X47: Q2-Q4 FU R&D uses the Q1 actual R&D-to-revenue ratio (~7.6%), not the AOP's Drivers!RD_Pct_Rev_Active assumption (8.3%) -- a -8.8% relative variance, above threshold (row 67). | Y47: =K47 -> 11419 | Z47: =Y47-T47 -> 3541.9171 | AA47: =Z47/ABS(T47) -> 0.44964833 | AB47: =AB41*$G$88 -> 10478.055 | AC47: =AC41*$G$88 -> 11505.431 | AD47: =Q47+Y47+AB47+AC47 -> 44289.486 | AE47: Q3-Q4 Reforecast R&D uses the Q2 actual R&D-to-revenue ratio (~10.3%), not the Q1 Forecast Update's own Q2 assumption (~7.6%, itself pinned to Q1's unusually low ratio) -- a +35.6% relative variance, far above threshold (row 88). Reads as a reversion off an unusually light Q1. | AF47: =AF41*RD_Pct_Rev_Active -> 11855.869 | AG47: =AG41*RD_Pct_Rev_Active -> 9046.2333 | AH47: =AH41*RD_Pct_Rev_Active -> 8734.2944 | AI47: =AI41*RD_Pct_Rev_Active -> 9590.6942 | AJ47: =SUM(AF47:AI47) -> 39227.091 | AK47: Uses Drivers!RD_Pct_Rev_Active directly (NOT the Q3 Reforecast's Q2-actual-pinned R&D% override, row 88) -- same reasoning as GM% above.
A48: Selling, general and administrative ($M) | B48: 6786 | C48: 6468 | D48: 6320 | E48: 6523 | F48: 7175 | G48: 6728 | H48: 6650 | I48: 7048 | J48: 7492 | K48: 7477 | L48: =L41*SGA_Pct_Rev_Active -> 8784.2192 | M48: =M41*SGA_Pct_Rev_Active -> 6702.5114 | N48: =N41*SGA_Pct_Rev_Active -> 6471.3904 | O48: =O41*SGA_Pct_Rev_Active -> 7105.9119 | P48: =SUM(L48:O48) -> 29064.033 | Q48: =J48 -> 7492 | R48: =Q48-L48 -> -1292.2192 | S48: =R48/ABS(L48) -> -0.14710689 | T48: =T41*$G$68 -> 5420.6948 | U48: =U41*$G$68 -> 5233.7744 | V48: =V41*$G$68 -> 5746.9474 | W48: =Q48+T48+U48+V48 -> 23893.417 | X48: Q2-Q4 FU SG&A uses the Q1 actual SG&A-to-revenue ratio (~5.2%), not the AOP's Drivers!SGA_Pct_Rev_Active assumption (6.6%) -- a -21.0% relative variance, well above threshold (row 68). | Y48: =K48 -> 7477 | Z48: =Y48-T48 -> 2056.3052 | AA48: =Z48/ABS(T48) -> 0.37934346 | AB48: =AB41*$G$89 -> 6860.8823 | AC48: =AC41*$G$89 -> 7533.5937 | AD48: =Q48+Y48+AB48+AC48 -> 29363.476 | AE48: Q3-Q4 Reforecast SG&A uses the Q2 actual SG&A-to-revenue ratio (~6.7%), not the Q1 Forecast Update's own Q2 assumption (~5.2%, itself pinned to Q1's unusually low ratio) -- a +29.0% relative variance, well above threshold (row 89). Same reversion pattern as R&D above. | AF48: =AF41*SGA_Pct_Rev_Active -> 9427.5584 | AG48: =AG41*SGA_Pct_Rev_Active -> 7193.3903 | AH48: =AH41*SGA_Pct_Rev_Active -> 6945.3425 | AI48: =AI41*SGA_Pct_Rev_Active -> 7626.3352 | AJ48: =SUM(AF48:AI48) -> 31192.626 | AK48: Uses Drivers!SGA_Pct_Rev_Active directly (NOT the Q3 Reforecast's Q2-actual-pinned SG&A% override, row 89) -- same reasoning as GM% above.
A49: Operating income ($M) | B49: 40373 | C49: 27900 | D49: 25352 | E49: 29591 | F49: 42832 | G49: 29589 | H49: 28202 | I49: 32427 | J49: 50852 | K49: 35885 | L49: =L44-L47-L48 -> 43750.926 | M49: =M44-M47-M48 -> 33382.714 | N49: =N44-N47-N48 -> 32231.587 | O49: =O44-O47-O48 -> 35391.902 | P49: =SUM(L49:O49) -> 144757.13 | Q49: =J49 -> 50852 | R49: =Q49-L49 -> 7101.074 | S49: =R49/ABS(L49) -> 0.16230683 | T49: =T44-T47-T48 -> 36390.952 | U49: =U44-U47-U48 -> 35136.092 | V49: =V44-V47-V48 -> 38581.196 | W49: =Q49+T49+U49+V49 -> 160960.24 | X49: Flows through from the adjusted revenue (higher), unchanged GM% (immaterial variance), and adjusted R&D%/SG&A% (both lower than AOP) above -- no separate Operating Income driver adjustment. | Y49: =K49 -> 35885 | Z49: =Y49-T49 -> -505.95233 | AA49: =Z49/ABS(T49) -> -0.013903245 | AB49: =AB44-AB47-AB48 -> 32928.014 | AC49: =AC44-AC47-AC48 -> 36156.615 | AD49: =Q49+Y49+AB49+AC49 -> 155821.63 | AE49: Flows through from the adjusted revenue (higher), adjusted GM% (slightly higher), and adjusted R&D%/SG&A% (both higher than the Q1 Forecast Update's Q1-anchored ratios) above -- no separate Operating Income driver adjustment. | AF49: =AF44-AF47-AF48 -> 47604.59 | AG49: =AG44-AG47-AG48 -> 36323.127 | AH49: =AH44-AH47-AH48 -> 35070.605 | AI49: =AI44-AI47-AI48 -> 38509.288 | AJ49: =SUM(AF49:AI49) -> 157507.61 | AK49: Flows through from FY2027 AOP revenue, GM%, R&D%, and SG&A% above -- no separate Operating Income driver.
A50: Operating margin % | B50: =B49/B41 -> 0.33763747 | C50: =C49/C41 -> 0.30742785 | D50: =D49/D41 -> 0.29555708 | E50: =E49/E41 -> 0.31171389 | F50: =F49/F41 -> 0.34458568 | G50: =G49/G41 -> 0.31029059 | H50: =H49/H41 -> 0.29990642 | I50: =I49/I41 -> 0.31646595 | ... P50: =P49/P41 -> 0.32872143 | Q50: =J50 -> 0.35373828 | R50: =Q50-L50 -> 0.025016846 | S50: n/a (pp diff shown at left) | T50: =T49/T41 -> 0.34987286 | U50: =U49/U41 -> 0.34987286 | V50: =V49/V41 -> 0.34987286 | W50: =W49/W41 -> 0.35108489 | Y50: =K50 -> 0.32275327 | Z50: =Y50-T50 -> -0.027119582 | AA50: n/a (pp diff shown at left) | AB50: =AB49/AB41 -> 0.32275327 | AC50: =AC49/AC41 -> 0.32275327 | AD50: =AD49/AD41 -> 0.33225092 | AF50: =AF49/AF41 -> 0.33326794 | AG50: =AG49/AG41 -> 0.33326794 | AH50: =AH49/AH41 -> 0.33326794 | AI50: =AI49/AI41 -> 0.33326794 | AJ50: =AJ49/AJ41 -> 0.33326794
A52: Income tax provision ($M) | B52: n/a | C52: n/a | D52: n/a | E52: n/a | F52: n/a | G52: n/a | H52: n/a | I52: n/a | J52: n/a | K52: n/a | L52: =L49*Tax_Rate_Active -> 7000.1482 | M52: =M49*Tax_Rate_Active -> 5341.2343 | N52: =N49*Tax_Rate_Active -> 5157.0539 | O52: =O49*Tax_Rate_Active -> 5662.7044 | P52: =SUM(L52:O52) -> 23161.141 | Q52: =J52 -> n/a | R52: n/a | S52: n/a | T52: =T49*$G$69 -> 6265.2951 | U52: =U49*$G$69 -> 6049.2505 | V52: =V49*$G$69 -> 6642.3812 | W52: =W49-W53 -> 27711.927 | X52: Q2-Q4 FU applies the Q1 implied bundled Tax/Other haircut rate (~17.2%), not Drivers!Tax_Rate_Active (16.0%) -- a +7.6% relative variance, above threshold but flagged as a bundled estimate (conflates true tax-rate change with Task 12's unmodeled Other Income/(Expense) simplification; row 69). | Y52: =K52 -> n/a | Z52: n/a | AA52: n/a | AB52: =AB49*$G$90 -> 5669.0939 | AC52: =AC49*$G$90 -> 6224.9501 | AD52: =AD49-AD53 -> 26956.044 | AE52: Unchanged from the Q1 Forecast Update -- Q2 implied Tax/Other variance was immaterial (+2.1% relative, below the 3% threshold; row 90). Q3-Q4 Reforecast continues to apply the same bundled ~17.2% Tax/Other haircut rate the Q1 Forecast Update carried forward from Q1 actual. | AF52: =AF49*Tax_Rate_Active -> 7616.7344 | AG52: =AG49*Tax_Rate_Active -> 5811.7003 | AH52: =AH49*Tax_Rate_Active -> 5611.2969 | AI52: =AI49*Tax_Rate_Active -> 6161.486 | AJ52: =SUM(AF52:AI52) -> 25201.218 | AK52: Uses Drivers!Tax_Rate_Active directly (NOT the Q3 Reforecast's bundled Tax/Other haircut rate, row 90) -- a fresh plan reverts to the Drivers tab's clean effective tax rate assumption rather than carrying forward FY2026's bundled Other-Income-conflated estimate.
A53: Net income ($M) | B53: 33916 | C53: 23636 | D53: 21448 | E53: 14736 | F53: 36330 | G53: 24780 | H53: 23434 | I53: 27466 | J53: 42097 | K53: 29578 | L53: =L49-L52 -> 36750.778 | M53: =M49-M52 -> 28041.48 | N53: =N49-N52 -> 27074.533 | O53: =O49-O52 -> 29729.198 | P53: =SUM(L53:O53) -> 121595.99 | Q53: =J53 -> 42097 | R53: =Q53-L53 -> 5346.2222 | S53: =R53/ABS(L53) -> 0.14547235 | T53: =T49-T52 -> 30125.657 | U53: =U49-U52 -> 29086.842 | V53: =V49-V52 -> 31938.814 | W53: =Q53+T53+U53+V53 -> 133248.31 | X53: Flows through from adjusted revenue, R&D%, SG&A%, and Tax/Other rate above -- no separate Net Income driver adjustment. | Y53: =K53 -> 29578 | Z53: =Y53-T53 -> -547.65721 | AA53: =Z53/ABS(T53) -> -0.018179096 | AB53: =AB49-AB52 -> 27258.92 | AC53: =AC49-AC52 -> 29931.665 | AD53: =Q53+Y53+AB53+AC53 -> 128865.59 | AE53: Flows through from adjusted revenue, GM%, R&D%, and SG&A% above; Tax/Other rate unchanged -- no separate Net Income driver adjustment. | AF53: =AF49-AF52 -> 39987.855 | AG53: =AG49-AG52 -> 30511.426 | AH53: =AH49-AH52 -> 29459.309 | AI53: =AI49-AI52 -> 32347.802 | AJ53: =SUM(AF53:AI53) -> 132306.39 | AK53: Flows through from FY2027 AOP Operating Income and Tax_Rate_Active above -- no separate Net Income driver.
A54: Net margin % | B54: =B53/B41 -> 0.28363788 | C54: =C53/C41 -> 0.26044318 | D54: =D53/D41 -> 0.25004372 | E54: =E53/E41 -> 0.15523017 | F54: =F53/F41 -> 0.29227675 | G54: =G53/G41 -> 0.25986011 | H54: =H53/H41 -> 0.24920243 | I54: =I53/I41 -> 0.26804989 | ... P54: =P53/P41 -> 0.276126 | Q54: =J54 -> 0.29283647 | R54: =Q54-L54 -> 0.016710469 | S54: n/a (pp diff shown at left) | T54: =T53/T41 -> 0.28963655 | U54: =U53/U41 -> 0.28963655 | V54: =V53/V41 -> 0.28963655 | W54: =W53/W41 -> 0.29063991 | Y54: =K54 -> 0.26602749 | Z54: =Y54-T54 -> -0.02360906 | AA54: n/a (pp diff shown at left) | AB54: =AB53/AB41 -> 0.26718604 | AC54: =AC53/AC41 -> 0.26718604 | AD54: =AD53/AD41 -> 0.27477385 | AF54: =AF53/AF41 -> 0.27994507 | AG54: =AG53/AG41 -> 0.27994507 | AH54: =AH53/AH41 -> 0.27994507 | AI54: =AI53/AI41 -> 0.27994507 | AJ54: =AJ53/AJ41 -> 0.27994507
A56: Diluted shares outstanding (M) -- historical: implied (NI / EPS); AOP: held flat at FY26 Q2 actual | B56: =B53/B57 -> 15557.798 | C56: =C53/C57 -> 15448.366 | D56: =D53/D57 -> 15320 | E56: =E53/E57 -> 15191.753 | F56: =F53/F57 -> 15137.5 | G56: =G53/G57 -> 15018.182 | H56: =H53/H57 -> 14926.115 | I56: =I53/I57 -> 14927.174 | ... K56: =K53/K57 -> 14715.423 | L56: =$K$56 -> 14715.423 | M56: =$K$56 -> 14715.423 | N56: =$K$56 -> 14715.423 | O56: =$K$56 -> 14715.423 | P56: =$K$56 -> 14715.423 | Q56: =J56 -> 14822.887 | R56: =Q56-L56 -> 107.46444 | S56: =R56/ABS(L56) -> 0.007302844 | T56: =$K$56 -> 14715.423 | U56: =$K$56 -> 14715.423 | V56: =$K$56 -> 14715.423 | W56: =$K$56 -> 14715.423 | Y56: =K56 -> 14715.423 | Z56: =Y56-T56 -> 0 | AA56: =Z56/ABS(T56) -> 0 | AB56: =$K$56 -> 14715.423 | AC56: =$K$56 -> 14715.423 | AD56: =$K$56 -> 14715.423 | AF56: =$K$56 -> 14715.423 | AG56: =$K$56 -> 14715.423 | AH56: =$K$56 -> 14715.423 | AI56: =$K$56 -> 14715.423 | AJ56: =$K$56 -> 14715.423
A57: Earnings per share - diluted ($/share) | B57: 2.18 | C57: 1.53 | D57: 1.4 | E57: 0.97 | F57: 2.4 | G57: 1.65 | H57: 1.57 | I57: 1.84 | J57: 2.84 | K57: 2.01 | L57: =L53/L56 -> 2.4974327 | M57: =M53/M56 -> 1.9055844 | N57: =N53/N56 -> 1.8398746 | O57: =O53/O56 -> 2.0202748 | P57: =P53/P56 -> 8.2631664 | Q57: =J57 -> 2.84 | R57: =Q57-L57 -> 0.34256733 | S57: =R57/ABS(L57) -> 0.1371678 | T57: =T53/T56 -> 2.0472165 | U57: =U53/U56 -> 1.9766229 | V57: =V53/V56 -> 2.1704313 | W57: =W53/W56 -> 9.0550108 | X57: Flows through from adjusted Net Income above; diluted share count held flat at the same FY26 Q2 actual implied count the AOP used (Task 12's inherited share-count simplification -- no buyback modeled in this IS tab). | Y57: =K57 -> 2.01 | Z57: =Y57-T57 -> -0.037216546 | AA57: =Z57/ABS(T57) -> -0.018179096 | AB57: =AB53/AB56 -> 1.8524048 | AC57: =AC53/AC56 -> 2.0340336 | AD57: =AD53/AD56 -> 8.7571785 | AE57: Flows through from adjusted Net Income above; diluted share count held flat at the same FY26 Q2 actual implied count the AOP and Q1 Forecast Update both used (Task 12's inherited share-count simplification -- no buyback modeled in this IS tab). | AF57: =AF53/AF56 -> 2.7174112 | AG57: =AG53/AG56 -> 2.0734318 | AH57: =AH53/AH56 -> 2.0019342 | AI57: =AI53/AI56 -> 2.1982244 | AJ57: =AJ53/AJ56 -> 8.9910017 | AK57: Flows through from FY2027 AOP Net Income above; diluted share count held flat at the same FY26 Q2 actual implied count every prior vintage used (Task 12's inherited share-count simplification -- no buyback modeled in this IS tab, so FY2027 EPS growth is entirely NI-driven, not share-count-driven).
A59: Color legend: blue = sourced/hardcoded input (historical actual or FY2025 anchor); black on light green = FY2026 Approved AOP formula (references Drivers tab Active column, cascades with the Scenario switch Drivers!B6); light grey = Total column (sum/recompute of the four AOP quarters). 'n/a' = not available at quarterly grain in the Historical Database source (no fabricated figures).
A61: Q1 FORECAST UPDATE -- second rolling-forecast vintage in the chain (FY2026 Approved AOP -> Q1 FY2026 Actual -> Q1 Forecast Update). Materiality threshold: a Q1 Actual vs. AOP Q1 driver variance is carried forward into the Q2-Q4 Forecast Update columns (T:V) only where ABS(relative variance) > 3% (brief's suggested 2-3% range; 3% chosen and applied consistently below). Variances at or below 3% are treated as noise and the original AOP Base-scenario Drivers-tab assumption is retained unchanged.
A63: DRIVER ADJUSTMENT LOG -- Q1 FY2026 Actual vs. FY2026 Approved AOP Q1 (each row below is a real formula referencing the IS tab's own Q1 Actual / AOP Q1 cells and the Drivers tab's Active named ranges; nothing here is hardcoded)
A64: Driver | B64: Q1 Actual | C64: AOP Q1 Assumption | D64: Variance (abs / pp) | E64: Variance (% relative) | F64: Material? (>3% relative) | G64: Adjusted Value -> Q2-Q4 FU (live IF(), mirrors col F -- never a static/hardcoded choice) | H64: Rationale (plain language)
A65: Consolidated Net Sales (blended Units x ASP x FX x Mix growth proxy -- Historical Database has no quarterly segment split, so the beat cannot be attributed to a specific product line; see Task 12 note). NOTE: column G here is expressed as a % of AOP ANNUAL revenue (col G = D/ABS(B31)), not of AOP Q1 (col E) -- deliberately, so the dollar-level Q1 beat still cascades with the Drivers!B6 scenario switch when grossed up into a full-year figure below (rows 73-78); dividing by AOP Q1 instead would algebraically cancel the scenario dependency out of the Q2-Q4 Forecast Update entirely (verified: AOPQ1(scenario) x [1 + (Actual-AOPQ1)/AOPQ1(scenario)] = Actual regardless of scenario -- a bug caught during self-review). | B65: =Q41 -> 143756 | C65: =L41 -> 133094.23 | D65: =B65-C65 -> 10661.77 | E65: =D65/ABS(C65) -> 0.08010693 | F65: =IF(ABS(E65)>0.03,"Y -- carried forward","N -- immaterial, AOP retained") -> Y -- carried forward | G65: =IF(ABS(E65)>0.03,D65/ABS(B31),0) -> 0.024211259 | H65: Q1 FY2026 actual net sales beat the Approved AOP Q1 assumption by roughly +$10.7B / +8.0% of AOP Q1 (col E) -- well above the 3% threshold, so col G evaluates its IF()'s TRUE branch: the +$10.7B beat is carried forward as a uniform annual-revenue uplift (~+2.4% of AOP Annual Total) applied to all five revenue streams' Q2-Q4 annual-build revenue (rows 73-78) -- i.e. the full-year AOP revenue path is raised by the Q1 dollar beat -- rather than reverting to the original AOP units/ASP path for Q2-Q4. If a future scenario toggle ever makes this variance immaterial (<=3%), col G's FALSE branch (0) means the annual build correctly falls back to the unmodified AOP annual revenue (B73=B18*(1+0)=B18).
A66: Blended Gross Margin % (Products_GM_Active / Services_GM_Active mix) | B66: =Q45 -> 0.48158686 | C66: =L45 -> 0.47772143 | D66: =B66-C66 -> 0.0038654225 | E66: =D66/ABS(C66) -> 0.0080913734 | F66: =IF(ABS(E66)>0.03,"Y -- carried forward","N -- immaterial, AOP retained") -> N -- immaterial, AOP retained | G66: =IF(ABS(E66)>0.03,B66,C66) -> 0.47772143 | H66: Q1 actual GM% came in only ~+0.4pp / +0.8% relative above the AOP Q1 assumption -- below the 3% materiality threshold, so col G's IF() evaluates to its FALSE branch (the AOP assumption, col C), unchanged. No GM% driver change is carried forward under the delivered Base scenario; Q2-Q4 FU gross margin continues to use Products_GM_Active / Services_GM_Active exactly as the AOP did. (Col G is now a live IF() re-testing col E each time, so if a different scenario ever pushed this variance above 3%, col G would automatically switch to the actual-based value, col B, instead of silently staying stuck at the AOP value the way the original hardcoded version did.)
A67: R&D as % of Net Sales (vs. Drivers!RD_Pct_Rev_Active) | B67: =Q47/Q41 -> 0.075732491 | C67: =RD_Pct_Rev_Active -> 0.083 | D67: =B67-C67 -> -0.0072675088 | E67: =D67/ABS(C67) -> -0.087560347 | F67: =IF(ABS(E67)>0.03,"Y -- carried forward","N -- immaterial, AOP retained") -> Y -- carried forward | G67: =IF(ABS(E67)>0.03,B67,C67) -> 0.075732491 | H67: Q1 actual R&D ran at ~7.6% of net sales vs. the AOP's 8.3% Base-scenario assumption (Drivers!RD_Pct_Rev_Active) -- a -0.7pp / -8.8% relative variance, above threshold, so col G's IF() evaluates to its TRUE branch (the actual ratio, col B). Carried forward: Q2-Q4 FU R&D uses the Q1 actual ratio (~7.6%) instead of reverting to the AOP's 8.3%, reflecting R&D spend growing slower than the Q1 revenue beat. Col G is a live IF() -- if a scenario toggle ever pushed Drivers!RD_Pct_Rev_Active close enough to 7.6% to fall within 3% relative, col G would automatically fall back to col C (the AOP assumption).
A68: SG&A as % of Net Sales (vs. Drivers!SGA_Pct_Rev_Active) | B68: =Q48/Q41 -> 0.052116086 | C68: =SGA_Pct_Rev_Active -> 0.066 | D68: =B68-C68 -> -0.013883914 | E68: =D68/ABS(C68) -> -0.21036234 | F68: =IF(ABS(E68)>0.03,"Y -- carried forward","N -- immaterial, AOP retained") -> Y -- carried forward | G68: =IF(ABS(E68)>0.03,B68,C68) -> 0.052116086 | H68: Q1 actual SG&A ran at ~5.2% of net sales vs. the AOP's 6.6% Base-scenario assumption (Drivers!SGA_Pct_Rev_Active) -- a -1.4pp / -21.0% relative variance, well above threshold, so col G's IF() evaluates to its TRUE branch (the actual ratio, col B). Carried forward: Q2-Q4 FU SG&A uses the Q1 actual ratio (~5.2%) instead of reverting to the AOP's 6.6%. Col G is a live IF() re-testing col E, not a value baked in from the Base scenario.
A69: Effective Tax / Other haircut rate, 1-(NI/OpInc) (vs. Drivers!Tax_Rate_Active; bundles the true effective tax rate with Task 12's unmodeled Other Income/(Expense) simplification -- see Task 12 Concern #1) | B69: =1-Q53/Q49 -> 0.17216629 | C69: =Tax_Rate_Active -> 0.16 | D69: =B69-C69 -> 0.012166286 | E69: =D69/ABS(C69) -> 0.07603929 | F69: =IF(ABS(E69)>0.03,"Y -- carried forward","N -- immaterial, AOP retained") -> Y -- carried forward | G69: =IF(ABS(E69)>0.03,B69,C69) -> 0.17216629 | H69: Q1 implied OpInc-to-NI haircut was ~17.2% vs. the AOP's 16.0% Tax_Rate_Active assumption -- a +1.2pp / +7.6% relative variance, above threshold, so col G's IF() evaluates to its TRUE branch (the actual ratio, col B). Because Task 12's IS tab applies Tax_Rate_Active directly to Operating Income (no separately modeled Other Income/(Expense) line), this implied gap conflates any real effective-tax-rate change with unmodeled non-operating items. Rather than assert a pure tax-rate change that cannot be isolated from this data, Q2-Q4 FU carries forward the full bundled ~17.2% haircut as a single 'Tax/Other Drag' proxy -- flagged here as a bundled estimate, not a confirmed tax-rate revision. Col G is a live IF(), not a value baked in from the Base scenario.
A71: Q1 FORECAST UPDATE -- ANNUAL BUILD (helper: FY2026 Approved AOP annual revenue by segment, grossed up by the Q1 blended revenue-growth-surprise factor from row 65, column G -- used below to split Q2-Q4 FU quarterly revenue via the SAME FY2024-FY2025 seasonality weights the AOP used, row 12 cols C:E)
A72: Segment | B72: FY2026 Q1 Forecast Update Annual Revenue ($M) | C72: Basis
A73: iPhone: FY2026 Q1 FU Annual Revenue ($M) | B73: =B18*(1+$G$65) -> 222237.85 | C73: FY2026 Approved AOP annual revenue (B18, still scenario-live) x (1 + Q1 dollar beat as % of AOP Annual Total, row 65 col G, ~+2.4%). Same uplift ratio applied to every segment/Services -- see Driver Adjustment Log row 65 for why (no quarterly segment actual to split it by) and for why this uses the ANNUAL total as the base, not AOP Q1 (preserves Base/Bull/Bear cascade in the Q2-Q4 Forecast Update total).
A74: Mac: FY2026 Q1 FU Annual Revenue ($M) | B74: =B21*(1+$G$65) -> 36623.179 | C74: FY2026 Approved AOP annual revenue (B21, still scenario-live) x (1 + Q1 dollar beat as % of AOP Annual Total, row 65 col G, ~+2.4%). Same uplift ratio applied to every segment/Services -- see Driver Adjustment Log row 65 for why (no quarterly segment actual to split it by) and for why this uses the ANNUAL total as the base, not AOP Q1 (preserves Base/Bull/Bear cascade in the Q2-Q4 Forecast Update total).
A75: iPad: FY2026 Q1 FU Annual Revenue ($M) | B75: =B24*(1+$G$65) -> 29423.314 | C75: FY2026 Approved AOP annual revenue (B24, still scenario-live) x (1 + Q1 dollar beat as % of AOP Annual Total, row 65 col G, ~+2.4%). Same uplift ratio applied to every segment/Services -- see Driver Adjustment Log row 65 for why (no quarterly segment actual to split it by) and for why this uses the ANNUAL total as the base, not AOP Q1 (preserves Base/Bull/Bear cascade in the Q2-Q4 Forecast Update total).
A76: Wearables, Home and Accessories: FY2026 Q1 FU Annual Revenue ($M) | B76: =B27*(1+$G$65) -> 36546.348 | C76: FY2026 Approved AOP annual revenue (B27, still scenario-live) x (1 + Q1 dollar beat as % of AOP Annual Total, row 65 col G, ~+2.4%). Same uplift ratio applied to every segment/Services -- see Driver Adjustment Log row 65 for why (no quarterly segment actual to split it by) and for why this uses the ANNUAL total as the base, not AOP Q1 (preserves Base/Bull/Bear cascade in the Q2-Q4 Forecast Update total).
A77: Services: FY2026 Q1 FU Annual Revenue ($M) | B77: =B30*(1+$G$65) -> 126195.21 | C77: FY2026 Approved AOP annual revenue (B30, still scenario-live) x (1 + Q1 dollar beat as % of AOP Annual Total, row 65 col G, ~+2.4%). Same uplift ratio applied to every segment/Services -- see Driver Adjustment Log row 65 for why (no quarterly segment actual to split it by) and for why this uses the ANNUAL total as the base, not AOP Q1 (preserves Base/Bull/Bear cascade in the Q2-Q4 Forecast Update total).
A78: Total FY2026 Q1 FU Annual Revenue ($M) | B78: =B73+B74+B75+B76+B77 -> 451025.9
A80: Color legend (Q1 Forecast Update block): dark grey header = Q1 FY2026 Actual (mirrors historical col J); orange header/light orange cells = Q1 vs AOP Variance; green header/light green cells = Q1 Forecast Update formula output (still references Drivers Active named ranges); amber cells = a material Q1-actual driver adjustment overriding the corresponding Drivers Active assumption for Q2-Q4 (R&D%, SG&A%, Tax/Other%, and the annual-build revenue uplift); light grey Total column = Q1 Actual + Q2-Q4 FU. Materiality threshold: >3% relative variance (see row 61).
A82: Q3 REFORECAST -- third rolling-forecast vintage in the chain (FY2026 Approved AOP -> Q1 FY2026 Actual -> Q1 Forecast Update -> Q3 Reforecast). This is the CURRENT / LIVE forecast: Q1 and Q2 FY2026 are both real reported actuals now; only Q3-Q4 remain forecast. Materiality threshold: a Q2 Actual vs. Q1 Forecast Update's own Q2 driver variance is carried forward into the Q3-Q4 Reforecast columns (AB:AC) only where ABS(relative variance) > 3% -- the SAME threshold Task 13 established. Variances at or below 3% are treated as noise and the Q1 Forecast Update's own assumption is retained unchanged.
A84: DRIVER ADJUSTMENT LOG -- Q2 FY2026 Actual vs. Q1 Forecast Update's own Q2 assumption (each row below is a real formula referencing the IS tab's own Q2 Actual / Q1 FU Q2 cells; nothing here is hardcoded)
A85: Driver | B85: Q2 Actual | C85: Q1 FU Q2 Assumption | D85: Variance (abs / pp) | E85: Variance (% relative) | F85: Material? (>3% relative) | G85: Adjusted Value -> Q3-Q4 RF (live IF(), mirrors col F -- never a static/hardcoded choice) | H85: Rationale (plain language)
A86: Consolidated Net Sales (blended Units x ASP x FX x Mix growth proxy -- Historical Database still has no quarterly segment split, so the beat cannot be attributed to a specific product line; see Task 12/13 notes). NOTE: column G here is expressed as a % of the Q1 Forecast Update's ANNUAL total (col G = D/ABS(B78)), not of the Q1 FU Q2 quarter (col E) -- deliberately, for the SAME reason Task 13 established for its own revenue row: dividing by the Q1 FU Q2 quarter instead would algebraically cancel the scenario dependency out of the Q3-Q4 Reforecast entirely (Q1FUQ2(scenario) x [1 + (Actual-Q1FUQ2)/Q1FUQ2(scenario)] = Actual regardless of scenario). Verified this does NOT cancel here (see toggle test in the task report) before shipping -- learned directly from Task 13's post-review bug. | B86: =Y41 -> 111184 | C86: =T41 -> 104011.93 | D86: =B86-C86 -> 7172.0663 | E86: =D86/ABS(C86) -> 0.068954263 | F86: =IF(ABS(E86)>0.03,"Y -- carried forward","N -- immaterial, Q1 FU retained") -> Y -- carried forward | G86: =IF(ABS(E86)>0.03,D86/ABS(B78),0) -> 0.015901673 | H86: Q2 FY2026 actual net sales beat the Q1 Forecast Update's own Q2 assumption (col C) by roughly +$7.2B / +6.9% (col E) -- well above the 3% threshold, so col G evaluates its IF()'s TRUE branch: the beat is carried forward as a uniform annual-revenue uplift (~+1.6% of the Q1 FU Annual Total) applied to all five revenue streams' Q3-Q4 annual-build revenue (rows 94-98) -- i.e. the Q1 Forecast Update's own full-year revenue path is raised further by the Q2 dollar beat -- rather than reverting to the Q1 FU's unmodified Q3-Q4 path. If a future scenario toggle ever makes this variance immaterial (<=3%), col G's FALSE branch (0) means the annual build correctly falls back to the unmodified Q1 FU annual revenue (B94=B73*(1+0)=B73, and likewise for the other four segments).
A87: Blended Gross Margin % (vs. Q1 Forecast Update's own Q2 GM%, itself Products_GM_Active / Services_GM_Active mix) | B87: =Y45 -> 0.49270579 | C87: =T45 -> 0.47772143 | D87: =B87-C87 -> 0.014984352 | E87: =D87/ABS(C87) -> 0.031366296 | F87: =IF(ABS(E87)>0.03,"Y -- carried forward","N -- immaterial, Q1 FU retained") -> Y -- carried forward | G87: =IF(ABS(E87)>0.03,B87,C87) -> 0.49270579 | H87: Q2 actual GM% came in ~+1.5pp / +3.1% relative above the Q1 Forecast Update's own Q2 assumption -- just above the 3% materiality threshold, so col G's IF() evaluates to its TRUE branch (the actual GM%, col B). Carried forward: Q3-Q4 Reforecast gross margin is computed as Net Sales x col G (the adjusted blended GM%) instead of the Products_GM_Active / Services_GM_Active segment mix Task 12/13 used, reflecting the realized Q2 margin mix rather than the AOP's original assumption. This is a borderline call (3.1% vs. the 3.0% threshold) -- flagged explicitly since a reviewer applying a slightly different rounding convention could reasonably land on 'immaterial' instead; col G is a live IF() so it will automatically flip to col C (the Q1 FU assumption, itself Products_GM_Active/Services_GM_Active-based) if a scenario toggle ever pushes this variance to or below 3%.
A88: R&D as % of Net Sales (vs. Q1 Forecast Update's own Q2 R&D%, itself the pinned Q1-actual ratio) | B88: =Y47/Y41 -> 0.10270363 | C88: =T47/T41 -> 0.075732491 | D88: =B88-C88 -> 0.026971135 | E88: =D88/ABS(C88) -> 0.35613691 | F88: =IF(ABS(E88)>0.03,"Y -- carried forward","N -- immaterial, Q1 FU retained") -> Y -- carried forward | G88: =IF(ABS(E88)>0.03,B88,C88) -> 0.10270363 | H88: Q2 actual R&D ran at ~10.3% of net sales, well ABOVE both the Q1 Forecast Update's Q2 assumption (~7.6%, itself pinned to Q1's unusually low actual ratio) and even the original AOP's 8.3% Base assumption -- a +2.7pp / +35.6% relative variance, far above threshold, so col G's IF() evaluates to its TRUE branch (the Q2 actual ratio, col B). This looks like a reversion: Q1's R&D ratio was unusually depressed (likely spend timing/phasing), and Q2 shows R&D spend catching back up and then some. Carried forward: Q3-Q4 Reforecast R&D uses the Q2 actual ratio (~10.3%) instead of continuing the Q1 Forecast Update's lower ~7.6%. Col G is a live IF() -- if a scenario toggle ever pushed this variance within 3%, col G would automatically fall back to col C (the Q1 FU's own Q2 assumption).
A89: SG&A as % of Net Sales (vs. Q1 Forecast Update's own Q2 SG&A%, itself the pinned Q1-actual ratio) | B89: =Y48/Y41 -> 0.067248885 | C89: =T48/T41 -> 0.052116086 | D89: =B89-C89 -> 0.015132799 | E89: =D89/ABS(C89) -> 0.29036715 | F89: =IF(ABS(E89)>0.03,"Y -- carried forward","N -- immaterial, Q1 FU retained") -> Y -- carried forward | G89: =IF(ABS(E89)>0.03,B89,C89) -> 0.067248885 | H89: Q2 actual SG&A ran at ~6.7% of net sales vs. the Q1 Forecast Update's Q2 assumption of ~5.2% (itself pinned to Q1's unusually low actual ratio) -- a +1.5pp / +29.0% relative variance, well above threshold, so col G's IF() evaluates to its TRUE branch (the Q2 actual ratio, col B). Same reversion pattern as R&D above: Q1's SG&A ratio was unusually depressed, and Q2 shows a partial catch-up (still below the original AOP's 6.6% Base assumption, but clearly above the Q1-anchored 5.2%). Carried forward: Q3-Q4 Reforecast SG&A uses the Q2 actual ratio (~6.7%) instead of continuing the Q1 Forecast Update's lower ~5.2%. Col G is a live IF() re-testing col E, not a value baked in from the Base scenario.
A90: Effective Tax / Other haircut rate, 1-(NI/OpInc) (vs. Q1 Forecast Update's own Q2 assumption; bundles the true effective tax rate with Task 12's unmodeled Other Income/(Expense) simplification -- see Task 12 Concern #1 and Task 13 Concern #2) | B90: =1-Y53/Y49 -> 0.17575589 | C90: =1-T53/T49 -> 0.17216629 | D90: =B90-C90 -> 0.0035896004 | E90: =D90/ABS(C90) -> 0.020849613 | F90: =IF(ABS(E90)>0.03,"Y -- carried forward","N -- immaterial, Q1 FU retained") -> N -- immaterial, Q1 FU retained | G90: =IF(ABS(E90)>0.03,B90,C90) -> 0.17216629 | H90: Q2 implied OpInc-to-NI haircut was ~17.6% vs. the Q1 Forecast Update's own Q2 assumption of ~17.2% -- a +0.4pp / +2.1% relative variance, BELOW the 3% threshold, so col G's IF() evaluates to its FALSE branch (the Q1 FU's own assumption, col C) -- unchanged. Q3-Q4 Reforecast continues to apply the same bundled ~17.2% Tax/Other haircut rate the Q1 Forecast Update carried forward from Q1 actual; this is the one driver in this task's log that does NOT move, mirroring Task 13's GM% row (which was also the one immaterial driver in that log). Col G is a live IF(), not a value baked in from the Base scenario -- if a scenario toggle ever pushed this variance above 3%, col G would automatically switch to col B.
A92: Q3 REFORECAST -- ANNUAL BUILD (helper: Q1 Forecast Update's own annual revenue by segment, rows 73-77, grossed up by the Q2 blended revenue-growth-surprise factor from row 86, column G -- used below to split Q3-Q4 Reforecast quarterly revenue via the SAME FY2024-FY2025 seasonality weights the AOP and Q1 Forecast Update both used, row 12 cols D:E)
A93: Segment | B93: FY2026 Q3 Reforecast Annual Revenue ($M) | C93: Basis
A94: iPhone: FY2026 Q3 RF Annual Revenue ($M) | B94: =B73*(1+$G$86) -> 225771.8 | C94: Q1 Forecast Update annual revenue (B73, still scenario-live) x (1 + Q2 dollar beat as % of Q1 FU Annual Total, row 86 col G, ~+1.6%). Same uplift ratio applied to every segment/Services -- see Driver Adjustment Log row 86 for why (no quarterly segment actual to split it by) and for why this uses the Q1 FU ANNUAL total as the base, not the Q1 FU Q2 quarter (preserves Base/Bull/Bear cascade in the Q3-Q4 Reforecast total).
A95: Mac: FY2026 Q3 RF Annual Revenue ($M) | B95: =B74*(1+$G$86) -> 37205.549 | C95: Q1 Forecast Update annual revenue (B74, still scenario-live) x (1 + Q2 dollar beat as % of Q1 FU Annual Total, row 86 col G, ~+1.6%). Same uplift ratio applied to every segment/Services -- see Driver Adjustment Log row 86 for why (no quarterly segment actual to split it by) and for why this uses the Q1 FU ANNUAL total as the base, not the Q1 FU Q2 quarter (preserves Base/Bull/Bear cascade in the Q3-Q4 Reforecast total).
A96: iPad: FY2026 Q3 RF Annual Revenue ($M) | B96: =B75*(1+$G$86) -> 29891.194 | C96: Q1 Forecast Update annual revenue (B75, still scenario-live) x (1 + Q2 dollar beat as % of Q1 FU Annual Total, row 86 col G, ~+1.6%). Same uplift ratio applied to every segment/Services -- see Driver Adjustment Log row 86 for why (no quarterly segment actual to split it by) and for why this uses the Q1 FU ANNUAL total as the base, not the Q1 FU Q2 quarter (preserves Base/Bull/Bear cascade in the Q3-Q4 Reforecast total).
A97: Wearables, Home and Accessories: FY2026 Q3 RF Annual Revenue ($M) | B97: =B76*(1+$G$86) -> 37127.496 | C97: Q1 Forecast Update annual revenue (B76, still scenario-live) x (1 + Q2 dollar beat as % of Q1 FU Annual Total, row 86 col G, ~+1.6%). Same uplift ratio applied to every segment/Services -- see Driver Adjustment Log row 86 for why (no quarterly segment actual to split it by) and for why this uses the Q1 FU ANNUAL total as the base, not the Q1 FU Q2 quarter (preserves Base/Bull/Bear cascade in the Q3-Q4 Reforecast total).
A98: Services: FY2026 Q3 RF Annual Revenue ($M) | B98: =B77*(1+$G$86) -> 128201.93 | C98: Q1 Forecast Update annual revenue (B77, still scenario-live) x (1 + Q2 dollar beat as % of Q1 FU Annual Total, row 86 col G, ~+1.6%). Same uplift ratio applied to every segment/Services -- see Driver Adjustment Log row 86 for why (no quarterly segment actual to split it by) and for why this uses the Q1 FU ANNUAL total as the base, not the Q1 FU Q2 quarter (preserves Base/Bull/Bear cascade in the Q3-Q4 Reforecast total).
A99: Total FY2026 Q3 RF Annual Revenue ($M) | B99: =B94+B95+B96+B97+B98 -> 458197.97
A101: Color legend (Q3 Reforecast block): dark grey header = Q2 FY2026 Actual (mirrors historical col K); gold header/light gold cells = Q2 vs Q1 FU Variance; teal header/light teal cells = Q3 Reforecast formula output (still references Drivers Active named ranges via the inherited Q1 FU Annual Build); amber cells = a material Q2-actual driver adjustment overriding the Q1 Forecast Update's own Q2 assumption for Q3-Q4 (GM%, R&D%, SG&A%, Tax/Other%, and the annual-build revenue uplift); light grey Total column = Q1 Actual + Q2 Actual + Q3-Q4 Reforecast. Materiality threshold: >3% relative variance (see row 82) -- same threshold Task 13 established. This vintage (Q3 Reforecast) is the CURRENT / LIVE forecast in the project's rolling-forecast story.
A103: FY2027 AOP -- fifth and final vintage in the chain (FY2026 Approved AOP -> Q1 FY2026 Actual -> Q1 Forecast Update -> Q3 Reforecast -> FY2027 AOP). This is next year's Annual Operating Plan, built the same structural way Task 12's FY2026 AOP was (Units x ASP x FX x Mix / Installed Base x ARPU via the Drivers tab's Active named ranges, split into quarters via the same seasonality weights), but anchored on the Q3 Reforecast's Q4 FY2026 EXIT run-rate (row 107-121 below, de-seasonalized -- col AC / Q4 weight, NOT a naive x4) instead of a FY2025 actual anchor -- so the plan reflects the Q2-actual-adjusted trajectory the business is exiting FY2026 on, not the FY26 Total that blends in the already-reported Q1/Q2 actuals.
A105: FY2027 AOP -- ANNUAL BUILD (helper: FY2026 Exit Run-Rate Annualized Revenue -- Q3 Reforecast's Q4 FY2026 quarterly revenue, col AC, de-seasonalized by dividing by the Q4 weight (row 12 col E) -- then grown one more year via Drivers Active Units/ASP/InstalledBase/ARPU/FX/Mix, exactly mirroring Task 12's FY2025-anchor AOP build)
A106: Segment | B106: Value ($M or units, see row label) | C106: Basis
A107: iPhone: FY2026 Exit Run-Rate Annualized Revenue ($M) | B107: =AC35/$E$12 -> 225771.8 | C107: Q3 Reforecast's Q4 FY2026 quarterly revenue (AC35, still scenario-live and still carrying Task 14's Q2-actual driver adjustments) divided by the Q4 seasonality weight (row 12 col E, ~24.4%) to de-seasonalize it into an annualized run-rate. A naive x4 was tried first and rejected on code review: it implicitly assumes every quarter is an equal 25% share of the year, which this model's own measured weights (row 12: Q1 30.2%, Q2 23.1%, Q3 22.3%, Q4 24.4%) show is false -- x4 mechanically discounted the anchor by ~2.2% for a reason unrelated to business momentum. Dividing by the Q4 weight removes that artifact while still anchoring on Q4 specifically (not a blend of the Q3 Reforecast's already-reported Q1/Q2 actuals): it recovers the Q3 Reforecast's own forward-looking Annual Build total (row 99), the pace implied by extrapolating the current Q2-actual-adjusted trajectory across the full year -- a genuinely different, and lower, number than the Q3 Reforecast's blended FY26 Total (col AD).
A108: iPhone: Implied FY2026 Exit-Run-Rate Units (M) | B108: =B107/iPhone_ASP_Active -> 245.93878 | C108: Exit run-rate revenue (row above) / Drivers!iPhone_ASP_Active -- the CURRENT Active ASP/ARPU (not the Historical Reference ASP Task 12 used for its FY2025 anchor), since the exit run-rate revenue already embeds a full year of Active-scenario ASP/FX/Mix via the AOP -> Q1 FU -> Q3 RF chain.
A109: iPhone: FY2027 AOP Annual Revenue ($M) | B109: =B108*(1+iPhone_Units_Growth_Active)*iPhone_ASP_Active*(1+FX_Impact_Active)*(1+Mix_Impact_Active) -> 229158.38 | C109: Implied exit-run-rate units/base x (1+iPhone_Units_Growth_Active) x iPhone_ASP_Active x (1+FX_Impact_Active) x (1+Mix_Impact_Active) -- one more year of Drivers Active growth applied on top of the FY2026 exit run-rate, same formula shape as Task 12's FY2025-anchor AOP build. FX_Impact_Active/Mix_Impact_Active are therefore applied for a second consecutive year (compounding with whatever FX/Mix was already embedded in the FY2026 build) -- immaterial at Base (both 0%), a real, documented compounding effect under Bull/Bear, since the Drivers tab has only one non-year-specific Active column shared by every downstream tab.
A110: Mac: FY2026 Exit Run-Rate Annualized Revenue ($M) | B110: =AC36/$E$12 -> 37205.549 | C110: Q3 Reforecast's Q4 FY2026 quarterly revenue (AC36, still scenario-live and still carrying Task 14's Q2-actual driver adjustments) divided by the Q4 seasonality weight (row 12 col E, ~24.4%) to de-seasonalize it into an annualized run-rate. A naive x4 was tried first and rejected on code review: it implicitly assumes every quarter is an equal 25% share of the year, which this model's own measured weights (row 12: Q1 30.2%, Q2 23.1%, Q3 22.3%, Q4 24.4%) show is false -- x4 mechanically discounted the anchor by ~2.2% for a reason unrelated to business momentum. Dividing by the Q4 weight removes that artifact while still anchoring on Q4 specifically (not a blend of the Q3 Reforecast's already-reported Q1/Q2 actuals): it recovers the Q3 Reforecast's own forward-looking Annual Build total (row 99), the pace implied by extrapolating the current Q2-actual-adjusted trajectory across the full year -- a genuinely different, and lower, number than the Q3 Reforecast's blended FY26 Total (col AD).
A111: Mac: Implied FY2026 Exit-Run-Rate Units (M) | B111: =B110/Mac_ASP_Active -> 26.054306 | C111: Exit run-rate revenue (row above) / Drivers!Mac_ASP_Active -- the CURRENT Active ASP/ARPU (not the Historical Reference ASP Task 12 used for its FY2025 anchor), since the exit run-rate revenue already embeds a full year of Active-scenario ASP/FX/Mix via the AOP -> Q1 FU -> Q3 RF chain.
A112: Mac: FY2027 AOP Annual Revenue ($M) | B112: =B111*(1+Mac_Units_Growth_Active)*Mac_ASP_Active*(1+FX_Impact_Active)*(1+Mix_Impact_Active) -> 38693.771 | C112: Implied exit-run-rate units/base x (1+Mac_Units_Growth_Active) x Mac_ASP_Active x (1+FX_Impact_Active) x (1+Mix_Impact_Active) -- one more year of Drivers Active growth applied on top of the FY2026 exit run-rate, same formula shape as Task 12's FY2025-anchor AOP build. FX_Impact_Active/Mix_Impact_Active are therefore applied for a second consecutive year (compounding with whatever FX/Mix was already embedded in the FY2026 build) -- immaterial at Base (both 0%), a real, documented compounding effect under Bull/Bear, since the Drivers tab has only one non-year-specific Active column shared by every downstream tab.
A113: iPad: FY2026 Exit Run-Rate Annualized Revenue ($M) | B113: =AC37/$E$12 -> 29891.194 | C113: Q3 Reforecast's Q4 FY2026 quarterly revenue (AC37, still scenario-live and still carrying Task 14's Q2-actual driver adjustments) divided by the Q4 seasonality weight (row 12 col E, ~24.4%) to de-seasonalize it into an annualized run-rate. A naive x4 was tried first and rejected on code review: it implicitly assumes every quarter is an equal 25% share of the year, which this model's own measured weights (row 12: Q1 30.2%, Q2 23.1%, Q3 22.3%, Q4 24.4%) show is false -- x4 mechanically discounted the anchor by ~2.2% for a reason unrelated to business momentum. Dividing by the Q4 weight removes that artifact while still anchoring on Q4 specifically (not a blend of the Q3 Reforecast's already-reported Q1/Q2 actuals): it recovers the Q3 Reforecast's own forward-looking Annual Build total (row 99), the pace implied by extrapolating the current Q2-actual-adjusted trajectory across the full year -- a genuinely different, and lower, number than the Q3 Reforecast's blended FY26 Total (col AD).
A114: iPad: Implied FY2026 Exit-Run-Rate Units (M) | B114: =B113/iPad_ASP_Active -> 61.998847 | C114: Exit run-rate revenue (row above) / Drivers!iPad_ASP_Active -- the CURRENT Active ASP/ARPU (not the Historical Reference ASP Task 12 used for its FY2025 anchor), since the exit run-rate revenue already embeds a full year of Active-scenario ASP/FX/Mix via the AOP -> Q1 FU -> Q3 RF chain.
A115: iPad: FY2027 AOP Annual Revenue ($M) | B115: =B114*(1+iPad_Units_Growth_Active)*iPad_ASP_Active*(1+FX_Impact_Active)*(1+Mix_Impact_Active) -> 30190.106 | C115: Implied exit-run-rate units/base x (1+iPad_Units_Growth_Active) x iPad_ASP_Active x (1+FX_Impact_Active) x (1+Mix_Impact_Active) -- one more year of Drivers Active growth applied on top of the FY2026 exit run-rate, same formula shape as Task 12's FY2025-anchor AOP build. FX_Impact_Active/Mix_Impact_Active are therefore applied for a second consecutive year (compounding with whatever FX/Mix was already embedded in the FY2026 build) -- immaterial at Base (both 0%), a real, documented compounding effect under Bull/Bear, since the Drivers tab has only one non-year-specific Active column shared by every downstream tab.
A116: Wearables, Home and Accessories: FY2026 Exit Run-Rate Annualized Revenue ($M) | B116: =AC38/$E$12 -> 37127.496 | C116: Q3 Reforecast's Q4 FY2026 quarterly revenue (AC38, still scenario-live and still carrying Task 14's Q2-actual driver adjustments) divided by the Q4 seasonality weight (row 12 col E, ~24.4%) to de-seasonalize it into an annualized run-rate. A naive x4 was tried first and rejected on code review: it implicitly assumes every quarter is an equal 25% share of the year, which this model's own measured weights (row 12: Q1 30.2%, Q2 23.1%, Q3 22.3%, Q4 24.4%) show is false -- x4 mechanically discounted the anchor by ~2.2% for a reason unrelated to business momentum. Dividing by the Q4 weight removes that artifact while still anchoring on Q4 specifically (not a blend of the Q3 Reforecast's already-reported Q1/Q2 actuals): it recovers the Q3 Reforecast's own forward-looking Annual Build total (row 99), the pace implied by extrapolating the current Q2-actual-adjusted trajectory across the full year -- a genuinely different, and lower, number than the Q3 Reforecast's blended FY26 Total (col AD).
A117: Wearables, Home and Accessories: Implied FY2026 Exit-Run-Rate Units (M) | B117: =B116/Wearables_Home_and_Accessories_ASP_Active -> 222.78726 | C117: Exit run-rate revenue (row above) / Drivers!Wearables_Home_and_Accessories_ASP_Active -- the CURRENT Active ASP/ARPU (not the Historical Reference ASP Task 12 used for its FY2025 anchor), since the exit run-rate revenue already embeds a full year of Active-scenario ASP/FX/Mix via the AOP -> Q1 FU -> Q3 RF chain.
A118: Wearables, Home and Accessories: FY2027 AOP Annual Revenue ($M) | B118: =B117*(1+Wearables_Home_and_Accessories_Units_Growth_Active)*Wearables_Home_and_Accessories_ASP_Active*(1+FX_Impact_Active)*(1+Mix_Impact_Active) -> 36756.221 | C118: Implied exit-run-rate units/base x (1+Wearables_Home_and_Accessories_Units_Growth_Active) x Wearables_Home_and_Accessories_ASP_Active x (1+FX_Impact_Active) x (1+Mix_Impact_Active) -- one more year of Drivers Active growth applied on top of the FY2026 exit run-rate, same formula shape as Task 12's FY2025-anchor AOP build. FX_Impact_Active/Mix_Impact_Active are therefore applied for a second consecutive year (compounding with whatever FX/Mix was already embedded in the FY2026 build) -- immaterial at Base (both 0%), a real, documented compounding effect under Bull/Bear, since the Drivers tab has only one non-year-specific Active column shared by every downstream tab.
A119: Services: FY2026 Exit Run-Rate Annualized Revenue ($M) | B119: =AC40/$E$12 -> 128201.93 | C119: Q3 Reforecast's Q4 FY2026 quarterly revenue (AC40, still scenario-live and still carrying Task 14's Q2-actual driver adjustments) divided by the Q4 seasonality weight (row 12 col E, ~24.4%) to de-seasonalize it into an annualized run-rate. A naive x4 was tried first and rejected on code review: it implicitly assumes every quarter is an equal 25% share of the year, which this model's own measured weights (row 12: Q1 30.2%, Q2 23.1%, Q3 22.3%, Q4 24.4%) show is false -- x4 mechanically discounted the anchor by ~2.2% for a reason unrelated to business momentum. Dividing by the Q4 weight removes that artifact while still anchoring on Q4 specifically (not a blend of the Q3 Reforecast's already-reported Q1/Q2 actuals): it recovers the Q3 Reforecast's own forward-looking Annual Build total (row 99), the pace implied by extrapolating the current Q2-actual-adjusted trajectory across the full year -- a genuinely different, and lower, number than the Q3 Reforecast's blended FY26 Total (col AD).
...

Sheet BS
A1: Apple Inc. -- Driver-Based Rolling Forecast Model: BALANCE SHEET (BS)
A2: Historical actuals: the Historical Database's Quarterly tab discloses only Cash, Accounts receivable, Inventories and Accounts payable at discrete-quarter grain for all 10 historical quarters (B:K) -- shown as real literal inputs. Columns E (FY24 Q4) and I (FY25 Q4) are fiscal year-ends, so the Historical Database's Annual tab supplies a COMPLETE real 10-K balance sheet for those two columns specifically; every other historical column shows 'n/a' for line items not disclosed at quarterly grain -- never fabricated. The Q1/Q2 FY2026 Actual overlay columns (Q, Y) are treated identically: real Cash/AR/Inventory/AP only, 'n/a' elsewhere (Apple does not disclose quarterly PP&E/debt/equity detail). WHY FORECAST CASH DOES NOT RE-ANCHOR TO THESE REAL OVERLAY COLUMNS (design choice, not an oversight): a modeled 'flash close' that tried to chain the NEXT forecast quarter's PP&E/debt/Retained-Earnings roll-forward through Q or Y is mathematically impossible to balance without a hidden plug -- Q/Y carry REAL Cash/AR/Inventory/AP, but Apple does not disclose quarterly PP&E, debt, or equity detail, so any modeled PP&E/debt/equity value placed at that same column would not reconcile against the real cash/working-capital figures already sitting there (the residual would be exactly 'what cash would have had to be, had it been computed instead of real' -- a disguised plug). FIX ADOPTED: every downstream forecast column's PP&E/Term-debt/Retained-Earnings/CF-Begin-Cash roll-forward skips Q and Y and chains instead from the last fully-MODELED column of a prior vintage (T's own Q2 roll-forward prior is L, not Q; AB's own Q3 roll-forward prior is T, not Y -- see PRIOR_COL in scripts/build_bs_cf_tabs.py for the complete map) -- proved by induction to keep the balance check at exactly $0 for every scenario. CONSEQUENCE, STATED EXPLICITLY: because forecast cash rolls forward from prior MODELED cash rather than resetting to the real disclosed balance each quarter, modeled cash increasingly diverges from real reported cash as actuals come in -- e.g. in this delivered file, the live Q3 Reforecast vintage's FY2026-exit modeled cash (col AD, row 9) is ~$29.8B vs. the real FY2026 Q2 reported cash of ~$45.6B sitting two columns to the left in this same row (col K) -- a ~$15.8B / ~35% gap. This is a disclosed methodological limitation of the 'flash close' hybrid design (real revenue actuals feed the IS tab; cash/PP&E/debt/equity remain fully modeled because Apple does not disclose quarterly detail for them), not a formula error -- the balance check (row 39) still holds at $0 on every column with a full balance sheet.
A3: Forecast columns: AR/Inventory/AP are driven by Drivers!DSO_Active/DIO_Active/DPO_Active (never a rollforward plug); PP&E, non-current Term Debt, and Retained Earnings are genuine roll-forwards; Cash is pulled from the CF tab's own computed ending-cash balance (never independently plugged). Every other BS line item is held FLAT at the FY25 Q4 anchor (col I) -- documented per-item in the block starting row 41 below. 'Total' columns (P/W/AD/AJ) mirror that vintage's own Q4 column -- a balance sheet is a point-in-time stock, not a summable flow like the IS tab's Totals.
B5: =IS!B5 -> HISTORICAL ACTUALS -- Source: 02 Historical Financial Database.xlsx, Quarterly tab (real values, not re-derived) | L5: =IS!L5 -> FY2026 Approved AOP -- first rolling-forecast vintage (Drivers tab Active column; Base/Bull/Bear scenario switch at Drivers!B6) | Q5: =IS!Q5 -> Q1 FY2026 ACTUAL vs. APPROVED AOP VARIANCE -- Actual = mirror of historical col J (real data); Variance = Actual - Approved AOP Q1 (col L) | T5: =IS!T5 -> Q1 FORECAST UPDATE -- second rolling-forecast vintage (Q1 FY2026 actual reported; Q2-Q4 FY2026 reforecast using the Drivers tab Active column PLUS the Q1-actual driver adjustments in rows 63-78 below, in place of reverting to the original AOP assumptions where the Q1 variance was material) | Y5: =IS!Y5 -> Q2 FY2026 ACTUAL vs. Q1 FORECAST UPDATE VARIANCE -- Actual = mirror of historical col K (real data); Variance = Actual - Q1 Forecast Update's own Q2 column (T) | AB5: =IS!AB5 -> Q3 REFORECAST -- third rolling-forecast vintage, and the CURRENT / LIVE forecast in this project's story (Q1 and Q2 FY2026 are now both real actuals; Q3-Q4 reforecast using the Q1 Forecast Update's own Annual Build PLUS the Q2-actual driver adjustments in rows 84-99 below, in place of reverting to the Q1 Forecast Update's own assumptions where the Q2 variance was material) | AF5: =IS!AF5 -> FY2027 AOP -- fifth and FINAL rolling-forecast vintage: next year's Annual Operating Plan, built off the Q3 Reforecast's Q4 FY2026 EXIT run-rate (col AC de-seasonalized by dividing by the Q4 weight, row 12 col E -- NOT a naive x4, and NOT the Q3 Reforecast's FY26 Total), grown one more year via the Drivers tab's Active assumptions (Base/Bull/Bear switch at Drivers!B6). Fresh forward plan -- no Driver Adjustment Log (see row 125).
A6: Line Item | B6: =IS!B6 -> FY24 Q1 | C6: =IS!C6 -> FY24 Q2 | D6: =IS!D6 -> FY24 Q3 | E6: =IS!E6 -> FY24 Q4 | F6: =IS!F6 -> FY25 Q1 | G6: =IS!G6 -> FY25 Q2 | H6: =IS!H6 -> FY25 Q3 | I6: =IS!I6 -> FY25 Q4 | ... Q6: =IS!Q6 -> Q1 FY2026 Actual | T6: =IS!T6 -> Q2 -- Q1 Forecast Update | U6: =IS!U6 -> Q3 -- Q1 Forecast Update | V6: =IS!V6 -> Q4 -- Q1 Forecast Update | W6: =IS!W6 -> FY26 Total -- Q1 Forecast Update | Y6: =IS!Y6 -> Q2 FY2026 Actual | AB6: =IS!AB6 -> Q3 -- Q3 Reforecast | AC6: =IS!AC6 -> Q4 -- Q3 Reforecast | AD6: =IS!AD6 -> FY26 Total -- Q3 Reforecast | AF6: =IS!AF6 -> Q1 -- FY2027 AOP | AG6: =IS!AG6 -> Q2 -- FY2027 AOP | AH6: =IS!AH6 -> Q3 -- FY2027 AOP | AI6: =IS!AI6 -> Q4 -- FY2027 AOP | AJ6: =IS!AJ6 -> FY27 Total -- FY2027 AOP
A8: BALANCE SHEET (quarter-end / period-end)
A9: Cash and cash equivalents ($M) | B9: 40760 | C9: 32695 | D9: 25565 | E9: 29943 | F9: 30299 | G9: 28162 | H9: 36269 | I9: 35934 | J9: 45317 | K9: 45572 | L9: =CF!L30 -> 34880.118 | M9: =CF!M30 -> 32705.437 | N9: =CF!N30 -> 31259.747 | O9: =CF!O30 -> 29998.905 | P9: =O9 -> 29998.905 | Q9: =J9 -> 45317 | T9: =CF!T30 -> 32660.716 | U9: =CF!U30 -> 31112.184 | V9: =CF!V30 -> 29746.323 | W9: =V9 -> 29746.323 | Y9: =K9 -> 45572 | AB9: =CF!AB30 -> 31063.864 | AC9: =CF!AC30 -> 29784.548 | AD9: =AC9 -> 29784.548 | AF9: =CF!AF30 -> 28642.83 | AG9: =CF!AG30 -> 26306.023 | AH9: =CF!AH30 -> 24736.353 | AI9: =CF!AI30 -> 23355.631 | AJ9: =AI9 -> 23355.631
A10: Marketable securities - current ($M) | B10: n/a | C10: n/a | D10: n/a | E10: 35228 | F10: n/a | G10: n/a | H10: n/a | I10: 18763 | J10: n/a | K10: n/a | L10: =$I$10 -> 18763 | M10: =$I$10 -> 18763 | N10: =$I$10 -> 18763 | O10: =$I$10 -> 18763 | P10: =O10 -> 18763 | Q10: n/a | T10: =$I$10 -> 18763 | U10: =$I$10 -> 18763 | V10: =$I$10 -> 18763 | W10: =V10 -> 18763 | Y10: n/a | AB10: =$I$10 -> 18763 | AC10: =$I$10 -> 18763 | AD10: =AC10 -> 18763 | AF10: =$I$10 -> 18763 | AG10: =$I$10 -> 18763 | AH10: =$I$10 -> 18763 | AI10: =$I$10 -> 18763 | AJ10: =AI10 -> 18763
A11: Accounts receivable, net ($M) | B11: 23194 | C11: 21837 | D11: 22795 | E11: 33410 | F11: 29639 | G11: 26136 | H11: 27557 | I11: 39777 | J11: 39921 | K11: 30339 | L11: =DSO_Active*(IS!L41/90) -> 48801.218 | M11: =DSO_Active*(IS!M41/90) -> 37236.174 | N11: =DSO_Active*(IS!N41/90) -> 35952.169 | O11: =DSO_Active*(IS!O41/90) -> 39477.289 | P11: =O11 -> 39477.289 | Q11: =J11 -> 39921 | T11: =DSO_Active*(IS!T41/90) -> 38137.709 | U11: =DSO_Active*(IS!U41/90) -> 36822.616 | V11: =DSO_Active*(IS!V41/90) -> 40433.083 | W11: =V11 -> 40433.083 | Y11: =K11 -> 30339 | AB11: =DSO_Active*(IS!AB41/90) -> 37408.157 | AC11: =DSO_Active*(IS!AC41/90) -> 41076.037 | AD11: =AC11 -> 41076.037 | AF11: =DSO_Active*(IS!AF41/90) -> 52375.324 | AG11: =DSO_Active*(IS!AG41/90) -> 39963.28 | AH11: =DSO_Active*(IS!AH41/90) -> 38585.236 | AI11: =DSO_Active*(IS!AI41/90) -> 42368.529 | AJ11: =AI11 -> 42368.529
A12: Vendor non-trade receivables ($M) | B12: n/a | C12: n/a | D12: n/a | E12: 32833 | F12: n/a | G12: n/a | H12: n/a | I12: 33180 | J12: n/a | K12: n/a | L12: =$I$12 -> 33180 | M12: =$I$12 -> 33180 | N12: =$I$12 -> 33180 | O12: =$I$12 -> 33180 | P12: =O12 -> 33180 | Q12: n/a | T12: =$I$12 -> 33180 | U12: =$I$12 -> 33180 | V12: =$I$12 -> 33180 | W12: =V12 -> 33180 | Y12: n/a | AB12: =$I$12 -> 33180 | AC12: =$I$12 -> 33180 | AD12: =AC12 -> 33180 | AF12: =$I$12 -> 33180 | AG12: =$I$12 -> 33180 | AH12: =$I$12 -> 33180 | AI12: =$I$12 -> 33180 | AJ12: =AI12 -> 33180
A13: Inventories ($M) | B13: 6511 | C13: 6232 | D13: 6165 | E13: 7286 | F13: 6911 | G13: 6269 | H13: 5925 | I13: 5718 | J13: 5875 | K13: 6747 | L13: =DIO_Active*(IS!L43/90) -> 7723.5848 | M13: =DIO_Active*(IS!M43/90) -> 5893.229 | N13: =DIO_Active*(IS!N43/90) -> 5690.0143 | O13: =DIO_Active*(IS!O43/90) -> 6247.9217 | P13: =O13 -> 6247.9217 | Q13: =J13 -> 5875 | T13: =DIO_Active*(IS!T43/90) -> 6035.9115 | U13: =DIO_Active*(IS!U43/90) -> 5827.7767 | V13: =DIO_Active*(IS!V43/90) -> 6399.1918 | W13: =V13 -> 6399.1918 | Y13: =K13 -> 6747 | AB13: =DIO_Active*(IS!AB43/90) -> 5750.5884 | AC13: =DIO_Active*(IS!AC43/90) -> 6314.4351 | AD13: =AC13 -> 6314.4351 | AF13: =DIO_Active*(IS!AF43/90) -> 8217.0863 | AG13: =DIO_Active*(IS!AG43/90) -> 6269.7792 | AH13: =DIO_Active*(IS!AH43/90) -> 6053.58 | AI13: =DIO_Active*(IS!AI43/90) -> 6647.1351 | AJ13: =AI13 -> 6647.1351
A14: Other current assets ($M) | B14: n/a | C14: n/a | D14: n/a | E14: 14287 | F14: n/a | G14: n/a | H14: n/a | I14: 14585 | J14: n/a | K14: n/a | L14: =$I$14 -> 14585 | M14: =$I$14 -> 14585 | N14: =$I$14 -> 14585 | O14: =$I$14 -> 14585 | P14: =O14 -> 14585 | Q14: n/a | T14: =$I$14 -> 14585 | U14: =$I$14 -> 14585 | V14: =$I$14 -> 14585 | W14: =V14 -> 14585 | Y14: n/a | AB14: =$I$14 -> 14585 | AC14: =$I$14 -> 14585 | AD14: =AC14 -> 14585 | AF14: =$I$14 -> 14585 | AG14: =$I$14 -> 14585 | AH14: =$I$14 -> 14585 | AI14: =$I$14 -> 14585 | AJ14: =AI14 -> 14585
A15: Total current assets ($M) | B15: n/a | C15: n/a | D15: n/a | E15: =SUM(E9:E14) -> 152987 | F15: n/a | G15: n/a | H15: n/a | I15: =SUM(I9:I14) -> 147957 | J15: n/a | K15: n/a | L15: =SUM(L9:L14) -> 157932.92 | M15: =SUM(M9:M14) -> 142362.84 | N15: =SUM(N9:N14) -> 139429.93 | O15: =SUM(O9:O14) -> 142252.11 | P15: =O15 -> 142252.11 | Q15: n/a | T15: =SUM(T9:T14) -> 143362.34 | U15: =SUM(U9:U14) -> 140290.58 | V15: =SUM(V9:V14) -> 143106.6 | W15: =V15 -> 143106.6 | Y15: n/a | AB15: =SUM(AB9:AB14) -> 140750.61 | AC15: =SUM(AC9:AC14) -> 143703.02 | AD15: =AC15 -> 143703.02 | AF15: =SUM(AF9:AF14) -> 155763.24 | AG15: =SUM(AG9:AG14) -> 139067.08 | AH15: =SUM(AH9:AH14) -> 135903.17 | AI15: =SUM(AI9:AI14) -> 138899.29 | AJ15: =AI15 -> 138899.29
A16: Marketable securities - non-current ($M) | B16: n/a | C16: n/a | D16: n/a | E16: 91479 | F16: n/a | G16: n/a | H16: n/a | I16: 77723 | J16: n/a | K16: n/a | L16: =$I$16 -> 77723 | M16: =$I$16 -> 77723 | N16: =$I$16 -> 77723 | O16: =$I$16 -> 77723 | P16: =O16 -> 77723 | Q16: n/a | T16: =$I$16 -> 77723 | U16: =$I$16 -> 77723 | V16: =$I$16 -> 77723 | W16: =V16 -> 77723 | Y16: n/a | AB16: =$I$16 -> 77723 | AC16: =$I$16 -> 77723 | AD16: =AC16 -> 77723 | AF16: =$I$16 -> 77723 | AG16: =$I$16 -> 77723 | AH16: =$I$16 -> 77723 | AI16: =$I$16 -> 77723 | AJ16: =AI16 -> 77723
A17: Property, plant and equipment, net ($M) | B17: n/a | C17: n/a | D17: n/a | E17: 45680 | F17: n/a | G17: n/a | H17: n/a | I17: 49834 | J17: n/a | K17: n/a | L17: =I17-CF!L22-CF!L16 -> 49928.857 | M17: =L17-CF!M22-CF!M16 -> 50001.235 | N17: =M17-CF!N22-CF!N16 -> 50071.116 | O17: =N17-CF!O22-CF!O16 -> 50147.85 | P17: =O17 -> 50147.85 | Q17: n/a | T17: =L17-CF!T22-CF!T16 -> 50002.987 | U17: =T17-CF!U22-CF!U16 -> 50074.561 | V17: =U17-CF!V22-CF!V16 -> 50153.152 | W17: =V17 -> 50153.152 | Y17: n/a | AB17: =T17-CF!AB22-CF!AB16 -> 50075.699 | AC17: =AB17-CF!AC22-CF!AC16 -> 50155.54 | AD17: =AC17 -> 50155.54 | AF17: =AC17-CF!AF22-CF!AF16 -> 50257.344 | AG17: =AF17-CF!AG22-CF!AG16 -> 50335.023 | AH17: =AG17-CF!AH22-CF!AH16 -> 50410.022 | AI17: =AH17-CF!AI22-CF!AI16 -> 50492.376 | AJ17: =AI17 -> 50492.376
A18: Other non-current assets ($M) | B18: n/a | C18: n/a | D18: n/a | E18: 74834 | F18: n/a | G18: n/a | H18: n/a | I18: 83727 | J18: n/a | K18: n/a | L18: =$I$18 -> 83727 | M18: =$I$18 -> 83727 | N18: =$I$18 -> 83727 | O18: =$I$18 -> 83727 | P18: =O18 -> 83727 | Q18: n/a | T18: =$I$18 -> 83727 | U18: =$I$18 -> 83727 | V18: =$I$18 -> 83727 | W18: =V18 -> 83727 | Y18: n/a | AB18: =$I$18 -> 83727 | AC18: =$I$18 -> 83727 | AD18: =AC18 -> 83727 | AF18: =$I$18 -> 83727 | AG18: =$I$18 -> 83727 | AH18: =$I$18 -> 83727 | AI18: =$I$18 -> 83727 | AJ18: =AI18 -> 83727
A19: Total non-current assets ($M) | B19: n/a | C19: n/a | D19: n/a | E19: =SUM(E16:E18) -> 211993 | F19: n/a | G19: n/a | H19: n/a | I19: =SUM(I16:I18) -> 211284 | J19: n/a | K19: n/a | L19: =SUM(L16:L18) -> 211378.86 | M19: =SUM(M16:M18) -> 211451.23 | N19: =SUM(N16:N18) -> 211521.12 | O19: =SUM(O16:O18) -> 211597.85 | P19: =O19 -> 211597.85 | Q19: n/a | T19: =SUM(T16:T18) -> 211452.99 | U19: =SUM(U16:U18) -> 211524.56 | V19: =SUM(V16:V18) -> 211603.15 | W19: =V19 -> 211603.15 | Y19: n/a | AB19: =SUM(AB16:AB18) -> 211525.7 | AC19: =SUM(AC16:AC18) -> 211605.54 | AD19: =AC19 -> 211605.54 | AF19: =SUM(AF16:AF18) -> 211707.34 | AG19: =SUM(AG16:AG18) -> 211785.02 | AH19: =SUM(AH16:AH18) -> 211860.02 | AI19: =SUM(AI16:AI18) -> 211942.38 | AJ19: =AI19 -> 211942.38
A20: TOTAL ASSETS ($M) | B20: n/a | C20: n/a | D20: n/a | E20: =E15+E19 -> 364980 | F20: n/a | G20: n/a | H20: n/a | I20: =I15+I19 -> 359241 | J20: n/a | K20: n/a | L20: =L15+L19 -> 369311.78 | M20: =M15+M19 -> 353814.07 | N20: =N15+N19 -> 350951.05 | O20: =O15+O19 -> 353849.96 | P20: =O20 -> 353849.96 | Q20: n/a | T20: =T15+T19 -> 354815.32 | U20: =U15+U19 -> 351815.14 | V20: =V15+V19 -> 354709.75 | W20: =V20 -> 354709.75 | Y20: n/a | AB20: =AB15+AB19 -> 352276.31 | AC20: =AC15+AC19 -> 355308.56 | AD20: =AC20 -> 355308.56 | AF20: =AF15+AF19 -> 367470.58 | AG20: =AG15+AG19 -> 350852.1 | AH20: =AH15+AH19 -> 347763.19 | AI20: =AI15+AI19 -> 350841.67 | AJ20: =AI20 -> 350841.67
A22: Accounts payable ($M) | B22: 58146 | C22: 45753 | D22: 47574 | E22: 68960 | F22: 61910 | G22: 54126 | H22: 50374 | I22: 69860 | J22: 70587 | K22: 57349 | L22: =DPO_Active*(IS!L43/90) -> 88821.226 | M22: =DPO_Active*(IS!M43/90) -> 67772.134 | N22: =DPO_Active*(IS!N43/90) -> 65435.165 | O22: =DPO_Active*(IS!O43/90) -> 71851.1 | P22: =O22 -> 71851.1 | Q22: =J22 -> 70587 | T22: =DPO_Active*(IS!T43/90) -> 69412.982 | U22: =DPO_Active*(IS!U43/90) -> 67019.432 | V22: =DPO_Active*(IS!V43/90) -> 73590.705 | W22: =V22 -> 73590.705 | Y22: =K22 -> 57349 | AB22: =DPO_Active*(IS!AB43/90) -> 66131.767 | AC22: =DPO_Active*(IS!AC43/90) -> 72616.004 | AD22: =AC22 -> 72616.004 | AF22: =DPO_Active*(IS!AF43/90) -> 94496.492 | AG22: =DPO_Active*(IS!AG43/90) -> 72102.461 | AH22: =DPO_Active*(IS!AH43/90) -> 69616.17 | AI22: =DPO_Active*(IS!AI43/90) -> 76442.054 | AJ22: =AI22 -> 76442.054
A23: Other current liabilities ($M) | B23: n/a | C23: n/a | D23: n/a | E23: 78304 | F23: n/a | G23: n/a | H23: n/a | I23: 66387 | J23: n/a | K23: n/a | L23: =$I$23 -> 66387 | M23: =$I$23 -> 66387 | N23: =$I$23 -> 66387 | O23: =$I$23 -> 66387 | P23: =O23 -> 66387 | Q23: n/a | T23: =$I$23 -> 66387 | U23: =$I$23 -> 66387 | V23: =$I$23 -> 66387 | W23: =V23 -> 66387 | Y23: n/a | AB23: =$I$23 -> 66387 | AC23: =$I$23 -> 66387 | AD23: =AC23 -> 66387 | AF23: =$I$23 -> 66387 | AG23: =$I$23 -> 66387 | AH23: =$I$23 -> 66387 | AI23: =$I$23 -> 66387 | AJ23: =AI23 -> 66387
A24: Deferred revenue ($M) | B24: n/a | C24: n/a | D24: n/a | E24: 8249 | F24: n/a | G24: n/a | H24: n/a | I24: 9055 | J24: n/a | K24: n/a | L24: =$I$24 -> 9055 | M24: =$I$24 -> 9055 | N24: =$I$24 -> 9055 | O24: =$I$24 -> 9055 | P24: =O24 -> 9055 | Q24: n/a | T24: =$I$24 -> 9055 | U24: =$I$24 -> 9055 | V24: =$I$24 -> 9055 | W24: =V24 -> 9055 | Y24: n/a | AB24: =$I$24 -> 9055 | AC24: =$I$24 -> 9055 | AD24: =AC24 -> 9055 | AF24: =$I$24 -> 9055 | AG24: =$I$24 -> 9055 | AH24: =$I$24 -> 9055 | AI24: =$I$24 -> 9055 | AJ24: =AI24 -> 9055
A25: Commercial paper ($M) | B25: n/a | C25: n/a | D25: n/a | E25: 9967 | F25: n/a | G25: n/a | H25: n/a | I25: 7979 | J25: n/a | K25: n/a | L25: =$I$25 -> 7979 | M25: =$I$25 -> 7979 | N25: =$I$25 -> 7979 | O25: =$I$25 -> 7979 | P25: =O25 -> 7979 | Q25: n/a | T25: =$I$25 -> 7979 | U25: =$I$25 -> 7979 | V25: =$I$25 -> 7979 | W25: =V25 -> 7979 | Y25: n/a | AB25: =$I$25 -> 7979 | AC25: =$I$25 -> 7979 | AD25: =AC25 -> 7979 | AF25: =$I$25 -> 7979 | AG25: =$I$25 -> 7979 | AH25: =$I$25 -> 7979 | AI25: =$I$25 -> 7979 | AJ25: =AI25 -> 7979
A26: Term debt - current ($M) | B26: n/a | C26: n/a | D26: n/a | E26: 10912 | F26: n/a | G26: n/a | H26: n/a | I26: 12350 | J26: n/a | K26: n/a | L26: =$I$26 -> 12350 | M26: =$I$26 -> 12350 | N26: =$I$26 -> 12350 | O26: =$I$26 -> 12350 | P26: =O26 -> 12350 | Q26: n/a | T26: =$I$26 -> 12350 | U26: =$I$26 -> 12350 | V26: =$I$26 -> 12350 | W26: =V26 -> 12350 | Y26: n/a | AB26: =$I$26 -> 12350 | AC26: =$I$26 -> 12350 | AD26: =AC26 -> 12350 | AF26: =$I$26 -> 12350 | AG26: =$I$26 -> 12350 | AH26: =$I$26 -> 12350 | AI26: =$I$26 -> 12350 | AJ26: =AI26 -> 12350
A27: Total current liabilities ($M) | B27: n/a | C27: n/a | D27: n/a | E27: =SUM(E22:E26) -> 176392 | F27: n/a | G27: n/a | H27: n/a | I27: =SUM(I22:I26) -> 165631 | J27: n/a | K27: n/a | L27: =SUM(L22:L26) -> 184592.23 | M27: =SUM(M22:M26) -> 163543.13 | N27: =SUM(N22:N26) -> 161206.16 | O27: =SUM(O22:O26) -> 167622.1 | P27: =O27 -> 167622.1 | Q27: n/a | T27: =SUM(T22:T26) -> 165183.98 | U27: =SUM(U22:U26) -> 162790.43 | V27: =SUM(V22:V26) -> 169361.71 | W27: =V27 -> 169361.71 | Y27: n/a | AB27: =SUM(AB22:AB26) -> 161902.77 | AC27: =SUM(AC22:AC26) -> 168387 | AD27: =AC27 -> 168387 | AF27: =SUM(AF22:AF26) -> 190267.49 | AG27: =SUM(AG22:AG26) -> 167873.46 | AH27: =SUM(AH22:AH26) -> 165387.17 | AI27: =SUM(AI22:AI26) -> 172213.05 | AJ27: =AI27 -> 172213.05
A28: Term debt - non-current ($M) | B28: n/a | C28: n/a | D28: n/a | E28: 85750 | F28: n/a | G28: n/a | H28: n/a | I28: 78328 | J28: n/a | K28: n/a | L28: =I28+Debt_Roll_Active -> 78328 | M28: =L28+Debt_Roll_Active -> 78328 | N28: =M28+Debt_Roll_Active -> 78328 | O28: =N28+Debt_Roll_Active -> 78328 | P28: =O28 -> 78328 | Q28: n/a | T28: =L28+Debt_Roll_Active -> 78328 | U28: =T28+Debt_Roll_Active -> 78328 | V28: =U28+Debt_Roll_Active -> 78328 | W28: =V28 -> 78328 | Y28: n/a | AB28: =T28+Debt_Roll_Active -> 78328 | AC28: =AB28+Debt_Roll_Active -> 78328 | AD28: =AC28 -> 78328 | AF28: =AC28+Debt_Roll_Active -> 78328 | AG28: =AF28+Debt_Roll_Active -> 78328 | AH28: =AG28+Debt_Roll_Active -> 78328 | AI28: =AH28+Debt_Roll_Active -> 78328 | AJ28: =AI28 -> 78328
A29: Other non-current liabilities ($M) | B29: n/a | C29: n/a | D29: n/a | E29: 45888 | F29: n/a | G29: n/a | H29: n/a | I29: 41549 | J29: n/a | K29: n/a | L29: =$I$29 -> 41549 | M29: =$I$29 -> 41549 | N29: =$I$29 -> 41549 | O29: =$I$29 -> 41549 | P29: =O29 -> 41549 | Q29: n/a | T29: =$I$29 -> 41549 | U29: =$I$29 -> 41549 | V29: =$I$29 -> 41549 | W29: =V29 -> 41549 | Y29: n/a | AB29: =$I$29 -> 41549 | AC29: =$I$29 -> 41549 | AD29: =AC29 -> 41549 | AF29: =$I$29 -> 41549 | AG29: =$I$29 -> 41549 | AH29: =$I$29 -> 41549 | AI29: =$I$29 -> 41549 | AJ29: =AI29 -> 41549
A30: Total non-current liabilities ($M) | B30: n/a | C30: n/a | D30: n/a | E30: =SUM(E28:E29) -> 131638 | F30: n/a | G30: n/a | H30: n/a | I30: =SUM(I28:I29) -> 119877 | J30: n/a | K30: n/a | L30: =SUM(L28:L29) -> 119877 | M30: =SUM(M28:M29) -> 119877 | N30: =SUM(N28:N29) -> 119877 | O30: =SUM(O28:O29) -> 119877 | P30: =O30 -> 119877 | Q30: n/a | T30: =SUM(T28:T29) -> 119877 | U30: =SUM(U28:U29) -> 119877 | V30: =SUM(V28:V29) -> 119877 | W30: =V30 -> 119877 | Y30: n/a | AB30: =SUM(AB28:AB29) -> 119877 | AC30: =SUM(AC28:AC29) -> 119877 | AD30: =AC30 -> 119877 | AF30: =SUM(AF28:AF29) -> 119877 | AG30: =SUM(AG28:AG29) -> 119877 | AH30: =SUM(AH28:AH29) -> 119877 | AI30: =SUM(AI28:AI29) -> 119877 | AJ30: =AI30 -> 119877
A31: TOTAL LIABILITIES ($M) | B31: n/a | C31: n/a | D31: n/a | E31: =E27+E30 -> 308030 | F31: n/a | G31: n/a | H31: n/a | I31: =I27+I30 -> 285508 | J31: n/a | K31: n/a | L31: =L27+L30 -> 304469.23 | M31: =M27+M30 -> 283420.13 | N31: =N27+N30 -> 281083.16 | O31: =O27+O30 -> 287499.1 | P31: =O31 -> 287499.1 | Q31: n/a | T31: =T27+T30 -> 285060.98 | U31: =U27+U30 -> 282667.43 | V31: =V27+V30 -> 289238.71 | W31: =V31 -> 289238.71 | Y31: n/a | AB31: =AB27+AB30 -> 281779.77 | AC31: =AC27+AC30 -> 288264 | AD31: =AC31 -> 288264 | AF31: =AF27+AF30 -> 310144.49 | AG31: =AG27+AG30 -> 287750.46 | AH31: =AH27+AH30 -> 285264.17 | AI31: =AI27+AI30 -> 292090.05 | AJ31: =AI31 -> 292090.05
A33: Common stock and additional paid-in capital ($M) | B33: n/a | C33: n/a | D33: n/a | E33: 83276 | F33: n/a | G33: n/a | H33: n/a | I33: 93568 | J33: n/a | K33: n/a | L33: =$I$33 -> 93568 | M33: =$I$33 -> 93568 | N33: =$I$33 -> 93568 | O33: =$I$33 -> 93568 | P33: =O33 -> 93568 | Q33: n/a | T33: =$I$33 -> 93568 | U33: =$I$33 -> 93568 | V33: =$I$33 -> 93568 | W33: =V33 -> 93568 | Y33: n/a | AB33: =$I$33 -> 93568 | AC33: =$I$33 -> 93568 | AD33: =AC33 -> 93568 | AF33: =$I$33 -> 93568 | AG33: =$I$33 -> 93568 | AH33: =$I$33 -> 93568 | AI33: =$I$33 -> 93568 | AJ33: =AI33 -> 93568
A34: Accumulated other comprehensive income/(loss) ($M) | B34: n/a | C34: n/a | D34: n/a | E34: -7172 | F34: n/a | G34: n/a | H34: n/a | I34: -5571 | J34: n/a | K34: n/a | L34: =$I$34 -> -5571 | M34: =$I$34 -> -5571 | N34: =$I$34 -> -5571 | O34: =$I$34 -> -5571 | P34: =O34 -> -5571 | Q34: n/a | T34: =$I$34 -> -5571 | U34: =$I$34 -> -5571 | V34: =$I$34 -> -5571 | W34: =V34 -> -5571 | Y34: n/a | AB34: =$I$34 -> -5571 | AC34: =$I$34 -> -5571 | AD34: =AC34 -> -5571 | AF34: =$I$34 -> -5571 | AG34: =$I$34 -> -5571 | AH34: =$I$34 -> -5571 | AI34: =$I$34 -> -5571 | AJ34: =AI34 -> -5571
A35: Retained earnings/(Accumulated deficit) ($M) | B35: n/a | C35: n/a | D35: n/a | E35: -19154 | F35: n/a | G35: n/a | H35: n/a | I35: -14264 | J35: n/a | K35: n/a | L35: =I35+IS!L53+CF!L26+CF!L25 -> -23154.449 | M35: =L35+IS!M53+CF!M26+CF!M25 -> -17603.059 | N35: =M35+IS!N53+CF!N26+CF!N25 -> -18129.118 | O35: =N35+IS!O53+CF!O26+CF!O25 -> -21646.135 | P35: =O35 -> -21646.135 | Q35: n/a | T35: =L35+IS!T53+CF!T26+CF!T25 -> -18242.659 | U35: =T35+IS!U53+CF!U26+CF!U25 -> -18849.295 | V35: =U35+IS!V53+CF!V26+CF!V25 -> -22525.955 | W35: =V35 -> -22525.955 | Y35: n/a | AB35: =T35+IS!AB53+CF!AB26+CF!AB25 -> -17500.458 | AC35: =AB35+IS!AC53+CF!AC26+CF!AC25 -> -20952.444 | AD35: =AC35 -> -20952.444 | AF35: =AC35+IS!AF53+CF!AF26+CF!AF25 -> -30670.907 | AG35: =AF35+IS!AG53+CF!AG26+CF!AG25 -> -24895.356 | AH35: =AG35+IS!AH53+CF!AH26+CF!AH25 -> -25497.979 | AI35: =AH35+IS!AI53+CF!AI26+CF!AI25 -> -29245.383 | AJ35: =AI35 -> -29245.383
A36: TOTAL SHAREHOLDERS' EQUITY ($M) | B36: n/a | C36: n/a | D36: n/a | E36: =SUM(E33:E35) -> 56950 | F36: n/a | G36: n/a | H36: n/a | I36: =SUM(I33:I35) -> 73733 | J36: n/a | K36: n/a | L36: =SUM(L33:L35) -> 64842.551 | M36: =SUM(M33:M35) -> 70393.941 | N36: =SUM(N33:N35) -> 69867.882 | O36: =SUM(O33:O35) -> 66350.865 | P36: =O36 -> 66350.865 | Q36: n/a | T36: =SUM(T33:T35) -> 69754.341 | U36: =SUM(U33:U35) -> 69147.705 | V36: =SUM(V33:V35) -> 65471.045 | W36: =V36 -> 65471.045 | Y36: n/a | AB36: =SUM(AB33:AB35) -> 70496.542 | AC36: =SUM(AC33:AC35) -> 67044.556 | AD36: =AC36 -> 67044.556 | AF36: =SUM(AF33:AF35) -> 57326.093 | AG36: =SUM(AG33:AG35) -> 63101.644 | AH36: =SUM(AH33:AH35) -> 62499.021 | AI36: =SUM(AI33:AI35) -> 58751.617 | AJ36: =AI36 -> 58751.617
A37: TOTAL LIABILITIES AND SHAREHOLDERS' EQUITY ($M) | B37: n/a | C37: n/a | D37: n/a | E37: =E31+E36 -> 364980 | F37: n/a | G37: n/a | H37: n/a | I37: =I31+I36 -> 359241 | J37: n/a | K37: n/a | L37: =L31+L36 -> 369311.78 | M37: =M31+M36 -> 353814.07 | N37: =N31+N36 -> 350951.05 | O37: =O31+O36 -> 353849.96 | P37: =O37 -> 353849.96 | Q37: n/a | T37: =T31+T36 -> 354815.32 | U37: =U31+U36 -> 351815.14 | V37: =V31+V36 -> 354709.75 | W37: =V37 -> 354709.75 | Y37: n/a | AB37: =AB31+AB36 -> 352276.31 | AC37: =AC31+AC36 -> 355308.56 | AD37: =AC37 -> 355308.56 | AF37: =AF31+AF36 -> 367470.58 | AG37: =AG31+AG36 -> 350852.1 | AH37: =AH31+AH36 -> 347763.19 | AI37: =AI31+AI36 -> 350841.67 | AJ37: =AI37 -> 350841.67
A39: BALANCE CHECK: Total Assets - Total Liabilities - Total Equity ($M) [must = 0] | B39: n/a | C39: n/a | D39: n/a | E39: =E20-E31-E36 -> 0 | F39: n/a | G39: n/a | H39: n/a | I39: =I20-I31-I36 -> 0 | J39: n/a | K39: n/a | L39: =L20-L31-L36 -> -5.0931703e-11 | M39: =M20-M31-M36 -> 0 | N39: =N20-N31-N36 -> -5.8207661e-11 | O39: =O20-O31-O36 -> 1.4551915e-11 | P39: =O39 -> 1.4551915e-11 | Q39: n/a | T39: =T20-T31-T36 -> -1.4551915e-11 | U39: =U20-U31-U36 -> -4.3655746e-11 | V39: =V20-V31-V36 -> -4.3655746e-11 | W39: =V39 -> -4.3655746e-11 | Y39: n/a | AB39: =AB20-AB31-AB36 -> 0 | AC39: =AC20-AC31-AC36 -> 0 | AD39: =AC39 -> 0 | AF39: =AF20-AF31-AF36 -> -1.4551915e-11 | AG39: =AG20-AG31-AG36 -> -1.4551915e-11 | AH39: =AH20-AH31-AH36 -> 1.4551915e-11 | AI39: =AI20-AI31-AI36 -> -4.3655746e-11 | AJ39: =AI39 -> -4.3655746e-11
A41: PER-LINE-ITEM TREATMENT (Step 1 of the task brief -- every non-driver-modeled line item's simplifying choice, documented, never invented/blank)
A42: Line Item | B42: Treatment | C42: Formula basis / rationale
A43: Cash and cash equivalents ($M) | B43: Driven | C43: Formula:CF tab's own computed ending-cash balance for this column (genuinely computed, never an independent plug -- see CF tab row 'Cash, end of period').
A44: Marketable securities - current ($M) | B44: Hold flat | C44: Formula:FY25 Q4 anchor (col I), held flat. No investment-portfolio driver exists on the Drivers tab; holding flat also guarantees this line contributes zero delta to the balance-sheet identity without requiring a new, un-briefed Cash Flow Statement line. (Proved algebraically before writing any code: an asset-side-only revenue-scaled delta with no offsetting CF line breaks Total Assets = Total Liabilities + Equity by exactly that delta every forecast period -- this is why every non-Driver-linked line on this tab is held flat rather than grown with revenue.)
A45: Accounts receivable, net ($M) | B45: Driven (DSO) | C45: Formula:DSO_Active x (IS!Net Sales / 90).
A46: Vendor non-trade receivables ($M) | B46: Hold flat | C46: Formula:FY25 Q4 anchor (col I), held flat. A revenue-scaled growth treatment was considered and rejected: unless paired with a corresponding new Cash Flow Statement line (which the brief does not specify), an asset-side-only revenue-scaled delta breaks Total Assets = Total Liabilities + Equity -- proved algebraically before writing any code (same reasoning as Marketable securities - current, above).
A47: Inventories ($M) | B47: Driven (DIO) | C47: Formula:DIO_Active x (IS!COGS / 90).
A48: Other current assets ($M) | B48: Hold flat | C48: Formula:FY25 Q4 anchor (col I), held flat. No specific driver identified for this catch-all line; flat guarantees zero balance-sheet-identity impact.
A49: Marketable securities - non-current ($M) | B49: Hold flat | C49: Formula:FY25 Q4 anchor (col I), held flat. Same rationale as current marketable securities.
A50: Property, plant and equipment, net ($M) | B50: Driven | C50: Formula:prior-period PP&E + CapEx$ (CapEx_Pct_Rev_Active x Revenue, from CF tab) - D&A$ (this tab's own D&A% assumption x Revenue, from CF tab row 9 -- D&A has no Drivers-tab named range, so this is a scenario-independent local assumption, documented on the CF tab).
A51: Other non-current assets ($M) | B51: Hold flat | C51: Formula:FY25 Q4 anchor (col I), held flat. No specific driver identified for this catch-all line.
A52: Accounts payable ($M) | B52: Driven (DPO) | C52: Formula:DPO_Active x (IS!COGS / 90).
A53: Other current liabilities ($M) | B53: Hold flat | C53: Formula:FY25 Q4 anchor (col I), held flat. No specific driver identified for this catch-all line.
... A61: Retained earnings/(Accumulated deficit) ($M) | B61: Driven (roll-forward) | C61: Formula:prior-period RE + Net Income (IS tab) - Dividends$ (Dividend_Payout_Active x NI, CF tab) - Buybacks$ (Buyback_Pct_FCF_Active x FCF, CF tab). Per the brief, buybacks reduce Retained Earnings directly -- a simplification, not the GAAP treasury-stock/APIC mechanic.
A63: Color legend: blue = real historical literal input (Quarterly tab for Cash/AR/Inventory/AP; Annual tab for the full FY24 Q4 / FY25 Q4 balance sheet; the Q1/Q2 FY2026 Actual overlay columns Q/Y mirror the real historical columns J/K); black on light green = forecast formula output (driven or hold-flat -- see documentation block above); light grey = subtotal / Total column (Total mirrors that vintage's own Q4 column). 'n/a' = not available at quarterly grain in the Historical Database, or (Q/Y) a line Apple does not disclose at quarterly grain at all -- never fabricated or plugged. Balance Check row is conditionally formatted green when within $1M of zero, red otherwise; it reads 'n/a' rather than a fabricated zero wherever a full balance sheet cannot honestly be built. BULL-SCENARIO CASH NOTE: under Bull, the Cash line's decline is visible starting from the very first forecast quarter (FY26 Q1 AOP, col L) and is continuous and steady through every subsequent vintage column -- Cash turns NEGATIVE starting FY2027 Q3 (col AH) and remains negative through FY2027 Q4 (col AI): two consecutive negative quarters, not a single Q4 tail event. Root cause: Bull sets Buyback_Pct_FCF_Active to 100% (consuming the entire FCF pool every quarter) with dividends layered on top and no revolver/cash-floor mechanic modeled -- a deterministic drain baked in from quarter one, confirmed by tracing every column of the Bull-scenario cash trajectory. This is NOT a balance-check bug: Total Assets - Total Liabilities - Total Equity holds at effectively exact zero at every column along this entire path under Bull, exactly as it does in Base and Bear.

Sheet CF
A1: Apple Inc. -- Driver-Based Rolling Forecast Model: CASH FLOW (CF)
A2: Historical actuals: Net income (via IS tab), Repurchases of common stock, and Dividends paid are real discrete-quarter disclosures for all 10 historical quarters (B:K) and the Q1/Q2 FY2026 Actual overlay columns (Q, Y). Change in AR/Inventory/AP is a REAL derived figure (this period's real BS balance minus the prior REAL period's real BS balance) wherever both quarters are available (col B has no prior quarter in the dataset). D&A, CapEx, and the OCF/ICF/Financing subtotals are NOT disclosed at discrete-quarter grain anywhere in the source data (10-Qs report cash flow YTD-cumulative, not discrete-quarter) -- shown 'n/a', never fabricated. 'Cash, end of period' for these columns is the real BS Cash balance.
A3: Forecast columns: Operating CF = Net income (IS tab) + D&A (row 9 assumption x Revenue) + working-capital changes (AR/Inventory/AP deltas vs. this column's own roll-forward prior on the BS tab). WHY THE ROLL-FORWARD PRIOR IS THE LAST MODELED COLUMN, NOT THE REAL Q1/Q2 ACTUAL OVERLAY COLUMNS (Q, Y) -- design choice, not an oversight: re-anchoring a forecast quarter's Begin-Cash/PP&E/debt/equity to Q or Y is mathematically impossible to balance without a hidden plug, because Q/Y carry REAL Cash/AR/Inventory/AP but Apple discloses no quarterly PP&E/debt/equity detail to match against them (full reasoning and algebraic proof: BS!A2 above). CONSEQUENCE, STATED EXPLICITLY: forecast cash increasingly diverges from real reported cash as actuals come in -- in this delivered file the live Q3 Reforecast vintage's FY2026-exit modeled cash (col AD, row 30) is ~$29.8B vs. the real FY2026 Q2 reported cash of ~$45.6B two columns to the left in this same row (col K) -- a disclosed methodological limitation, not a formula error. Investing CF = -CapEx (Drivers!CapEx_Pct_Rev_Active x Revenue). Financing CF = -Buyback$ (Drivers!Buyback_Pct_FCF_Active x this period's own FCF -- a same-period proxy for the Drivers tab's 'trailing FCF' label; no multi-period trailing mechanism exists elsewhere in this model) - Dividend$ (Drivers!Dividend_Payout_Active x NI) + Drivers!Debt_Roll_Active. 'Cash, end of period' = 'Cash, beginning of period' + net change -- this IS the figure the BS tab's Cash line pulls from (never an independent plug). Total columns (P/W/AD/AJ): Net income/Buyback/Dividend sum cleanly across the vintage's own quarters (matching the IS tab's own Total-column convention); every other flow line is 'n/a' for the two Totals (W, AD) that blend a real actual quarter with modeled quarters whose own roll-forward prior is NOT that real quarter (summing across that seam would silently misstate the figure) -- Begin/End Cash for every Total instead read directly off the BS tab.
B5: =IS!B5 -> HISTORICAL ACTUALS -- Source: 02 Historical Financial Database.xlsx, Quarterly tab (real values, not re-derived) | L5: =IS!L5 -> FY2026 Approved AOP -- first rolling-forecast vintage (Drivers tab Active column; Base/Bull/Bear scenario switch at Drivers!B6) | Q5: =IS!Q5 -> Q1 FY2026 ACTUAL vs. APPROVED AOP VARIANCE -- Actual = mirror of historical col J (real data); Variance = Actual - Approved AOP Q1 (col L) | T5: =IS!T5 -> Q1 FORECAST UPDATE -- second rolling-forecast vintage (Q1 FY2026 actual reported; Q2-Q4 FY2026 reforecast using the Drivers tab Active column PLUS the Q1-actual driver adjustments in rows 63-78 below, in place of reverting to the original AOP assumptions where the Q1 variance was material) | Y5: =IS!Y5 -> Q2 FY2026 ACTUAL vs. Q1 FORECAST UPDATE VARIANCE -- Actual = mirror of historical col K (real data); Variance = Actual - Q1 Forecast Update's own Q2 column (T) | AB5: =IS!AB5 -> Q3 REFORECAST -- third rolling-forecast vintage, and the CURRENT / LIVE forecast in this project's story (Q1 and Q2 FY2026 are now both real actuals; Q3-Q4 reforecast using the Q1 Forecast Update's own Annual Build PLUS the Q2-actual driver adjustments in rows 84-99 below, in place of reverting to the Q1 Forecast Update's own assumptions where the Q2 variance was material) | AF5: =IS!AF5 -> FY2027 AOP -- fifth and FINAL rolling-forecast vintage: next year's Annual Operating Plan, built off the Q3 Reforecast's Q4 FY2026 EXIT run-rate (col AC de-seasonalized by dividing by the Q4 weight, row 12 col E -- NOT a naive x4, and NOT the Q3 Reforecast's FY26 Total), grown one more year via the Drivers tab's Active assumptions (Base/Bull/Bear switch at Drivers!B6). Fresh forward plan -- no Driver Adjustment Log (see row 125).
A6: Line Item | B6: =IS!B6 -> FY24 Q1 | C6: =IS!C6 -> FY24 Q2 | D6: =IS!D6 -> FY24 Q3 | E6: =IS!E6 -> FY24 Q4 | F6: =IS!F6 -> FY25 Q1 | G6: =IS!G6 -> FY25 Q2 | H6: =IS!H6 -> FY25 Q3 | I6: =IS!I6 -> FY25 Q4 | ... Q6: =IS!Q6 -> Q1 FY2026 Actual | T6: =IS!T6 -> Q2 -- Q1 Forecast Update | U6: =IS!U6 -> Q3 -- Q1 Forecast Update | V6: =IS!V6 -> Q4 -- Q1 Forecast Update | W6: =IS!W6 -> FY26 Total -- Q1 Forecast Update | Y6: =IS!Y6 -> Q2 FY2026 Actual | AB6: =IS!AB6 -> Q3 -- Q3 Reforecast | AC6: =IS!AC6 -> Q4 -- Q3 Reforecast | AD6: =IS!AD6 -> FY26 Total -- Q3 Reforecast | AF6: =IS!AF6 -> Q1 -- FY2027 AOP | AG6: =IS!AG6 -> Q2 -- FY2027 AOP | AH6: =IS!AH6 -> Q3 -- FY2027 AOP | AI6: =IS!AI6 -> Q4 -- FY2027 AOP | AJ6: =IS!AJ6 -> FY27 Total -- FY2027 AOP
A8: KEY ASSUMPTION -- DEPRECIATION & AMORTIZATION
A9: D&A (% of Net Sales) -- assumption, held flat, scenario-independent | C9: 0.029287294 | D9: 5-yr FY2021-FY2025 average of (D&A / Net sales), computed from the Historical Database's Annual tab (yearly ratios: 3.08%, 2.82%, 3.01%, 2.93%, 2.81%; average 2.93%). The Drivers tab has no scenario-specific D&A named range (confirmed by reading its full 29-row map), so this is this task's own scenario-INDEPENDENT local assumption -- held flat at the same rate in Base/Bull/Bear.
A11: CASH FLOW STATEMENT
A13: Cash, beginning of period ($M) | B13: n/a | C13: =BS!B9 -> 40760 | D13: =BS!C9 -> 32695 | E13: =BS!D9 -> 25565 | F13: =BS!E9 -> 29943 | G13: =BS!F9 -> 30299 | H13: =BS!G9 -> 28162 | I13: =BS!H9 -> 36269 | J13: =BS!I9 -> 35934 | K13: =BS!J9 -> 45317 | L13: =BS!I9 -> 35934 | M13: =BS!L9 -> 34880.118 | N13: =BS!M9 -> 32705.437 | O13: =BS!N9 -> 31259.747 | P13: =BS!I9 -> 35934 | Q13: =BS!I9 -> 35934 | T13: =BS!L9 -> 34880.118 | U13: =BS!T9 -> 32660.716 | V13: =BS!U9 -> 31112.184 | W13: =BS!I9 -> 35934 | Y13: =BS!J9 -> 45317 | AB13: =BS!T9 -> 32660.716 | AC13: =BS!AB9 -> 31063.864 | AD13: =BS!I9 -> 35934 | AF13: =BS!AC9 -> 29784.548 | AG13: =BS!AF9 -> 28642.83 | AH13: =BS!AG9 -> 26306.023 | AI13: =BS!AH9 -> 24736.353 | AJ13: =BS!AC9 -> 29784.548
A14: OPERATING ACTIVITIES
A15: Net income ($M) | B15: =IS!B53 -> 33916 | C15: =IS!C53 -> 23636 | D15: =IS!D53 -> 21448 | E15: =IS!E53 -> 14736 | F15: =IS!F53 -> 36330 | G15: =IS!G53 -> 24780 | H15: =IS!H53 -> 23434 | I15: =IS!I53 -> 27466 | ... O15: =IS!O53 -> 29729.198 | P15: =L15+M15+N15+O15 -> 121595.99 | Q15: =IS!Q53 -> 42097 | T15: =IS!T53 -> 30125.657 | U15: =IS!U53 -> 29086.842 | V15: =IS!V53 -> 31938.814 | W15: =Q15+T15+U15+V15 -> 133248.31 | Y15: =IS!Y53 -> 29578 | AB15: =IS!AB53 -> 27258.92 | AC15: =IS!AC53 -> 29931.665 | AD15: =Q15+Y15+AB15+AC15 -> 128865.59 | AF15: =IS!AF53 -> 39987.855 | AG15: =IS!AG53 -> 30511.426 | AH15: =IS!AH53 -> 29459.309 | AI15: =IS!AI53 -> 32347.802 | AJ15: =AF15+AG15+AH15+AI15 -> 132306.39
A16: Add: Depreciation and amortization ($M) | B16: n/a | C16: n/a | D16: n/a | E16: n/a | F16: n/a | G16: n/a | H16: n/a | I16: n/a | J16: n/a | K16: n/a | L16: =$C$9*IS!L41 -> 3897.9699 | M16: =$C$9*IS!M41 -> 2974.2185 | N16: =$C$9*IS!N41 -> 2871.6593 | O16: =$C$9*IS!O41 -> 3153.2263 | P16: =L16+M16+N16+O16 -> 12897.074 | Q16: n/a | T16: =$C$9*IS!T41 -> 3046.2281 | U16: =$C$9*IS!U41 -> 2941.1858 | V16: =$C$9*IS!V41 -> 3229.5698 | W16: n/a (blends a real FY2026 actual quarter -- which lacks quarterly D&A/CapEx/debt-roll disclosure and whose successor quarter's own roll-forward prior is NOT this actual quarter -- with modeled quarters; see the individual quarter columns for full detail) | Y16: n/a | AB16: =$C$9*IS!AB41 -> 2987.9556 | AC16: =$C$9*IS!AC41 -> 3280.9254 | AD16: n/a (blends a real FY2026 actual quarter -- which lacks quarterly D&A/CapEx/debt-roll disclosure and whose successor quarter's own roll-forward prior is NOT this actual quarter -- with modeled quarters; see the individual quarter columns for full detail) | AF16: =$C$9*IS!AF41 -> 4183.4496 | AG16: =$C$9*IS!AG41 -> 3192.0445 | AH16: =$C$9*IS!AH41 -> 3081.9741 | AI16: =$C$9*IS!AI41 -> 3384.1624 | AJ16: =AF16+AG16+AH16+AI16 -> 13841.631
A17: (Increase)/decrease in accounts receivable ($M) | B17: n/a | C17: =-(BS!C11-BS!B11) -> 1357 | D17: =-(BS!D11-BS!C11) -> -958 | E17: =-(BS!E11-BS!D11) -> -10615 | F17: =-(BS!F11-BS!E11) -> 3771 | G17: =-(BS!G11-BS!F11) -> 3503 | H17: =-(BS!H11-BS!G11) -> -1421 | I17: =-(BS!I11-BS!H11) -> -12220 | J17: =-(BS!J11-BS!I11) -> -144 | K17: =-(BS!K11-BS!J11) -> 9582 | L17: =-(BS!L11-BS!I11) -> -9024.2176 | M17: =-(BS!M11-BS!L11) -> 11565.043 | N17: =-(BS!N11-BS!M11) -> 1284.0055 | O17: =-(BS!O11-BS!N11) -> -3525.1197 | P17: =L17+M17+N17+O17 -> 299.7115 | Q17: =-(BS!Q11-BS!I11) -> -144 | T17: =-(BS!T11-BS!L11) -> 10663.509 | U17: =-(BS!U11-BS!T11) -> 1315.0929 | V17: =-(BS!V11-BS!U11) -> -3610.4672 | W17: n/a (blends a real FY2026 actual quarter -- which lacks quarterly D&A/CapEx/debt-roll disclosure and whose successor quarter's own roll-forward prior is NOT this actual quarter -- with modeled quarters; see the individual quarter columns for full detail) | Y17: =-(BS!Y11-BS!J11) -> 9582 | AB17: =-(BS!AB11-BS!T11) -> 729.55172 | AC17: =-(BS!AC11-BS!AB11) -> -3667.8797 | AD17: n/a (blends a real FY2026 actual quarter -- which lacks quarterly D&A/CapEx/debt-roll disclosure and whose successor quarter's own roll-forward prior is NOT this actual quarter -- with modeled quarters; see the individual quarter columns for full detail) | AF17: =-(BS!AF11-BS!AC11) -> -11299.287 | AG17: =-(BS!AG11-BS!AF11) -> 12412.045 | AH17: =-(BS!AH11-BS!AG11) -> 1378.0436 | AI17: =-(BS!AI11-BS!AH11) -> -3783.2926 | AJ17: =AF17+AG17+AH17+AI17 -> -1292.4917
A18: (Increase)/decrease in inventories ($M) | B18: n/a | C18: =-(BS!C13-BS!B13) -> 279 | D18: =-(BS!D13-BS!C13) -> 67 | E18: =-(BS!E13-BS!D13) -> -1121 | F18: =-(BS!F13-BS!E13) -> 375 | G18: =-(BS!G13-BS!F13) -> 642 | H18: =-(BS!H13-BS!G13) -> 344 | I18: =-(BS!I13-BS!H13) -> 207 | J18: =-(BS!J13-BS!I13) -> -157 | K18: =-(BS!K13-BS!J13) -> -872 | L18: =-(BS!L13-BS!I13) -> -2005.5848 | M18: =-(BS!M13-BS!L13) -> 1830.3558 | N18: =-(BS!N13-BS!M13) -> 203.21472 | O18: =-(BS!O13-BS!N13) -> -557.90741 | P18: =L18+M18+N18+O18 -> -529.92172 | Q18: =-(BS!Q13-BS!I13) -> -157 | T18: =-(BS!T13-BS!L13) -> 1687.6733 | U18: =-(BS!U13-BS!T13) -> 208.1348 | V18: =-(BS!V13-BS!U13) -> -571.41505 | W18: n/a (blends a real FY2026 actual quarter -- which lacks quarterly D&A/CapEx/debt-roll disclosure and whose successor quarter's own roll-forward prior is NOT this actual quarter -- with modeled quarters; see the individual quarter columns for full detail) | Y18: =-(BS!Y13-BS!J13) -> -872 | AB18: =-(BS!AB13-BS!T13) -> 285.3231 | AC18: =-(BS!AC13-BS!AB13) -> -563.84671 | AD18: n/a (blends a real FY2026 actual quarter -- which lacks quarterly D&A/CapEx/debt-roll disclosure and whose successor quarter's own roll-forward prior is NOT this actual quarter -- with modeled quarters; see the individual quarter columns for full detail) | AF18: =-(BS!AF13-BS!AC13) -> -1902.6512 | AG18: =-(BS!AG13-BS!AF13) -> 1947.3071 | AH18: =-(BS!AH13-BS!AG13) -> 216.1992 | AI18: =-(BS!AI13-BS!AH13) -> -593.55512 | AJ18: =AF18+AG18+AH18+AI18 -> -332.69995
A19: Increase/(decrease) in accounts payable ($M) | B19: n/a | C19: =(BS!C22-BS!B22) -> -12393 | D19: =(BS!D22-BS!C22) -> 1821 | E19: =(BS!E22-BS!D22) -> 21386 | F19: =(BS!F22-BS!E22) -> -7050 | G19: =(BS!G22-BS!F22) -> -7784 | H19: =(BS!H22-BS!G22) -> -3752 | I19: =(BS!I22-BS!H22) -> 19486 | J19: =(BS!J22-BS!I22) -> 727 | K19: =(BS!K22-BS!J22) -> -13238 | L19: =(BS!L22-BS!I22) -> 18961.226 | M19: =(BS!M22-BS!L22) -> -21049.092 | N19: =(BS!N22-BS!M22) -> -2336.9692 | O19: =(BS!O22-BS!N22) -> 6415.9352 | P19: =L19+M19+N19+O19 -> 1991.0998 | Q19: =(BS!Q22-BS!I22) -> 727 | T19: =(BS!T22-BS!L22) -> -19408.243 | U19: =(BS!U22-BS!T22) -> -2393.5502 | V19: =(BS!V22-BS!U22) -> 6571.273 | W19: n/a (blends a real FY2026 actual quarter -- which lacks quarterly D&A/CapEx/debt-roll disclosure and whose successor quarter's own roll-forward prior is NOT this actual quarter -- with modeled quarters; see the individual quarter columns for full detail) | Y19: =(BS!Y22-BS!J22) -> -13238 | AB19: =(BS!AB22-BS!T22) -> -3281.2156 | AC19: =(BS!AC22-BS!AB22) -> 6484.2372 | AD19: n/a (blends a real FY2026 actual quarter -- which lacks quarterly D&A/CapEx/debt-roll disclosure and whose successor quarter's own roll-forward prior is NOT this actual quarter -- with modeled quarters; see the individual quarter columns for full detail) | AF19: =(BS!AF22-BS!AC22) -> 21880.488 | AG19: =(BS!AG22-BS!AF22) -> -22394.032 | AH19: =(BS!AH22-BS!AG22) -> -2486.2908 | AI19: =(BS!AI22-BS!AH22) -> 6825.8838 | AJ19: =AF19+AG19+AH19+AI19 -> 3826.0495
A20: Cash generated by/(used in) operating activities ($M) | B20: n/a | C20: n/a | D20: n/a | E20: n/a | F20: n/a | G20: n/a | H20: n/a | I20: n/a | J20: n/a | K20: n/a | L20: =L15+L16+L17+L18+L19 -> 48580.171 | M20: =M15+M16+M17+M18+M19 -> 23362.006 | N20: =N15+N16+N17+N18+N19 -> 29096.443 | O20: =O15+O16+O17+O18+O19 -> 35215.332 | P20: =P15+P16+P17+P18+P19 -> 136253.95 | Q20: n/a | T20: =T15+T16+T17+T18+T19 -> 26114.824 | U20: =U15+U16+U17+U18+U19 -> 31157.705 | V20: =V15+V16+V17+V18+V19 -> 37557.775 | W20: n/a (blends a real FY2026 actual quarter -- which lacks quarterly D&A/CapEx/debt-roll disclosure and whose successor quarter's own roll-forward prior is NOT this actual quarter -- with modeled quarters; see the individual quarter columns for full detail) | Y20: n/a | AB20: =AB15+AB16+AB17+AB18+AB19 -> 27980.535 | AC20: =AC15+AC16+AC17+AC18+AC19 -> 35465.101 | AD20: n/a (blends a real FY2026 actual quarter -- which lacks quarterly D&A/CapEx/debt-roll disclosure and whose successor quarter's own roll-forward prior is NOT this actual quarter -- with modeled quarters; see the individual quarter columns for full detail) | AF20: =AF15+AF16+AF17+AF18+AF19 -> 52849.855 | AG20: =AG15+AG16+AG17+AG18+AG19 -> 25668.791 | AH20: =AH15+AH16+AH17+AH18+AH19 -> 31649.235 | AI20: =AI15+AI16+AI17+AI18+AI19 -> 38181 | AJ20: =AJ15+AJ16+AJ17+AJ18+AJ19 -> 148348.88
A21: INVESTING ACTIVITIES
A22: Capital expenditures (CapEx) ($M) | B22: n/a | C22: n/a | D22: n/a | E22: n/a | F22: n/a | G22: n/a | H22: n/a | I22: n/a | J22: n/a | K22: n/a | L22: =-CapEx_Pct_Rev_Active*IS!L41 -> -3992.8269 | M22: =-CapEx_Pct_Rev_Active*IS!M41 -> -3046.5961 | N22: =-CapEx_Pct_Rev_Active*IS!N41 -> -2941.5411 | O22: =-CapEx_Pct_Rev_Active*IS!O41 -> -3229.96 | P22: =L22+M22+N22+O22 -> -13210.924 | Q22: n/a | T22: =-CapEx_Pct_Rev_Active*IS!T41 -> -3120.358 | U22: =-CapEx_Pct_Rev_Active*IS!U41 -> -3012.7595 | V22: =-CapEx_Pct_Rev_Active*IS!V41 -> -3308.1614 | W22: n/a (blends a real FY2026 actual quarter -- which lacks quarterly D&A/CapEx/debt-roll disclosure and whose successor quarter's own roll-forward prior is NOT this actual quarter -- with modeled quarters; see the individual quarter columns for full detail) | Y22: n/a | AB22: =-CapEx_Pct_Rev_Active*IS!AB41 -> -3060.6674 | AC22: =-CapEx_Pct_Rev_Active*IS!AC41 -> -3360.7667 | AD22: n/a (blends a real FY2026 actual quarter -- which lacks quarterly D&A/CapEx/debt-roll disclosure and whose successor quarter's own roll-forward prior is NOT this actual quarter -- with modeled quarters; see the individual quarter columns for full detail) | AF22: =-CapEx_Pct_Rev_Active*IS!AF41 -> -4285.2538 | AG22: =-CapEx_Pct_Rev_Active*IS!AG41 -> -3269.7229 | AH22: =-CapEx_Pct_Rev_Active*IS!AH41 -> -3156.9739 | AI22: =-CapEx_Pct_Rev_Active*IS!AI41 -> -3466.516 | AJ22: =AF22+AG22+AH22+AI22 -> -14178.467
A23: Cash generated by/(used in) investing activities ($M) | B23: n/a | C23: n/a | D23: n/a | E23: n/a | F23: n/a | G23: n/a | H23: n/a | I23: n/a | J23: n/a | K23: n/a | L23: =L22 -> -3992.8269 | M23: =M22 -> -3046.5961 | N23: =N22 -> -2941.5411 | O23: =O22 -> -3229.96 | P23: =P22 -> -13210.924 | Q23: n/a | T23: =T22 -> -3120.358 | U23: =U22 -> -3012.7595 | V23: =V22 -> -3308.1614 | W23: n/a (blends a real FY2026 actual quarter -- which lacks quarterly D&A/CapEx/debt-roll disclosure and whose successor quarter's own roll-forward prior is NOT this actual quarter -- with modeled quarters; see the individual quarter columns for full detail) | Y23: n/a | AB23: =AB22 -> -3060.6674 | AC23: =AC22 -> -3360.7667 | AD23: n/a (blends a real FY2026 actual quarter -- which lacks quarterly D&A/CapEx/debt-roll disclosure and whose successor quarter's own roll-forward prior is NOT this actual quarter -- with modeled quarters; see the individual quarter columns for full detail) | AF23: =AF22 -> -4285.2538 | AG23: =AG22 -> -3269.7229 | AH23: =AH22 -> -3156.9739 | AI23: =AI22 -> -3466.516 | AJ23: =AJ22 -> -14178.467
A24: FINANCING ACTIVITIES
A25: Repurchases of common stock ($M) | B25: -20139 | C25: -23205 | D25: -26522 | E25: -25083 | F25: -23606 | G25: -25898 | H25: -21075 | I25: -20132 | J25: -24701 | K25: -12288 | L25: =-Buyback_Pct_FCF_Active*L32 -> -40128.61 | M25: =-Buyback_Pct_FCF_Active*M32 -> -18283.869 | N25: =-Buyback_Pct_FCF_Active*N32 -> -23539.412 | O25: =-Buyback_Pct_FCF_Active*O32 -> -28786.835 | P25: =L25+M25+N25+O25 -> -110738.73 | Q25: =J25 -> -24701 | T25: =-Buyback_Pct_FCF_Active*T32 -> -20695.019 | U25: =-Buyback_Pct_FCF_Active*U32 -> -25330.451 | V25: =-Buyback_Pct_FCF_Active*V32 -> -30824.652 | W25: =Q25+T25+U25+V25 -> -101551.12 | Y25: =K25 -> -12288 | AB25: =-Buyback_Pct_FCF_Active*AB32 -> -22427.881 | AC25: =-Buyback_Pct_FCF_Active*AC32 -> -28893.901 | AD25: =Q25+Y25+AB25+AC25 -> -88310.782 | AF25: =-Buyback_Pct_FCF_Active*AF32 -> -43708.141 | AG25: =-Buyback_Pct_FCF_Active*AG32 -> -20159.161 | AH25: =-Buyback_Pct_FCF_Active*AH32 -> -25643.035 | AI25: =-Buyback_Pct_FCF_Active*AI32 -> -31243.036 | AJ25: =AF25+AG25+AH25+AI25 -> -120753.37
A26: Dividends and dividend equivalents paid ($M) | B26: -3825 | C26: -3710 | D26: -3895 | E26: -3804 | F26: -3856 | G26: -3758 | H26: -3945 | I26: -3862 | J26: -3921 | K26: -3822 | L26: =-Dividend_Payout_Active*L15 -> -5512.6167 | M26: =-Dividend_Payout_Active*M15 -> -4206.222 | N26: =-Dividend_Payout_Active*N15 -> -4061.1799 | O26: =-Dividend_Payout_Active*O15 -> -4459.3797 | P26: =L26+M26+N26+O26 -> -18239.398 | Q26: =J26 -> -3921 | T26: =-Dividend_Payout_Active*T15 -> -4518.8486 | U26: =-Dividend_Payout_Active*U15 -> -4363.0263 | V26: =-Dividend_Payout_Active*V15 -> -4790.8222 | W26: =Q26+T26+U26+V26 -> -17593.697 | Y26: =K26 -> -3822 | AB26: =-Dividend_Payout_Active*AB15 -> -4088.8381 | AC26: =-Dividend_Payout_Active*AC15 -> -4489.7497 | AD26: =Q26+Y26+AB26+AC26 -> -16321.588 | AF26: =-Dividend_Payout_Active*AF15 -> -5998.1783 | AG26: =-Dividend_Payout_Active*AG15 -> -4576.714 | AH26: =-Dividend_Payout_Active*AH15 -> -4418.8963 | AI26: =-Dividend_Payout_Active*AI15 -> -4852.1702 | AJ26: =AF26+AG26+AH26+AI26 -> -19845.959
A27: Net debt issuance/(repayment) ($M) | B27: n/a | C27: n/a | D27: n/a | E27: n/a | F27: n/a | G27: n/a | H27: n/a | I27: n/a | J27: n/a | K27: n/a | L27: =Debt_Roll_Active -> 0 | M27: =Debt_Roll_Active -> 0 | N27: =Debt_Roll_Active -> 0 | O27: =Debt_Roll_Active -> 0 | P27: =L27+M27+N27+O27 -> 0 | Q27: n/a | T27: =Debt_Roll_Active -> 0 | U27: =Debt_Roll_Active -> 0 | V27: =Debt_Roll_Active -> 0 | W27: n/a (blends a real FY2026 actual quarter -- which lacks quarterly D&A/CapEx/debt-roll disclosure and whose successor quarter's own roll-forward prior is NOT this actual quarter -- with modeled quarters; see the individual quarter columns for full detail) | Y27: n/a | AB27: =Debt_Roll_Active -> 0 | AC27: =Debt_Roll_Active -> 0 | AD27: n/a (blends a real FY2026 actual quarter -- which lacks quarterly D&A/CapEx/debt-roll disclosure and whose successor quarter's own roll-forward prior is NOT this actual quarter -- with modeled quarters; see the individual quarter columns for full detail) | AF27: =Debt_Roll_Active -> 0 | AG27: =Debt_Roll_Active -> 0 | AH27: =Debt_Roll_Active -> 0 | AI27: =Debt_Roll_Active -> 0 | AJ27: =AF27+AG27+AH27+AI27 -> 0
A28: Cash used in financing activities ($M) | B28: n/a | C28: n/a | D28: n/a | E28: n/a | F28: n/a | G28: n/a | H28: n/a | I28: n/a | J28: n/a | K28: n/a | L28: =L25+L26+L27 -> -45641.226 | M28: =M25+M26+M27 -> -22490.091 | N28: =N25+N26+N27 -> -27600.592 | O28: =O25+O26+O27 -> -33246.215 | P28: =P25+P26+P27 -> -128978.12 | Q28: n/a | T28: =T25+T26+T27 -> -25213.868 | U28: =U25+U26+U27 -> -29693.477 | V28: =V25+V26+V27 -> -35615.474 | W28: n/a (blends a real FY2026 actual quarter -- which lacks quarterly D&A/CapEx/debt-roll disclosure and whose successor quarter's own roll-forward prior is NOT this actual quarter -- with modeled quarters; see the individual quarter columns for full detail) | Y28: n/a | AB28: =AB25+AB26+AB27 -> -26516.719 | AC28: =AC25+AC26+AC27 -> -33383.65 | AD28: n/a (blends a real FY2026 actual quarter -- which lacks quarterly D&A/CapEx/debt-roll disclosure and whose successor quarter's own roll-forward prior is NOT this actual quarter -- with modeled quarters; see the individual quarter columns for full detail) | AF28: =AF25+AF26+AF27 -> -49706.319 | AG28: =AG25+AG26+AG27 -> -24735.875 | AH28: =AH25+AH26+AH27 -> -30061.931 | AI28: =AI25+AI26+AI27 -> -36095.206 | AJ28: =AJ25+AJ26+AJ27 -> -140599.33
A29: Net increase/(decrease) in cash ($M) | B29: n/a | C29: =BS!C9-BS!B9 -> -8065 | D29: =BS!D9-BS!C9 -> -7130 | E29: =BS!E9-BS!D9 -> 4378 | F29: =BS!F9-BS!E9 -> 356 | G29: =BS!G9-BS!F9 -> -2137 | H29: =BS!H9-BS!G9 -> 8107 | I29: =BS!I9-BS!H9 -> -335 | J29: =BS!J9-BS!I9 -> 9383 | K29: =BS!K9-BS!J9 -> 255 | L29: =L20+L23+L28 -> -1053.8823 | M29: =M20+M23+M28 -> -2174.681 | N29: =N20+N23+N28 -> -1445.6897 | O29: =O20+O23+O28 -> -1260.8425 | P29: =P30-P13 -> -5935.0955 | Q29: =BS!Q9-BS!I9 -> 9383 | T29: =T20+T23+T28 -> -2219.402 | U29: =U20+U23+U28 -> -1548.5317 | V29: =V20+V23+V28 -> -1365.8608 | W29: =W30-W13 -> -6187.6768 | Y29: =BS!Y9-BS!J9 -> 255 | AB29: =AB20+AB23+AB28 -> -1596.8513 | AC29: =AC20+AC23+AC28 -> -1279.3163 | AD29: =AD30-AD13 -> -6149.4518 | AF29: =AF20+AF23+AF28 -> -1141.7182 | AG29: =AG20+AG23+AG28 -> -2336.8072 | AH29: =AH20+AH23+AH28 -> -1569.6702 | AI29: =AI20+AI23+AI28 -> -1380.7218 | AJ29: =AJ30-AJ13 -> -6428.9174
A30: Cash, end of period ($M) | B30: =BS!B9 -> 40760 | C30: =BS!C9 -> 32695 | D30: =BS!D9 -> 25565 | E30: =BS!E9 -> 29943 | F30: =BS!F9 -> 30299 | G30: =BS!G9 -> 28162 | H30: =BS!H9 -> 36269 | I30: =BS!I9 -> 35934 | ... K30: =BS!K9 -> 45572 | L30: =L13+L29 -> 34880.118 | M30: =M13+M29 -> 32705.437 | N30: =N13+N29 -> 31259.747 | O30: =O13+O29 -> 29998.905 | P30: =BS!O9 -> 29998.905 | Q30: =BS!Q9 -> 45317 | T30: =T13+T29 -> 32660.716 | U30: =U13+U29 -> 31112.184 | V30: =V13+V29 -> 29746.323 | W30: =BS!V9 -> 29746.323 | Y30: =BS!Y9 -> 45572 | AB30: =AB13+AB29 -> 31063.864 | AC30: =AC13+AC29 -> 29784.548 | AD30: =BS!AC9 -> 29784.548 | AF30: =AF13+AF29 -> 28642.83 | AG30: =AG13+AG29 -> 26306.023 | AH30: =AH13+AH29 -> 24736.353 | AI30: =AI13+AI29 -> 23355.631 | AJ30: =BS!AI9 -> 23355.631
A32: Memo: Free Cash Flow (OCF - CapEx) ($M) | B32: n/a | C32: n/a | D32: n/a | E32: n/a | F32: n/a | G32: n/a | H32: n/a | I32: n/a | J32: n/a | K32: n/a | L32: =L20+L23 -> 44587.344 | M32: =M20+M23 -> 20315.41 | N32: =N20+N23 -> 26154.902 | O32: =O20+O23 -> 31985.372 | P32: =P20+P23 -> 123043.03 | Q32: n/a | T32: =T20+T23 -> 22994.466 | U32: =U20+U23 -> 28144.946 | V32: =V20+V23 -> 34249.614 | W32: n/a (blends a real FY2026 actual quarter -- which lacks quarterly D&A/CapEx/debt-roll disclosure and whose successor quarter's own roll-forward prior is NOT this actual quarter -- with modeled quarters; see the individual quarter columns for full detail) | Y32: n/a | AB32: =AB20+AB23 -> 24919.868 | AC32: =AC20+AC23 -> 32104.334 | AD32: n/a (blends a real FY2026 actual quarter -- which lacks quarterly D&A/CapEx/debt-roll disclosure and whose successor quarter's own roll-forward prior is NOT this actual quarter -- with modeled quarters; see the individual quarter columns for full detail) | AF32: =AF20+AF23 -> 48564.601 | AG32: =AG20+AG23 -> 22399.068 | AH32: =AH20+AH23 -> 28492.261 | AI32: =AI20+AI23 -> 34714.484 | AJ32: =AJ20+AJ23 -> 134170.41
A34: Color legend: blue = real historical literal/derived input (Net income mirrors the IS tab; Repurchases/Dividends are real discrete-quarter disclosures; working-capital changes are real period-over-period BS deltas); black on light green = forecast formula output (driven by the Drivers tab's Active named ranges -- CapEx_Pct_Rev_Active, Buyback_Pct_FCF_Active, Dividend_Payout_Active, Debt_Roll_Active -- and this tab's own D&A% assumption, row 9); light grey = subtotal/Total column; 'n/a' = not available at discrete-quarter grain historically, or (Total columns W/AD only) a blend of a real actual quarter with modeled quarters that would otherwise silently misstate the figure. 'Cash, end of period' is the figure BS!Cash pulls from for every forecast column -- never an independent plug. BULL-SCENARIO CASH NOTE: under Bull, this line's decline is visible starting from the very first forecast quarter (FY26 Q1 AOP, col L) and is continuous and steady through every subsequent vintage column -- Cash turns NEGATIVE starting FY2027 Q3 (col AH) and remains negative through FY2027 Q4 (col AI): two consecutive negative quarters, not a single Q4 tail event. Root cause: Bull sets Buyback_Pct_FCF_Active to 100% (consuming the entire FCF pool every quarter) with dividends layered on top and no revolver/cash-floor mechanic modeled -- a deterministic drain baked in from quarter one. This is NOT a balance-check bug: BS!row39 holds at effectively exact zero at every column along this entire path under Bull, exactly as it does in Base and Bear.

Sheet Forecast Bridge
A1: Apple Inc. -- Driver-Based Rolling Forecast Model: FORECAST BRIDGE (Waterfall Variance Analysis)
A2: Consumes: IS tab (FY2026 Approved AOP / Q1 Actual / Q1 Forecast Update / Q2 Actual / Q3 Reforecast columns, and each vintage's Annual Build helper rows 15-31 / 71-78 / 92-99) built by Tasks 12-14, and the Drivers tab's Units Growth / ASP YoY / FX Impact / Mix Impact Active named ranges (Task 11). Nothing on this tab is fabricated -- every cell is a live formula referencing IS-tab or Drivers-tab cells; toggling Drivers!B6 (Scenario switch) recalculates every number below (bridges are most meaningful under Base, since only Base's actual-vs-forecast quarters are REAL reported variances -- see the caveat below and each waterfall's own description).
A3: THREE WATERFALLS, one per real "vs." step in the vintage chain: (A) FY2026 Approved AOP Q1 -> Q1 FY2026 Actual (ties to IS!R41, a REAL actual-vs-plan variance); (B) Q1 Forecast Update's own Q2 -> Q2 FY2026 Actual (ties to IS!Z41, also REAL); (C) Q1 Forecast Update's Q3+Q4 forecast -> Q3 Reforecast's Q3+Q4 forecast (ties to a value computed on this tab, (IS!AB41+IS!AC41)-(IS!U41+IS!V41); NOT a pre-built IS-tab variance column, since Q3-Q4 FY2026 have not happened yet). DEVIATION FROM THE TASK 17 BRIEF'S LITERAL WORDING, DOCUMENTED PER THE BRIEF'S OWN INSTRUCTION: the brief's Step 1 names "Q1 Forecast Update -> Q3 Reforecast" as the third comparison; that is followed here for WHICH TWO VINTAGES to compare, but the comparison is scoped to the Q3-Q4 quarters both vintages actually forecast (IS! cols U:V vs AB:AC), NOT the FY26 Total columns (IS!W vs IS!AD). The Totals were considered and rejected: IS!W = Q1 Actual + Q1 FU's own (now-superseded) Q2 FORECAST + Q3-Q4 FU forecast, while IS!AD = Q1 Actual + REAL Q2 Actual + Q3-Q4 RF forecast -- their Q2 components differ (forecast vs. real actual), so IS!AD-IS!W = Z41 (Waterfall B's own Q2 variance) PLUS the Q3-Q4 forecast revision; comparing Totals would silently double-count Waterfall B inside Waterfall C. Using only Q3+Q4 isolates the clean, non-overlapping forward-forecast revision that Task 14's own Driver Adjustment Log (IS! rows 84-90) and Annual Build (rows 92-99) actually produced: the Q2-beat uplift ratio (IS!G86) re-applied to Q1 FU's Q3-Q4 forecast.
A4: DECOMPOSITION METHOD: (1) SEGMENT SPLIT -- each waterfall's total $ variance is split across iPhone/Mac/iPad/Wearables/Services using the EXACT per-segment dollar figures Tasks 13/14 already computed in the IS tab's Annual Build helper rows (Waterfall A: IS! rows 73-77 minus rows 18/21/24/27/30; Waterfall B: rows 94-98 minus rows 73-77; Waterfall C: the same rows 94-98 minus 73-77 delta, re-seasonalized onto Q3+Q4 only via IS!D12:E12) -- not re-derived: Tasks 13/14's own Driver Adjustment Logs (IS! rows 65/86) apply each vintage's real $ beat as a UNIFORM % uplift to every segment's prior-vintage annual revenue, because real segment-level revenue is not disclosed at quarterly grain (IS! row 65/86 notes) -- this proportional allocation is Task 13/14's own method, read directly off the sheet. (2) UNITS/ASP/FX/MIX SPLIT -- since the Driver Adjustment Logs treat revenue as a single "blended Units x ASP x FX x Mix growth proxy" and explicitly decline to attribute the beat to a specific driver, each segment's $ contribution is further split using the Drivers tab's OWN Active assumption weights for that segment/scenario: weight_x = ABS(driver x's Active rate) / SUM(ABS(all 4 drivers' Active rates)) -- i.e. the beat is assumed to carry the same relative Units/ASP/FX/Mix composition as management's own plan for that segment (rows 11-15). Weights sum to exactly 100% by construction (column J), so there is NO residual/plug line -- every dollar of variance is fully allocated, and each waterfall's CHECK row (independently summing every Units+ASP+FX+Mix cell across all 5 segments) confirms this ties to the IS-tab total.
A6: CAVEAT (shown here, not just on the Drivers tab): segment-level Units and ASP/ARPU figures throughout this workbook -- including every Units $ / ASP $ column on THIS tab -- are IMPLIED / ESTIMATED, not Apple-disclosed data (Apple has not disclosed iPhone/Mac/iPad/Wearables unit shipments since FY2018; see Drivers! row 4 and rows 12/15/18/21/26 Source/Notes). The Units/ASP/FX/Mix SPLIT below is a further estimate layered on top of that: real quarterly revenue is only disclosed on a CONSOLIDATED basis (no segment split), so neither the segment allocation nor the driver split below is independently observed -- both are modeled allocations, fully formula-traceable to the Drivers tab's Active assumptions and the IS tab's own Driver Adjustment Logs, but NOT real disclosed splits. Treat every $ figure on this tab as directional attribution, not an audited actual-driver breakdown.
A8: DRIVER WEIGHT REFERENCE (Base/Bull/Bear-cascading; used to split each segment's $ variance into Units/ASP/FX/Mix sub-components below)
A9: weight_x = ABS(that driver's Active rate) / SUM(ABS(all four Active rates)) for the SAME segment -- e.g. iPhone's Units weight = ABS(iPhone_Units_Growth_Active) / (ABS(iPhone_Units_Growth_Active)+ABS(iPhone_ASP_YoY_Active)+ABS(FX_Impact_Active)+ABS(Mix_Impact_Active)). FX Impact and Mix Impact are consolidated (single Drivers-tab Active cells, not segment-specific), so they repeat across all 5 rows. Services uses Installed Base Growth in place of "Units" and ARPU YoY in place of "ASP" (same Units x ASP-equivalent structure Drivers! rows 24-26 already use).
A10: Segment | B10: Units/Installed-Base Growth (Active, rate) | C10: ASP/ARPU YoY (Active, rate) | D10: FX Impact (Active, rate) | E10: Mix Impact (Active, rate) | F10: Units weight | G10: ASP weight | H10: FX weight | I10: Mix weight | J10: Check (sums to 100%)
A11: iPhone | B11: =iPhone_Units_Growth_Active -> 0.015 | C11: =iPhone_ASP_YoY_Active -> 0.02 | D11: =FX_Impact_Active -> 0 | E11: =Mix_Impact_Active -> 0 | F11: =IFERROR(ABS(B11)/(ABS(B11)+ABS(C11)+ABS(D11)+ABS(E11)),0.25) -> 0.42857143 | G11: =IFERROR(ABS(C11)/(ABS(B11)+ABS(C11)+ABS(D11)+ABS(E11)),0.25) -> 0.57142857 | H11: =IFERROR(ABS(D11)/(ABS(B11)+ABS(C11)+ABS(D11)+ABS(E11)),0.25) -> 0 | I11: =IFERROR(ABS(E11)/(ABS(B11)+ABS(C11)+ABS(D11)+ABS(E11)),0.25) -> 0 | J11: =SUM(F11:I11) -> 1
A12: Mac | B12: =Mac_Units_Growth_Active -> 0.04 | C12: =Mac_ASP_YoY_Active -> 0.02 | D12: =FX_Impact_Active -> 0 | E12: =Mix_Impact_Active -> 0 | F12: =IFERROR(ABS(B12)/(ABS(B12)+ABS(C12)+ABS(D12)+ABS(E12)),0.25) -> 0.66666667 | G12: =IFERROR(ABS(C12)/(ABS(B12)+ABS(C12)+ABS(D12)+ABS(E12)),0.25) -> 0.33333333 | H12: =IFERROR(ABS(D12)/(ABS(B12)+ABS(C12)+ABS(D12)+ABS(E12)),0.25) -> 0 | I12: =IFERROR(ABS(E12)/(ABS(B12)+ABS(C12)+ABS(D12)+ABS(E12)),0.25) -> 0 | J12: =SUM(F12:I12) -> 1
A13: iPad | B13: =iPad_Units_Growth_Active -> 0.01 | C13: =iPad_ASP_YoY_Active -> 0.015 | D13: =FX_Impact_Active -> 0 | E13: =Mix_Impact_Active -> 0 | F13: =IFERROR(ABS(B13)/(ABS(B13)+ABS(C13)+ABS(D13)+ABS(E13)),0.25) -> 0.4 | G13: =IFERROR(ABS(C13)/(ABS(B13)+ABS(C13)+ABS(D13)+ABS(E13)),0.25) -> 0.6 | H13: =IFERROR(ABS(D13)/(ABS(B13)+ABS(C13)+ABS(D13)+ABS(E13)),0.25) -> 0 | I13: =IFERROR(ABS(E13)/(ABS(B13)+ABS(C13)+ABS(D13)+ABS(E13)),0.25) -> 0 | J13: =SUM(F13:I13) -> 1
A14: Wearables, Home and Accessories | B14: =Wearables_Home_and_Accessories_Units_Growth_Active -> -0.01 | C14: =Wearables_Home_and_Accessories_ASP_YoY_Active -> 0.01 | D14: =FX_Impact_Active -> 0 | E14: =Mix_Impact_Active -> 0 | F14: =IFERROR(ABS(B14)/(ABS(B14)+ABS(C14)+ABS(D14)+ABS(E14)),0.25) -> 0.5 | G14: =IFERROR(ABS(C14)/(ABS(B14)+ABS(C14)+ABS(D14)+ABS(E14)),0.25) -> 0.5 | H14: =IFERROR(ABS(D14)/(ABS(B14)+ABS(C14)+ABS(D14)+ABS(E14)),0.25) -> 0 | I14: =IFERROR(ABS(E14)/(ABS(B14)+ABS(C14)+ABS(D14)+ABS(E14)),0.25) -> 0 | J14: =SUM(F14:I14) -> 1
A15: Services | B15: =Services_InstalledBase_Growth_Active -> 0.075 | C15: =Services_ARPU_YoY_Active -> 0.05 | D15: =FX_Impact_Active -> 0 | E15: =Mix_Impact_Active -> 0 | F15: =IFERROR(ABS(B15)/(ABS(B15)+ABS(C15)+ABS(D15)+ABS(E15)),0.25) -> 0.6 | G15: =IFERROR(ABS(C15)/(ABS(B15)+ABS(C15)+ABS(D15)+ABS(E15)),0.25) -> 0.4 | H15: =IFERROR(ABS(D15)/(ABS(B15)+ABS(C15)+ABS(D15)+ABS(E15)),0.25) -> 0 | I15: =IFERROR(ABS(E15)/(ABS(B15)+ABS(C15)+ABS(D15)+ABS(E15)),0.25) -> 0 | J15: =SUM(F15:I15) -> 1
A16: Under the delivered Base scenario, FX Impact and Mix Impact are both 0% (Drivers! rows 29-30), so every segment's Units/ASP/FX/Mix split above collapses to a pure Units-vs-ASP split with $0 FX/Mix contribution in every waterfall below -- this is a direct, mechanical consequence of the Base scenario's own assumptions (not a bridge-method choice), and the FX/Mix columns activate automatically with non-zero contributions if the Scenario switch (Drivers!B6) is set to Bull or Bear.
A17: WATERFALL A: FY2026 Approved AOP (Q1) -> Q1 FY2026 Actual (REAL variance; ties to IS!R41)
A18: Total $ variance = IS!R41 (Q1 vs AOP Variance $), a REAL actual-vs-plan number (Q1 FY2026 actual net sales vs. the Approved AOP Q1 assumption). Segment $ variance = IS! rows 73-77 (Q1 FU's grossed-up annual revenue) minus IS! rows 18/21/24/27/30 (AOP annual revenue) -- Task 13's own formulas; these five deltas sum to R41 exactly because Task 13 defined the uplift ratio (IS!G65) as R41 / AOP Annual Total (IS!B31).
A19: Segment | B19: Units $ | C19: ASP $ | D19: FX $ | E19: Mix $ | F19: Total Segment $ Variance | G19: % of Total Variance
A20: iPhone | B20: =$F20*F11 -> 2251.4851 | C20: =$F20*G11 -> 3001.9801 | D20: =$F20*H11 -> 0 | E20: =$F20*I11 -> 0 | F20: ='IS'!B73-'IS'!B18 -> 5253.4652 | G20: =IFERROR(F20/$F$25,0) -> 0.49273855
A21: Mac | B21: =$F21*F12 -> 577.1552 | C21: =$F21*G12 -> 288.5776 | D21: =$F21*H12 -> 0 | E21: =$F21*I12 -> 0 | F21: ='IS'!B74-'IS'!B21 -> 865.7328 | G21: =IFERROR(F21/$F$25,0) -> 0.081199724
A22: iPad | B22: =$F22*F13 -> 278.21427 | C22: =$F22*G13 -> 417.32141 | D22: =$F22*H13 -> 0 | E22: =$F22*I13 -> 0 | F22: ='IS'!B75-'IS'!B24 -> 695.53569 | G22: =IFERROR(F22/$F$25,0) -> 0.065236417
A23: Wearables, Home and Accessories | B23: =$F23*F14 -> 431.9583 | C23: =$F23*G14 -> 431.9583 | D23: =$F23*H14 -> 0 | E23: =$F23*I14 -> 0 | F23: ='IS'!B76-'IS'!B27 -> 863.91659 | G23: =IFERROR(F23/$F$25,0) -> 0.081029377
A24: Services | B24: =$F24*F15 -> 1789.8719 | C24: =$F24*G15 -> 1193.248 | D24: =$F24*H15 -> 0 | E24: =$F24*I15 -> 0 | F24: ='IS'!B77-'IS'!B30 -> 2983.1199 | G24: =IFERROR(F24/$F$25,0) -> 0.27979593
A25: TOTAL (sum of 5 segments) | B25: =SUM(B20:B24) -> 5328.6848 | C25: =SUM(C20:C24) -> 5333.0854 | D25: =SUM(D20:D24) -> 0 | E25: =SUM(E20:E24) -> 0 | F25: =SUM(F20:F24) -> 10661.77 | G25: =SUM(G20:G24) -> 1
A26: CHECK: SUM of all Units+ASP+FX+Mix sub-components (all 5 segments, independent of the TOTAL row above) vs. the IS-tab total variance -- Bridge Sum | IS Tab Total | Difference (must be $0) | E26: =SUM(B20:E24) -> 10661.77 | F26: ='IS'!R41 -> 10661.77 | G26: =E26-F26 -> 7.2759576e-12 | H26: IS!R41 = Q1 vs AOP Variance ($), row 41 column R.
A28: WATERFALL B: Q1 Forecast Update's own Q2 -> Q2 FY2026 Actual (REAL variance; ties to IS!Z41)
A29: Total $ variance = IS!Z41 (Q2 vs Q1 FU Variance $), a REAL actual-vs-plan number (Q2 FY2026 actual net sales vs. the Q1 Forecast Update's own Q2 assumption). Segment $ variance = IS! rows 94-98 (Q3 Reforecast's grossed-up annual revenue) minus IS! rows 73-77 (Q1 FU annual revenue) -- Task 14's own formulas; these five deltas sum to Z41 exactly because Task 14 defined the uplift ratio (IS!G86) as Z41 / Q1 FU Annual Total (IS!B78).
A30: Segment | B30: Units $ | C30: ASP $ | D30: FX $ | E30: Mix $ | F30: Total Segment $ Variance | G30: % of Total Variance
A31: iPhone | B31: =$F31*F11 -> 1514.5515 | C31: =$F31*G11 -> 2019.402 | D31: =$F31*H11 -> 0 | E31: =$F31*I11 -> 0 | F31: ='IS'!B94-'IS'!B73 -> 3533.9536 | G31: =IFERROR(F31/$F$36,0) -> 0.49273855
A32: Mac | B32: =$F32*F12 -> 388.24654 | C32: =$F32*G12 -> 194.12327 | D32: =$F32*H12 -> 0 | E32: =$F32*I12 -> 0 | F32: ='IS'!B95-'IS'!B74 -> 582.36981 | G32: =IFERROR(F32/$F$36,0) -> 0.081199724
A33: iPad | B33: =$F33*F13 -> 187.15196 | C33: =$F33*G13 -> 280.72795 | D33: =$F33*H13 -> 0 | E33: =$F33*I13 -> 0 | F33: ='IS'!B96-'IS'!B75 -> 467.87991 | G33: =IFERROR(F33/$F$36,0) -> 0.065236417
A34: Wearables, Home and Accessories | B34: =$F34*F14 -> 290.57403 | C34: =$F34*G14 -> 290.57403 | D34: =$F34*H14 -> 0 | E34: =$F34*I14 -> 0 | F34: ='IS'!B97-'IS'!B76 -> 581.14806 | G34: =IFERROR(F34/$F$36,0) -> 0.081029377
A35: Services | B35: =$F35*F15 -> 1204.029 | C35: =$F35*G15 -> 802.68598 | D35: =$F35*H15 -> 0 | E35: =$F35*I15 -> 0 | F35: ='IS'!B98-'IS'!B77 -> 2006.715 | G35: =IFERROR(F35/$F$36,0) -> 0.27979593
A36: TOTAL (sum of 5 segments) | B36: =SUM(B31:B35) -> 3584.553 | C36: =SUM(C31:C35) -> 3587.5133 | D36: =SUM(D31:D35) -> 0 | E36: =SUM(E31:E35) -> 0 | F36: =SUM(F31:F35) -> 7172.0663 | G36: =SUM(G31:G35) -> 1
A37: CHECK: SUM of all Units+ASP+FX+Mix sub-components (all 5 segments, independent of the TOTAL row above) vs. the IS-tab total variance -- Bridge Sum | IS Tab Total | Difference (must be $0) | E37: =SUM(B31:E35) -> 7172.0663 | F37: ='IS'!Z41 -> 7172.0663 | G37: =E37-F37 -> 4.7293724e-11 | H37: IS!Z41 = Q2 vs Q1 FU Variance ($), row 41 column Z.
A39: WATERFALL C: Q1 Forecast Update's Q3+Q4 -> Q3 Reforecast's Q3+Q4 (forecast revision; ties to a value computed on this tab, not a pre-built IS-tab column -- see row 3 deviation note)
A40: Total $ variance = (IS!AB41+IS!AC41) - (IS!U41+IS!V41): Q3 Reforecast's Q3+Q4 forecast minus Q1 Forecast Update's own Q3+Q4 forecast for the SAME two future quarters -- a forecast-REVISION, not an actual-vs-plan variance (Q3-Q4 FY2026 have not happened yet). See row 3 above for why this is scoped to Q3+Q4 only, not the FY26 Total columns. Segment $ variance = (IS! AB+AC) minus (IS! U+V) per segment, which algebraically equals Waterfall B's own segment delta (IS! rows 94-98 minus 73-77) multiplied by the Q3+Q4 seasonality weight (IS!D12+IS!E12) -- Waterfall C is not new information: it is Waterfall B's real Q2 beat, re-seasonalized onto the two quarters it actually gets applied to going forward.
A41: Segment | B41: Units $ | C41: ASP $ | D41: FX $ | E41: Mix $ | F41: Total Segment $ Variance | G41: % of Total Variance
A42: iPhone | B42: =$F42*F11 -> 707.52479 | C42: =$F42*G11 -> 943.36639 | D42: =$F42*H11 -> 0 | E42: =$F42*I11 -> 0 | F42: =('IS'!AB35+'IS'!AC35)-('IS'!U35+'IS'!V35) -> 1650.8912 | G42: =IFERROR(F42/$F$47,0) -> 0.49273855
A43: Mac | B43: =$F43*F12 -> 181.3699 | C43: =$F43*G12 -> 90.684948 | D43: =$F43*H12 -> 0 | E43: =$F43*I12 -> 0 | F43: =('IS'!AB36+'IS'!AC36)-('IS'!U36+'IS'!V36) -> 272.05484 | G43: =IFERROR(F43/$F$47,0) -> 0.081199724
A44: iPad | B44: =$F44*F13 -> 87.428293 | C44: =$F44*G13 -> 131.14244 | D44: =$F44*H13 -> 0 | E44: =$F44*I13 -> 0 | F44: =('IS'!AB37+'IS'!AC37)-('IS'!U37+'IS'!V37) -> 218.57073 | G44: =IFERROR(F44/$F$47,0) -> 0.065236417
A45: Wearables, Home and Accessories | B45: =$F45*F14 -> 135.74205 | C45: =$F45*G14 -> 135.74205 | D45: =$F45*H14 -> 0 | E45: =$F45*I14 -> 0 | F45: =('IS'!AB38+'IS'!AC38)-('IS'!U38+'IS'!V38) -> 271.4841 | G45: =IFERROR(F45/$F$47,0) -> 0.081029377
A46: Services | B46: =$F46*F15 -> 562.46377 | C46: =$F46*G15 -> 374.97584 | D46: =$F46*H15 -> 0 | E46: =$F46*I15 -> 0 | F46: =('IS'!AB40+'IS'!AC40)-('IS'!U40+'IS'!V40) -> 937.43961 | G46: =IFERROR(F46/$F$47,0) -> 0.27979593
A47: TOTAL (sum of 5 segments) | B47: =SUM(B42:B46) -> 1674.5288 | C47: =SUM(C42:C46) -> 1675.9117 | D47: =SUM(D42:D46) -> 0 | E47: =SUM(E42:E46) -> 0 | F47: =SUM(F42:F46) -> 3350.4405 | G47: =SUM(G42:G46) -> 1
A48: CHECK: SUM of all Units+ASP+FX+Mix sub-components (all 5 segments, independent of the TOTAL row above) vs. the IS-tab total variance -- Bridge Sum | IS Tab Total | Difference (must be $0) | E48: =SUM(B42:E46) -> 3350.4405 | F48: =('IS'!AB41+'IS'!AC41)-('IS'!U41+'IS'!V41) -> 3350.4405 | G48: =E48-F48 -> 1.6370905e-11 | H48: Computed here (not an IS-tab cell): (IS!AB41+IS!AC41) - (IS!U41+IS!V41).
A50: Color legend: dark title bar = tab title; blue section header = Driver Weight Reference block; orange/gold/teal section headers = Waterfall A/B/C respectively (orange and gold match the IS tab's own Q1-vs-AOP and Q2-vs-Q1FU variance column colors; teal matches the IS tab's Q3 Reforecast vintage color, signaling Waterfall C is a forecast revision, not a realized variance); light green fill = live formula referencing the IS tab's own Annual Build rows (never hardcoded); light grey = TOTAL row; light grey CHECK row with a green/red Difference cell (green = ties out exactly, red = does not -- conditional formatting, live). All $ figures in $M. Every Units/ASP/FX/Mix weight (rows 11-15) and every $ figure below is an ESTIMATE traceable to the Drivers tab's Active assumptions and the IS tab's own Driver Adjustment Log / Annual Build formulas -- not independently disclosed data (see the caveat in row 6).

Sheet Sensitivity
A1: Apple Inc. -- Driver-Based Rolling Forecast Model: SENSITIVITY ANALYSIS (FY2027 AOP)
A2: Consumes: Drivers tab (column D = Base scenario values for all 29 drivers -- NOT the Active column, and NOT whatever Drivers!B6 is currently set to, so this tab's baseline never moves when the live Scenario switch is toggled), and the IS/BS/CF tabs' FY2027 AOP formula chain built by Tasks 12/15/16 (IS! rows 107-123 & AF:AJ; CF! rows 13-32). Nothing on the Drivers/IS/BS/CF/Forecast Bridge tabs is read-modified -- every cell below is either a live formula link to an existing cell, or a fresh arithmetic formula built on this tab.
A3: METHOD: this sandbox has no Excel/LibreOffice install, so Excel's native what-if Data Table feature (TABLE() array formula) cannot be relied on here -- it only populates via a real spreadsheet engine's specific iterative recalculation, which the pure-Python `formulas` library used by recalc_and_cache.py does not implement; a native Data Table would show blank/stale cells in every headless read. Instead, BOTH Step 1 and Step 2 below are built as explicit, self-contained SHADOW formulas that replicate the FY2027 AOP's own formula chain using ordinary SUM/product/quotient formulas only (no TABLE() array formula, no what-if construct) -- fully real, inspectable, and independently recalculable, in this sandbox AND in real Excel if this file is later opened there.
A4: ISOLATION METHOD (Step 1): every scenario row holds all drivers at Drivers! column D (Base) EXCEPT ONE, which is manually offset by a single Swing Size input cell (row 49, default 1.0 percentage point) added or subtracted -- an explicit formula, never a hardcoded number. The FY2026 Exit Run-Rate anchors (IS! B107/B110/B113/B116/B119) and FY2026 Q4 beginning balances (BS! AC9/AC11/AC13/AC22) are pulled as FIXED live references (rows 11-22) -- they are upstream of the FY2027-specific driver application (built by the Q3 Reforecast vintage, Tasks 13-14) and are not touched by any of the 7 drivers tested here. "Gross Margin" is treated as ONE driver per the brief, applying the SAME swing to BOTH Products_GM_Active and Services_GM_Active simultaneously (the Drivers tab splits GM into two segments by design -- Task 11 -- so a single-driver swing must move both, or it silently narrows to only one segment's margin). IMPORTANT SCOPE LIMIT (verified by a toggle test, not assumed): unlike the BASE DRIVER VALUES block (rows 27-45, hard-locked to column D always), the FIXED REFERENCE anchors above are pulled from the LIVE IS/BS/CF tabs, so they reflect whatever scenario Drivers!B6 is CURRENTLY set to (Q1 Actual/Q1 Forecast Update/Q3 Reforecast all cascade off the Active column, per Tasks 12-14's own design) -- this tab's Step 1/Step 2 results are a pure "everything at Base" sensitivity ONLY when Drivers!B6 = "Base" (true for the delivered file, confirmed below). Re-deriving the full upstream Q1 Actual/Q1 FU/Q3 RF chain a second time in hardcoded-Base terms was judged out of scope for this task (the brief's own recommended approach asks to replicate "the relevant piece of the FY2027 AOP calculation chain," not the entire prior vintage history) -- flagged here, not silently glossed over. The Delta columns (AS:AV) stay a valid, internally consistent isolation of each driver's marginal effect regardless of Drivers!B6's position, since every one of the 15 rows below shares the same anchor.
A5: STRUCTURAL FINDING (verified, not hidden): this model's IS tab (Task 12) holds diluted share count FLAT for every forecast vintage (buyback-driven share reduction is explicitly out of the IS tab's scope, per its own row-3 note) -- so a Buyback % swing has ZERO effect on Operating Income/EPS below (it only moves Cash, via the CF tab's Financing section). Likewise Tax Rate is applied strictly below the Operating Income line, so a Tax Rate swing has ZERO OI impact but DOES move EPS/Cash/FCF. Both $0.00 results in the table below are real, mechanically correct formula outputs of the existing model -- not omissions or errors on this tab.
A6: SIMPLIFICATIONS (Step 2 -- see also the Step 2 section notes below): "Revenue growth %" is a SINGLE blended axis (Total FY2027 Net Sales = FY2026 Exit-Run-Rate anchor total x (1+g)), not a re-decomposition into 5 segment growth rates -- the standard simpler convention for a 2-variable data table, distinct from Step 1's per-driver isolation. Products:Services revenue MIX is held at Base proportions across the whole growth axis. "Gross Margin %" is a column OFFSET applied equally to both Products and Services GM% (same convention as Step 1's Gross Margin driver). R&D%/SG&A%/Tax Rate/Share count are held at Base throughout Step 2's grid (not axes of that table).
A8: FIXED REFERENCE VALUES -- live formula links to IS/BS/CF; upstream of the FY2027-specific driver application; NOT altered or swung by this tab
A9: These come from the Q3 Reforecast vintage (Tasks 13-14), already baked into the live model before any FY2027-specific driver is applied -- none of the 7 sensitivity drivers tested below can affect them, so they are safe to hold fixed while isolating each driver's FY2027-specific effect.
A10: Item | B10: Source Cell | C10: Value
A11: iPhone: FY2026 Exit Run-Rate Annualized Revenue ($M) | B11: IS!B107 | C11: =IS!B107 -> 225771.8
A12: Mac: FY2026 Exit Run-Rate Annualized Revenue ($M) | B12: IS!B110 | C12: =IS!B110 -> 37205.549
A13: iPad: FY2026 Exit Run-Rate Annualized Revenue ($M) | B13: IS!B113 | C13: =IS!B113 -> 29891.194
A14: Wearables: FY2026 Exit Run-Rate Annualized Revenue ($M) | B14: IS!B116 | C14: =IS!B116 -> 37127.496
A15: Services: FY2026 Exit Run-Rate Annualized Revenue ($M) | B15: IS!B119 | C15: =IS!B119 -> 128201.93
A16: Q4 Seasonality Weight (applied to every FY2027 AOP quarterly split) | B16: IS!E12 | C16: =IS!E12 -> 0.2444916
A17: Diluted Shares Outstanding, held flat (M) | B17: IS!K56 | C17: =IS!K56 -> 14715.423
A18: D&A (% of Net Sales), flat assumption | B18: CF!C9 | C18: =CF!C9 -> 0.029287294
A19: Cash, Beginning FY2027 (= Q4 FY2026 Q3 Reforecast ending cash) ($M) | B19: BS!AC9 | C19: =BS!AC9 -> 29784.548
A20: Accounts Receivable, Beginning FY2027 ($M) | B20: BS!AC11 | C20: =BS!AC11 -> 41076.037
A21: Inventory, Beginning FY2027 ($M) | B21: BS!AC13 | C21: =BS!AC13 -> 6314.4351
A22: Accounts Payable, Beginning FY2027 ($M) | B22: BS!AC22 | C22: =BS!AC22 -> 72616.004
A24: BASE-SCENARIO DRIVER VALUES -- Drivers! column D (Base), used for every driver NOT being swung in a given scenario row below, and for every non-axis assumption in Step 2's grid
A25: Always Drivers! column D specifically (never column G/Active) -- this tab's baseline is always Base scenario, independent of whatever Drivers!B6 is currently switched to, so results are reproducible regardless of the live model's scenario state.
A26: Driver | B26: Source Cell | C26: Base Value
A27: iPhone -- Units Growth % (SWUNG driver #1) | B27: Drivers!D10 | C27: =Drivers!D10 -> 0.015
A28: Mac -- Units Growth % (SWUNG driver #2) | B28: Drivers!D13 | C28: =Drivers!D13 -> 0.04
A29: iPad -- Units Growth % (fixed, never swung) | B29: Drivers!D16 | C29: =Drivers!D16 -> 0.01
A30: Wearables -- Units Growth % (fixed, never swung) | B30: Drivers!D19 | C30: =Drivers!D19 -> -0.01
A31: Services -- Installed Base Growth % (SWUNG driver #3) | B31: Drivers!D24 | C31: =Drivers!D24 -> 0.075
A32: FX Impact on Revenue % (SWUNG driver #4) | B32: Drivers!D29 | C32: =Drivers!D29 -> 0
A33: Mix Impact on Revenue % (fixed, never swung) | B33: Drivers!D30 | C33: =Drivers!D30 -> 0
A34: Products Gross Margin % (SWUNG driver #5a) | B34: Drivers!D33 | C34: =Drivers!D33 -> 0.37
A35: Services Gross Margin % (SWUNG driver #5b) | B35: Drivers!D34 | C35: =Drivers!D34 -> 0.755
A36: SG&A (% of Revenue) (fixed, never swung) | B36: Drivers!D37 | C36: =Drivers!D37 -> 0.066
A37: R&D (% of Revenue) (fixed, never swung) | B37: Drivers!D38 | C37: =Drivers!D38 -> 0.083
A38: Days Sales Outstanding (DSO) (fixed, never swung) | B38: Drivers!D41 | C38: =Drivers!D41 -> 33
A39: Days Inventory Outstanding (DIO) (fixed, never swung) | B39: Drivers!D42 | C39: =Drivers!D42 -> 10
A40: Days Payable Outstanding (DPO) (fixed, never swung) | B40: Drivers!D43 | C40: =Drivers!D43 -> 115
A41: CapEx (% of Revenue) (fixed, never swung) | B41: Drivers!D46 | C41: =Drivers!D46 -> 0.03
A42: Buyback ($ as % of Trailing FCF) (SWUNG driver #6) | B42: Drivers!D47 | C42: =Drivers!D47 -> 0.9
A43: Dividend Payout (% of Net Income) (fixed, never swung) | B43: Drivers!D48 | C43: =Drivers!D48 -> 0.15
A44: Effective Tax Rate % (SWUNG driver #7) | B44: Drivers!D49 | C44: =Drivers!D49 -> 0.16
A45: Debt Roll -- Net New Issuance/(Repayment) ($M) (fixed, never swung) | B45: Drivers!D50 | C45: =Drivers!D50 -> 0
A47: STEP 1 -- SCENARIO-DRIVEN SINGLE-DRIVER SENSITIVITY: FY2027 Operating Income / EPS / Cash / Free Cash Flow impact of a Base +/- Swing Size move in ONE driver, holding all other drivers at Base
A48: Each row below is a fully self-contained shadow replica of the FY2027 AOP's annual P&L and cash flow (columns D:AR), built from the fixed references and Base driver values above. Exactly ONE driver cell (columns D:K) differs from its Base value per scenario row, offset by the Swing Size input cell below -- every other driver cell is an unmodified link to its Base value. Columns W (Operating Income), Z (EPS), AL (Free Cash Flow), and AR (Cash, FY2027 Q4 ending) are the 4 KEY outputs the brief asks for (shaded gold); columns AS:AV show each row's impact vs. the Base row directly below.
A49: SWING SIZE (percentage points, applied to every one of the 7 drivers below, +/- as noted per row) -- single editable input cell: | C49: 0.01
A51: Scenario | B51: Driver Swung | C51: Swing (signed, pt) | D51: g_iPhone (Units Growth) | E51: g_Mac (Units Growth) | F51: g_Services (Inst.Base Growth) | G51: FX Impact | H51: GM% Products | I51: GM% Services | J51: Buyback % of FCF | K51: Tax Rate | L51: Rev: iPhone ($M) | M51: Rev: Mac ($M) | N51: Rev: iPad ($M) | O51: Rev: Wearables ($M) | P51: Rev: Services ($M) | Q51: Total Net Sales ($M) | R51: Products Rev ($M) | S51: Gross Margin ($M) | T51: Cost of Sales ($M) | U51: R&D ($M) | V51: SG&A ($M) | W51: OPERATING INCOME ($M) | X51: Income Tax ($M) | Y51: Net Income ($M) | Z51: EPS ($/sh) | AA51: Q4 Net Sales ($M) | AB51: Q4 COGS ($M) | AC51: D&A ($M) | AD51: AR, End FY27Q4 ($M) | AE51: Inventory, End FY27Q4 ($M) | AF51: AP, End FY27Q4 ($M) | AG51: Chg AR (CF sign) | AH51: Chg Inventory (CF sign) | AI51: Chg AP (CF sign) | AJ51: Operating CF ($M) | AK51: CapEx ($M) | AL51: FREE CASH FLOW ($M) | AM51: Buyback $ ($M) | AN51: Dividend $ ($M) | AO51: Debt Roll $ ($M) | AP51: Financing CF ($M) | AQ51: Net Chg Cash ($M) | AR51: CASH, End FY27Q4 ($M) | AS51: Delta OI vs Base | AT51: Delta EPS vs Base | AU51: Delta FCF vs Base | AV51: Delta Cash vs Base
A52: BASE (0 swing -- ties to live model) | B52: -- (none) | C52: =0 -> 0 | D52: =$C$27 -> 0.015 | E52: =$C$28 -> 0.04 | F52: =$C$31 -> 0.075 | G52: =$C$32 -> 0 | H52: =$C$34 -> 0.37 | I52: =$C$35 -> 0.755 | J52: =$C$42 -> 0.9 | K52: =$C$44 -> 0.16 | L52: =$C$11*(1+D52)*(1+G52)*(1+$C$33) -> 229158.38 | M52: =$C$12*(1+E52)*(1+G52)*(1+$C$33) -> 38693.771 | N52: =$C$13*(1+$C$29)*(1+G52)*(1+$C$33) -> 30190.106 | O52: =$C$14*(1+$C$30)*(1+G52)*(1+$C$33) -> 36756.221 | P52: =$C$15*(1+F52)*(1+G52)*(1+$C$33) -> 137817.07 | Q52: =SUM(L52:P52) -> 472615.55 | R52: =SUM(L52:O52) -> 334798.48 | S52: =R52*H52+P52*I52 -> 227927.33 | T52: =Q52-S52 -> 244688.22 | U52: =Q52*$C$37 -> 39227.091 | V52: =Q52*$C$36 -> 31192.626 | W52: =S52-U52-V52 -> 157507.61 | X52: =W52*K52 -> 25201.218 | Y52: =W52-X52 -> 132306.39 | Z52: =Y52/$C$17 -> 8.9910017 | AA52: =Q52*$C$16 -> 115550.53 | AB52: =T52*$C$16 -> 59824.216 | AC52: =$C$18*Q52 -> 13841.631 | AD52: =$C$38*(AA52/90) -> 42368.529 | AE52: =$C$39*(AB52/90) -> 6647.1351 | AF52: =$C$40*(AB52/90) -> 76442.054 | AG52: =-(AD52-$C$20) -> -1292.4917 | AH52: =-(AE52-$C$21) -> -332.69995 | AI52: =(AF52-$C$22) -> 3826.0495 | AJ52: =Y52+AC52+AG52+AH52+AI52 -> 148348.88 | AK52: =-$C$41*Q52 -> -14178.467 | AL52: =AJ52+AK52 -> 134170.41 | AM52: =-J52*AL52 -> -120753.37 | AN52: =-$C$43*Y52 -> -19845.959 | AO52: =4*$C$45 -> 0 | AP52: =AM52+AN52+AO52 -> -140599.33 | AQ52: =AJ52+AK52+AP52 -> -6428.9174 | AR52: =$C$19+AQ52 -> 23355.631 | AS52: =W52-$W$52 -> 0 | AT52: =Z52-$Z$52 -> 0 | AU52: =AL52-$AL$52 -> 0 | AV52: =AR52-$AR$52 -> 0
A53: TIE-OUT CHECK: Base row (0 swing, above) vs. the live model's ACTUAL FY2027 AOP Base-scenario output (IS!AJ49 / IS!AJ57 / CF!AJ32 / CF!AJ30) -- differences must be ~$0 / ~$0.00, confirming this shadow formula chain is algebraically identical to the real model, not merely similar. | W53: =W52-IS!AJ49 -> 0 | Z53: =Z52-IS!AJ57 -> 1.7763568e-15 | AL53: =AL52-CF!AJ32 -> 2.910383e-11 | AR53: =AR52-CF!AJ30 -> 7.2759576e-12 | AS53: Drivers!B6 currently = | AU53: =Drivers!B6 -> Base | AV53: (must = "Base" for this tab's Fixed Reference anchors to represent a pure Base-scenario baseline -- see row 4 scope-limit note)
A54: iPhone Units Growth -- LOW | B54: iPhone Units Growth | C54: =-$C$49 -> -0.01 | D54: =$C$27+C54 -> 0.005 | E54: =$C$28 -> 0.04 | F54: =$C$31 -> 0.075 | G54: =$C$32 -> 0 | H54: =$C$34 -> 0.37 | I54: =$C$35 -> 0.755 | J54: =$C$42 -> 0.9 | K54: =$C$44 -> 0.16 | L54: =$C$11*(1+D54)*(1+G54)*(1+$C$33) -> 226900.66 | M54: =$C$12*(1+E54)*(1+G54)*(1+$C$33) -> 38693.771 | N54: =$C$13*(1+$C$29)*(1+G54)*(1+$C$33) -> 30190.106 | O54: =$C$14*(1+$C$30)*(1+G54)*(1+$C$33) -> 36756.221 | P54: =$C$15*(1+F54)*(1+G54)*(1+$C$33) -> 137817.07 | Q54: =SUM(L54:P54) -> 470357.83 | R54: =SUM(L54:O54) -> 332540.76 | S54: =R54*H54+P54*I54 -> 227091.97 | T54: =Q54-S54 -> 243265.86 | U54: =Q54*$C$37 -> 39039.7 | V54: =Q54*$C$36 -> 31043.617 | W54: =S54-U54-V54 -> 157008.65 | X54: =W54*K54 -> 25121.385 | Y54: =W54-X54 -> 131887.27 | Z54: =Y54/$C$17 -> 8.9625198 | AA54: =Q54*$C$16 -> 114998.54 | AB54: =T54*$C$16 -> 59476.46 | AC54: =$C$18*Q54 -> 13775.508 | AD54: =$C$38*(AA54/90) -> 42166.131 | AE54: =$C$39*(AB54/90) -> 6608.4956 | AF54: =$C$40*(AB54/90) -> 75997.699 | AG54: =-(AD54-$C$20) -> -1090.0942 | AH54: =-(AE54-$C$21) -> -294.06044 | AI54: =(AF54-$C$22) -> 3381.695 | AJ54: =Y54+AC54+AG54+AH54+AI54 -> 147660.32 | AK54: =-$C$41*Q54 -> -14110.735 | AL54: =AJ54+AK54 -> 133549.58 | AM54: =-J54*AL54 -> -120194.62 | AN54: =-$C$43*Y54 -> -19783.09 | AO54: =4*$C$45 -> 0 | AP54: =AM54+AN54+AO54 -> -139977.71 | AQ54: =AJ54+AK54+AP54 -> -6428.1321 | AR54: =$C$19+AQ54 -> 23356.416 | AS54: =W54-$W$52 -> -498.95569 | AT54: =Z54-$Z$52 -> -0.028481871 | AU54: =AL54-$AL$52 -> -620.83115 | AV54: =AR54-$AR$52 -> 0.78530195
A55: iPhone Units Growth -- HIGH | B55: iPhone Units Growth | C55: =$C$49 -> 0.01 | D55: =$C$27+C55 -> 0.025 | E55: =$C$28 -> 0.04 | F55: =$C$31 -> 0.075 | G55: =$C$32 -> 0 | H55: =$C$34 -> 0.37 | I55: =$C$35 -> 0.755 | J55: =$C$42 -> 0.9 | K55: =$C$44 -> 0.16 | L55: =$C$11*(1+D55)*(1+G55)*(1+$C$33) -> 231416.1 | M55: =$C$12*(1+E55)*(1+G55)*(1+$C$33) -> 38693.771 | N55: =$C$13*(1+$C$29)*(1+G55)*(1+$C$33) -> 30190.106 | O55: =$C$14*(1+$C$30)*(1+G55)*(1+$C$33) -> 36756.221 | P55: =$C$15*(1+F55)*(1+G55)*(1+$C$33) -> 137817.07 | Q55: =SUM(L55:P55) -> 474873.27 | R55: =SUM(L55:O55) -> 337056.2 | S55: =R55*H55+P55*I55 -> 228762.68 | T55: =Q55-S55 -> 246110.59 | U55: =Q55*$C$37 -> 39414.481 | V55: =Q55*$C$36 -> 31341.636 | W55: =S55-U55-V55 -> 158006.57 | X55: =W55*K55 -> 25281.05 | Y55: =W55-X55 -> 132725.51 | Z55: =Y55/$C$17 -> 9.0194836 | AA55: =Q55*$C$16 -> 116102.53 | AB55: =T55*$C$16 -> 60171.971 | AC55: =$C$18*Q55 -> 13907.753 | AD55: =$C$38*(AA55/90) -> 42570.926 | AE55: =$C$39*(AB55/90) -> 6685.7746 | AF55: =$C$40*(AB55/90) -> 76886.408 | AG55: =-(AD55-$C$20) -> -1494.8892 | AH55: =-(AE55-$C$21) -> -371.33947 | AI55: =(AF55-$C$22) -> 4270.4039 | AJ55: =Y55+AC55+AG55+AH55+AI55 -> 149037.44 | AK55: =-$C$41*Q55 -> -14246.198 | AL55: =AJ55+AK55 -> 134791.25 | AM55: =-J55*AL55 -> -121312.12 | AN55: =-$C$43*Y55 -> -19908.827 | AO55: =4*$C$45 -> 0 | AP55: =AM55+AN55+AO55 -> -141220.95 | AQ55: =AJ55+AK55+AP55 -> -6429.7027 | AR55: =$C$19+AQ55 -> 23354.845 | AS55: =W55-$W$52 -> 498.95569 | AT55: =Z55-$Z$52 -> 0.028481871 | AU55: =AL55-$AL$52 -> 620.83115 | AV55: =AR55-$AR$52 -> -0.78530195
A56: Mac Units Growth -- LOW | B56: Mac Units Growth | C56: =-$C$49 -> -0.01 | D56: =$C$27 -> 0.015 | E56: =$C$28+C56 -> 0.03 | F56: =$C$31 -> 0.075 | G56: =$C$32 -> 0 | H56: =$C$34 -> 0.37 | I56: =$C$35 -> 0.755 | J56: =$C$42 -> 0.9 | K56: =$C$44 -> 0.16 | L56: =$C$11*(1+D56)*(1+G56)*(1+$C$33) -> 229158.38 | M56: =$C$12*(1+E56)*(1+G56)*(1+$C$33) -> 38321.715 | N56: =$C$13*(1+$C$29)*(1+G56)*(1+$C$33) -> 30190.106 | O56: =$C$14*(1+$C$30)*(1+G56)*(1+$C$33) -> 36756.221 | P56: =$C$15*(1+F56)*(1+G56)*(1+$C$33) -> 137817.07 | Q56: =SUM(L56:P56) -> 472243.5 | R56: =SUM(L56:O56) -> 334426.42 | S56: =R56*H56+P56*I56 -> 227789.67 | T56: =Q56-S56 -> 244453.83 | U56: =Q56*$C$37 -> 39196.21 | V56: =Q56*$C$36 -> 31168.071 | W56: =S56-U56-V56 -> 157425.39 | X56: =W56*K56 -> 25188.062 | Y56: =W56-X56 -> 132237.32 | Z56: =Y56/$C$17 -> 8.9863081 | AA56: =Q56*$C$16 -> 115459.57 | AB56: =T56*$C$16 -> 59766.908 | AC56: =$C$18*Q56 -> 13830.734 | AD56: =$C$38*(AA56/90) -> 42335.175 | AE56: =$C$39*(AB56/90) -> 6640.7676 | AF56: =$C$40*(AB56/90) -> 76368.827 | AG56: =-(AD56-$C$20) -> -1259.1381 | AH56: =-(AE56-$C$21) -> -326.33244 | AI56: =(AF56-$C$22) -> 3752.8231 | AJ56: =Y56+AC56+AG56+AH56+AI56 -> 148235.41 | AK56: =-$C$41*Q56 -> -14167.305 | AL56: =AJ56+AK56 -> 134068.11 | AM56: =-J56*AL56 -> -120661.29 | AN56: =-$C$43*Y56 -> -19835.599 | AO56: =4*$C$45 -> 0 | AP56: =AM56+AN56+AO56 -> -140496.89 | AQ56: =AJ56+AK56+AP56 -> -6428.788 | AR56: =$C$19+AQ56 -> 23355.76 | AS56: =W56-$W$52 -> -82.224263 | AT56: =Z56-$Z$52 -> -0.0046936049 | AU56: =AL56-$AL$52 -> -102.30845 | AV56: =AR56-$AR$52 -> 0.12941204
A57: Mac Units Growth -- HIGH | B57: Mac Units Growth | C57: =$C$49 -> 0.01 | D57: =$C$27 -> 0.015 | E57: =$C$28+C57 -> 0.05 | F57: =$C$31 -> 0.075 | G57: =$C$32 -> 0 | H57: =$C$34 -> 0.37 | I57: =$C$35 -> 0.755 | J57: =$C$42 -> 0.9 | K57: =$C$44 -> 0.16 | L57: =$C$11*(1+D57)*(1+G57)*(1+$C$33) -> 229158.38 | M57: =$C$12*(1+E57)*(1+G57)*(1+$C$33) -> 39065.826 | N57: =$C$13*(1+$C$29)*(1+G57)*(1+$C$33) -> 30190.106 | O57: =$C$14*(1+$C$30)*(1+G57)*(1+$C$33) -> 36756.221 | P57: =$C$15*(1+F57)*(1+G57)*(1+$C$33) -> 137817.07 | Q57: =SUM(L57:P57) -> 472987.61 | R57: =SUM(L57:O57) -> 335170.54 | S57: =R57*H57+P57*I57 -> 228064.99 | T57: =Q57-S57 -> 244922.62 | U57: =Q57*$C$37 -> 39257.971 | V57: =Q57*$C$36 -> 31217.182 | W57: =S57-U57-V57 -> 157589.83 | X57: =W57*K57 -> 25214.373 | Y57: =W57-X57 -> 132375.46 | Z57: =Y57/$C$17 -> 8.9956953 | AA57: =Q57*$C$16 -> 115641.5 | AB57: =T57*$C$16 -> 59881.523 | AC57: =$C$18*Q57 -> 13852.527 | AD57: =$C$38*(AA57/90) -> 42401.882 | AE57: =$C$39*(AB57/90) -> 6653.5026 | AF57: =$C$40*(AB57/90) -> 76515.28 | AG57: =-(AD57-$C$20) -> -1325.8453 | AH57: =-(AE57-$C$21) -> -339.06747 | AI57: =(AF57-$C$22) -> 3899.2758 | AJ57: =Y57+AC57+AG57+AH57+AI57 -> 148462.35 | AK57: =-$C$41*Q57 -> -14189.628 | AL57: =AJ57+AK57 -> 134272.72 | AM57: =-J57*AL57 -> -120845.45 | AN57: =-$C$43*Y57 -> -19856.319 | AO57: =4*$C$45 -> 0 | AP57: =AM57+AN57+AO57 -> -140701.77 | AQ57: =AJ57+AK57+AP57 -> -6429.0468 | AR57: =$C$19+AQ57 -> 23355.501 | AS57: =W57-$W$52 -> 82.224263 | AT57: =Z57-$Z$52 -> 0.0046936049 | AU57: =AL57-$AL$52 -> 102.30845 | AV57: =AR57-$AR$52 -> -0.12941204
A58: Services Installed-Base Growth -- LOW | B58: Services Installed-Base Growth | C58: =-$C$49 -> -0.01 | D58: =$C$27 -> 0.015 | E58: =$C$28 -> 0.04 | F58: =$C$31+C58 -> 0.065 | G58: =$C$32 -> 0 | H58: =$C$34 -> 0.37 | I58: =$C$35 -> 0.755 | J58: =$C$42 -> 0.9 | K58: =$C$44 -> 0.16 | L58: =$C$11*(1+D58)*(1+G58)*(1+$C$33) -> 229158.38 | M58: =$C$12*(1+E58)*(1+G58)*(1+$C$33) -> 38693.771 | N58: =$C$13*(1+$C$29)*(1+G58)*(1+$C$33) -> 30190.106 | O58: =$C$14*(1+$C$30)*(1+G58)*(1+$C$33) -> 36756.221 | P58: =$C$15*(1+F58)*(1+G58)*(1+$C$33) -> 136535.05 | Q58: =SUM(L58:P58) -> 471333.53 | R58: =SUM(L58:O58) -> 334798.48 | S58: =R58*H58+P58*I58 -> 226959.4 | T58: =Q58-S58 -> 244374.13 | U58: =Q58*$C$37 -> 39120.683 | V58: =Q58*$C$36 -> 31108.013 | W58: =S58-U58-V58 -> 156730.71 | X58: =W58*K58 -> 25076.913 | Y58: =W58-X58 -> 131653.79 | Z58: =Y58/$C$17 -> 8.9466537 | AA58: =Q58*$C$16 -> 115237.09 | AB58: =T58*$C$16 -> 59747.422 | AC58: =$C$18*Q58 -> 13804.084 | AD58: =$C$38*(AA58/90) -> 42253.6 | AE58: =$C$39*(AB58/90) -> 6638.6025 | AF58: =$C$40*(AB58/90) -> 76343.929 | AG58: =-(AD58-$C$20) -> -1177.5626 | AH58: =-(AE58-$C$21) -> -324.16734 | AI58: =(AF58-$C$22) -> 3727.9244 | AJ58: =Y58+AC58+AG58+AH58+AI58 -> 147684.07 | AK58: =-$C$41*Q58 -> -14140.006 | AL58: =AJ58+AK58 -> 133544.07 | AM58: =-J58*AL58 -> -120189.66 | AN58: =-$C$43*Y58 -> -19748.069 | AO58: =4*$C$45 -> 0 | AP58: =AM58+AN58+AO58 -> -139937.73 | AQ58: =AJ58+AK58+AP58 -> -6393.6624 | AR58: =$C$19+AQ58 -> 23390.886 | AS58: =W58-$W$52 -> -776.90368 | AT58: =Z58-$Z$52 -> -0.044347967 | AU58: =AL58-$AL$52 -> -626.34875 | AV58: =AR58-$AR$52 -> 35.254989
A59: Services Installed-Base Growth -- HIGH | B59: Services Installed-Base Growth | C59: =$C$49 -> 0.01 | D59: =$C$27 -> 0.015 | E59: =$C$28 -> 0.04 | F59: =$C$31+C59 -> 0.085 | G59: =$C$32 -> 0 | H59: =$C$34 -> 0.37 | I59: =$C$35 -> 0.755 | J59: =$C$42 -> 0.9 | K59: =$C$44 -> 0.16 | L59: =$C$11*(1+D59)*(1+G59)*(1+$C$33) -> 229158.38 | M59: =$C$12*(1+E59)*(1+G59)*(1+$C$33) -> 38693.771 | N59: =$C$13*(1+$C$29)*(1+G59)*(1+$C$33) -> 30190.106 | O59: =$C$14*(1+$C$30)*(1+G59)*(1+$C$33) -> 36756.221 | P59: =$C$15*(1+F59)*(1+G59)*(1+$C$33) -> 139099.09 | Q59: =SUM(L59:P59) -> 473897.57 | R59: =SUM(L59:O59) -> 334798.48 | S59: =R59*H59+P59*I59 -> 228895.25 | T59: =Q59-S59 -> 245002.32 | U59: =Q59*$C$37 -> 39333.498 | V59: =Q59*$C$36 -> 31277.24 | W59: =S59-U59-V59 -> 158284.51 | X59: =W59*K59 -> 25325.522 | Y59: =W59-X59 -> 132958.99 | Z59: =Y59/$C$17 -> 9.0353497 | AA59: =Q59*$C$16 -> 115863.98 | AB59: =T59*$C$16 -> 59901.009 | AC59: =$C$18*Q59 -> 13879.178 | AD59: =$C$38*(AA59/90) -> 42483.458 | AE59: =$C$39*(AB59/90) -> 6655.6677 | AF59: =$C$40*(AB59/90) -> 76540.179 | AG59: =-(AD59-$C$20) -> -1407.4208 | AH59: =-(AE59-$C$21) -> -341.23257 | AI59: =(AF59-$C$22) -> 3924.1745 | AJ59: =Y59+AC59+AG59+AH59+AI59 -> 149013.69 | AK59: =-$C$41*Q59 -> -14216.927 | AL59: =AJ59+AK59 -> 134796.76 | AM59: =-J59*AL59 -> -121317.09 | AN59: =-$C$43*Y59 -> -19943.849 | AO59: =4*$C$45 -> 0 | AP59: =AM59+AN59+AO59 -> -141260.94 | AQ59: =AJ59+AK59+AP59 -> -6464.1724 | AR59: =$C$19+AQ59 -> 23320.376 | AS59: =W59-$W$52 -> 776.90368 | AT59: =Z59-$Z$52 -> 0.044347967 | AU59: =AL59-$AL$52 -> 626.34875 | AV59: =AR59-$AR$52 -> -35.254989
A60: FX Impact -- LOW | B60: FX Impact | C60: =-$C$49 -> -0.01 | D60: =$C$27 -> 0.015 | E60: =$C$28 -> 0.04 | F60: =$C$31 -> 0.075 | G60: =$C$32+C60 -> -0.01 | H60: =$C$34 -> 0.37 | I60: =$C$35 -> 0.755 | J60: =$C$42 -> 0.9 | K60: =$C$44 -> 0.16 | L60: =$C$11*(1+D60)*(1+G60)*(1+$C$33) -> 226866.8 | M60: =$C$12*(1+E60)*(1+G60)*(1+$C$33) -> 38306.833 | N60: =$C$13*(1+$C$29)*(1+G60)*(1+$C$33) -> 29888.205 | O60: =$C$14*(1+$C$30)*(1+G60)*(1+$C$33) -> 36388.659 | P60: =$C$15*(1+F60)*(1+G60)*(1+$C$33) -> 136438.9 | Q60: =SUM(L60:P60) -> 467889.4 | R60: =SUM(L60:O60) -> 331450.49 | S60: =R60*H60+P60*I60 -> 225648.05 | T60: =Q60-S60 -> 242241.34 | U60: =Q60*$C$37 -> 38834.82 | V60: =Q60*$C$36 -> 30880.7 | W60: =S60-U60-V60 -> 155932.53 | X60: =W60*K60 -> 24949.205 | Y60: =W60-X60 -> 130983.33 | Z60: =Y60/$C$17 -> 8.9010917 | AA60: =Q60*$C$16 -> 114395.03 | AB60: =T60*$C$16 -> 59225.974 | AC60: =$C$18*Q60 -> 13703.214 | AD60: =$C$38*(AA60/90) -> 41944.843 | AE60: =$C$39*(AB60/90) -> 6580.6637 | AF60: =$C$40*(AB60/90) -> 75677.633 | AG60: =-(AD60-$C$20) -> -868.80641 | AH60: =-(AE60-$C$21) -> -266.2286 | AI60: =(AF60-$C$22) -> 3061.6289 | AJ60: =Y60+AC60+AG60+AH60+AI60 -> 146613.14 | AK60: =-$C$41*Q60 -> -14036.682 | AL60: =AJ60+AK60 -> 132576.45 | AM60: =-J60*AL60 -> -119318.81 | AN60: =-$C$43*Y60 -> -19647.499 | AO60: =4*$C$45 -> 0 | AP60: =AM60+AN60+AO60 -> -138966.31 | AQ60: =AJ60+AK60+AP60 -> -6389.8538 | AR60: =$C$19+AQ60 -> 23394.694 | AS60: =W60-$W$52 -> -1575.0761 | AT60: =Z60-$Z$52 -> -0.089910017 | AU60: =AL60-$AL$52 -> -1593.9595 | AV60: =AR60-$AR$52 -> 39.063642
A61: FX Impact -- HIGH | B61: FX Impact | C61: =$C$49 -> 0.01 | D61: =$C$27 -> 0.015 | E61: =$C$28 -> 0.04 | F61: =$C$31 -> 0.075 | G61: =$C$32+C61 -> 0.01 | H61: =$C$34 -> 0.37 | I61: =$C$35 -> 0.755 | J61: =$C$42 -> 0.9 | K61: =$C$44 -> 0.16 | L61: =$C$11*(1+D61)*(1+G61)*(1+$C$33) -> 231449.97 | M61: =$C$12*(1+E61)*(1+G61)*(1+$C$33) -> 39080.709 | N61: =$C$13*(1+$C$29)*(1+G61)*(1+$C$33) -> 30492.007 | O61: =$C$14*(1+$C$30)*(1+G61)*(1+$C$33) -> 37123.783 | P61: =$C$15*(1+F61)*(1+G61)*(1+$C$33) -> 139195.24 | Q61: =SUM(L61:P61) -> 477341.71 | R61: =SUM(L61:O61) -> 338146.46 | S61: =R61*H61+P61*I61 -> 230206.6 | T61: =Q61-S61 -> 247135.11 | U61: =Q61*$C$37 -> 39619.362 | V61: =Q61*$C$36 -> 31504.553 | W61: =S61-U61-V61 -> 159082.69 | X61: =W61*K61 -> 25453.23 | Y61: =W61-X61 -> 133629.46 | Z61: =Y61/$C$17 -> 9.0809117 | AA61: =Q61*$C$16 -> 116706.04 | AB61: =T61*$C$16 -> 60422.458 | AC61: =$C$18*Q61 -> 13980.047 | AD61: =$C$38*(AA61/90) -> 42792.214 | AE61: =$C$39*(AB61/90) -> 6713.6064 | AF61: =$C$40*(AB61/90) -> 77206.474 | AG61: =-(AD61-$C$20) -> -1716.177 | AH61: =-(AE61-$C$21) -> -399.17131 | AI61: =(AF61-$C$22) -> 4590.47 | AJ61: =Y61+AC61+AG61+AH61+AI61 -> 150084.62 | AK61: =-$C$41*Q61 -> -14320.251 | AL61: =AJ61+AK61 -> 135764.37 | AM61: =-J61*AL61 -> -122187.94 | AN61: =-$C$43*Y61 -> -20044.418 | AO61: =4*$C$45 -> 0 | AP61: =AM61+AN61+AO61 -> -142232.35 | AQ61: =AJ61+AK61+AP61 -> -6467.981 | AR61: =$C$19+AQ61 -> 23316.567 | AS61: =W61-$W$52 -> 1575.0761 | AT61: =Z61-$Z$52 -> 0.089910017 | AU61: =AL61-$AL$52 -> 1593.9595 | AV61: =AR61-$AR$52 -> -39.063642
A62: Gross Margin (Products & Services) -- LOW | B62: Gross Margin (Products & Services) | C62: =-$C$49 -> -0.01 | D62: =$C$27 -> 0.015 | E62: =$C$28 -> 0.04 | F62: =$C$31 -> 0.075 | G62: =$C$32 -> 0 | H62: =$C$34+C62 -> 0.36 | I62: =$C$35+C62 -> 0.745 | J62: =$C$42 -> 0.9 | K62: =$C$44 -> 0.16 | L62: =$C$11*(1+D62)*(1+G62)*(1+$C$33) -> 229158.38 | M62: =$C$12*(1+E62)*(1+G62)*(1+$C$33) -> 38693.771 | N62: =$C$13*(1+$C$29)*(1+G62)*(1+$C$33) -> 30190.106 | O62: =$C$14*(1+$C$30)*(1+G62)*(1+$C$33) -> 36756.221 | P62: =$C$15*(1+F62)*(1+G62)*(1+$C$33) -> 137817.07 | Q62: =SUM(L62:P62) -> 472615.55 | R62: =SUM(L62:O62) -> 334798.48 | S62: =R62*H62+P62*I62 -> 223201.17 | T62: =Q62-S62 -> 249414.38 | U62: =Q62*$C$37 -> 39227.091 | V62: =Q62*$C$36 -> 31192.626 | W62: =S62-U62-V62 -> 152781.45 | X62: =W62*K62 -> 24445.033 | Y62: =W62-X62 -> 128336.42 | Z62: =Y62/$C$17 -> 8.7212187 | AA62: =Q62*$C$16 -> 115550.53 | AB62: =T62*$C$16 -> 60979.721 | AC62: =$C$18*Q62 -> 13841.631 | AD62: =$C$38*(AA62/90) -> 42368.529 | AE62: =$C$39*(AB62/90) -> 6775.5246 | AF62: =$C$40*(AB62/90) -> 77918.533 | AG62: =-(AD62-$C$20) -> -1292.4917 | AH62: =-(AE62-$C$21) -> -461.08944 | AI62: =(AF62-$C$22) -> 5302.5285 | AJ62: =Y62+AC62+AG62+AH62+AI62 -> 145727 | AK62: =-$C$41*Q62 -> -14178.467 | AL62: =AJ62+AK62 -> 131548.53 | AM62: =-J62*AL62 -> -118393.68 | AN62: =-$C$43*Y62 -> -19250.463 | AO62: =4*$C$45 -> 0 | AP62: =AM62+AN62+AO62 -> -137644.14 | AQ62: =AJ62+AK62+AP62 -> -6095.6099 | AR62: =$C$19+AQ62 -> 23688.938 | AS62: =W62-$W$52 -> -4726.1555 | AT62: =Z62-$Z$52 -> -0.26978298 | AU62: =AL62-$AL$52 -> -2621.8811 | AV62: =AR62-$AR$52 -> 333.30749
A63: Gross Margin (Products & Services) -- HIGH | B63: Gross Margin (Products & Services) | C63: =$C$49 -> 0.01 | D63: =$C$27 -> 0.015 | E63: =$C$28 -> 0.04 | F63: =$C$31 -> 0.075 | G63: =$C$32 -> 0 | H63: =$C$34+C63 -> 0.38 | I63: =$C$35+C63 -> 0.765 | J63: =$C$42 -> 0.9 | K63: =$C$44 -> 0.16 | L63: =$C$11*(1+D63)*(1+G63)*(1+$C$33) -> 229158.38 | M63: =$C$12*(1+E63)*(1+G63)*(1+$C$33) -> 38693.771 | N63: =$C$13*(1+$C$29)*(1+G63)*(1+$C$33) -> 30190.106 | O63: =$C$14*(1+$C$30)*(1+G63)*(1+$C$33) -> 36756.221 | P63: =$C$15*(1+F63)*(1+G63)*(1+$C$33) -> 137817.07 | Q63: =SUM(L63:P63) -> 472615.55 | R63: =SUM(L63:O63) -> 334798.48 | S63: =R63*H63+P63*I63 -> 232653.48 | T63: =Q63-S63 -> 239962.07 | U63: =Q63*$C$37 -> 39227.091 | V63: =Q63*$C$36 -> 31192.626 | W63: =S63-U63-V63 -> 162233.77 | X63: =W63*K63 -> 25957.402 | Y63: =W63-X63 -> 136276.36 | Z63: =Y63/$C$17 -> 9.2607847 | AA63: =Q63*$C$16 -> 115550.53 | AB63: =T63*$C$16 -> 58668.71 | AC63: =$C$18*Q63 -> 13841.631 | AD63: =$C$38*(AA63/90) -> 42368.529 | AE63: =$C$39*(AB63/90) -> 6518.7456 | AF63: =$C$40*(AB63/90) -> 74965.575 | AG63: =-(AD63-$C$20) -> -1292.4917 | AH63: =-(AE63-$C$21) -> -204.31047 | AI63: =(AF63-$C$22) -> 2349.5704 | AJ63: =Y63+AC63+AG63+AH63+AI63 -> 150970.76 | AK63: =-$C$41*Q63 -> -14178.467 | AL63: =AJ63+AK63 -> 136792.3 | AM63: =-J63*AL63 -> -123113.07 | AN63: =-$C$43*Y63 -> -20441.454 | AO63: =4*$C$45 -> 0 | AP63: =AM63+AN63+AO63 -> -143554.52 | AQ63: =AJ63+AK63+AP63 -> -6762.2249 | AR63: =$C$19+AQ63 -> 23022.323 | AS63: =W63-$W$52 -> 4726.1555 | AT63: =Z63-$Z$52 -> 0.26978298 | AU63: =AL63-$AL$52 -> 2621.8811 | AV63: =AR63-$AR$52 -> -333.30749
A64: Buyback % of Trailing FCF -- LOW | B64: Buyback % of Trailing FCF | C64: =-$C$49 -> -0.01 | D64: =$C$27 -> 0.015 | E64: =$C$28 -> 0.04 | F64: =$C$31 -> 0.075 | G64: =$C$32 -> 0 | H64: =$C$34 -> 0.37 | I64: =$C$35 -> 0.755 | J64: =$C$42+C64 -> 0.89 | K64: =$C$44 -> 0.16 | L64: =$C$11*(1+D64)*(1+G64)*(1+$C$33) -> 229158.38 | M64: =$C$12*(1+E64)*(1+G64)*(1+$C$33) -> 38693.771 | N64: =$C$13*(1+$C$29)*(1+G64)*(1+$C$33) -> 30190.106 | O64: =$C$14*(1+$C$30)*(1+G64)*(1+$C$33) -> 36756.221 | P64: =$C$15*(1+F64)*(1+G64)*(1+$C$33) -> 137817.07 | Q64: =SUM(L64:P64) -> 472615.55 | R64: =SUM(L64:O64) -> 334798.48 | S64: =R64*H64+P64*I64 -> 227927.33 | T64: =Q64-S64 -> 244688.22 | U64: =Q64*$C$37 -> 39227.091 | V64: =Q64*$C$36 -> 31192.626 | W64: =S64-U64-V64 -> 157507.61 | X64: =W64*K64 -> 25201.218 | Y64: =W64-X64 -> 132306.39 | Z64: =Y64/$C$17 -> 8.9910017 | AA64: =Q64*$C$16 -> 115550.53 | AB64: =T64*$C$16 -> 59824.216 | AC64: =$C$18*Q64 -> 13841.631 | AD64: =$C$38*(AA64/90) -> 42368.529 | AE64: =$C$39*(AB64/90) -> 6647.1351 | AF64: =$C$40*(AB64/90) -> 76442.054 | AG64: =-(AD64-$C$20) -> -1292.4917 | AH64: =-(AE64-$C$21) -> -332.69995 | AI64: =(AF64-$C$22) -> 3826.0495 | AJ64: =Y64+AC64+AG64+AH64+AI64 -> 148348.88 | AK64: =-$C$41*Q64 -> -14178.467 | AL64: =AJ64+AK64 -> 134170.41 | AM64: =-J64*AL64 -> -119411.67 | AN64: =-$C$43*Y64 -> -19845.959 | AO64: =4*$C$45 -> 0 | AP64: =AM64+AN64+AO64 -> -139257.63 | AQ64: =AJ64+AK64+AP64 -> -5087.2133 | AR64: =$C$19+AQ64 -> 24697.335 | AS64: =W64-$W$52 -> 0 | AT64: =Z64-$Z$52 -> 0 | AU64: =AL64-$AL$52 -> 0 | AV64: =AR64-$AR$52 -> 1341.7041
A65: Buyback % of Trailing FCF -- HIGH | B65: Buyback % of Trailing FCF | C65: =$C$49 -> 0.01 | D65: =$C$27 -> 0.015 | E65: =$C$28 -> 0.04 | F65: =$C$31 -> 0.075 | G65: =$C$32 -> 0 | H65: =$C$34 -> 0.37 | I65: =$C$35 -> 0.755 | J65: =$C$42+C65 -> 0.91 | K65: =$C$44 -> 0.16 | L65: =$C$11*(1+D65)*(1+G65)*(1+$C$33) -> 229158.38 | M65: =$C$12*(1+E65)*(1+G65)*(1+$C$33) -> 38693.771 | N65: =$C$13*(1+$C$29)*(1+G65)*(1+$C$33) -> 30190.106 | O65: =$C$14*(1+$C$30)*(1+G65)*(1+$C$33) -> 36756.221 | P65: =$C$15*(1+F65)*(1+G65)*(1+$C$33) -> 137817.07 | Q65: =SUM(L65:P65) -> 472615.55 | R65: =SUM(L65:O65) -> 334798.48 | S65: =R65*H65+P65*I65 -> 227927.33 | T65: =Q65-S65 -> 244688.22 | U65: =Q65*$C$37 -> 39227.091 | V65: =Q65*$C$36 -> 31192.626 | W65: =S65-U65-V65 -> 157507.61 | X65: =W65*K65 -> 25201.218 | Y65: =W65-X65 -> 132306.39 | Z65: =Y65/$C$17 -> 8.9910017 | AA65: =Q65*$C$16 -> 115550.53 | AB65: =T65*$C$16 -> 59824.216 | AC65: =$C$18*Q65 -> 13841.631 | AD65: =$C$38*(AA65/90) -> 42368.529 | AE65: =$C$39*(AB65/90) -> 6647.1351 | AF65: =$C$40*(AB65/90) -> 76442.054 | AG65: =-(AD65-$C$20) -> -1292.4917 | AH65: =-(AE65-$C$21) -> -332.69995 | AI65: =(AF65-$C$22) -> 3826.0495 | AJ65: =Y65+AC65+AG65+AH65+AI65 -> 148348.88 | AK65: =-$C$41*Q65 -> -14178.467 | AL65: =AJ65+AK65 -> 134170.41 | AM65: =-J65*AL65 -> -122095.08 | AN65: =-$C$43*Y65 -> -19845.959 | AO65: =4*$C$45 -> 0 | AP65: =AM65+AN65+AO65 -> -141941.04 | AQ65: =AJ65+AK65+AP65 -> -7770.6215 | AR65: =$C$19+AQ65 -> 22013.927 | AS65: =W65-$W$52 -> 0 | AT65: =Z65-$Z$52 -> 0 | AU65: =AL65-$AL$52 -> 0 | AV65: =AR65-$AR$52 -> -1341.7041
A66: Effective Tax Rate -- LOW | B66: Effective Tax Rate | C66: =-$C$49 -> -0.01 | D66: =$C$27 -> 0.015 | E66: =$C$28 -> 0.04 | F66: =$C$31 -> 0.075 | G66: =$C$32 -> 0 | H66: =$C$34 -> 0.37 | I66: =$C$35 -> 0.755 | J66: =$C$42 -> 0.9 | K66: =$C$44+C66 -> 0.15 | L66: =$C$11*(1+D66)*(1+G66)*(1+$C$33) -> 229158.38 | M66: =$C$12*(1+E66)*(1+G66)*(1+$C$33) -> 38693.771 | N66: =$C$13*(1+$C$29)*(1+G66)*(1+$C$33) -> 30190.106 | O66: =$C$14*(1+$C$30)*(1+G66)*(1+$C$33) -> 36756.221 | P66: =$C$15*(1+F66)*(1+G66)*(1+$C$33) -> 137817.07 | Q66: =SUM(L66:P66) -> 472615.55 | R66: =SUM(L66:O66) -> 334798.48 | S66: =R66*H66+P66*I66 -> 227927.33 | T66: =Q66-S66 -> 244688.22 | U66: =Q66*$C$37 -> 39227.091 | V66: =Q66*$C$36 -> 31192.626 | W66: =S66-U66-V66 -> 157507.61 | X66: =W66*K66 -> 23626.141 | Y66: =W66-X66 -> 133881.47 | Z66: =Y66/$C$17 -> 9.0980374 | AA66: =Q66*$C$16 -> 115550.53 | AB66: =T66*$C$16 -> 59824.216 | AC66: =$C$18*Q66 -> 13841.631 | AD66: =$C$38*(AA66/90) -> 42368.529 | AE66: =$C$39*(AB66/90) -> 6647.1351 | AF66: =$C$40*(AB66/90) -> 76442.054 | AG66: =-(AD66-$C$20) -> -1292.4917 | AH66: =-(AE66-$C$21) -> -332.69995 | AI66: =(AF66-$C$22) -> 3826.0495 | AJ66: =Y66+AC66+AG66+AH66+AI66 -> 149923.96 | AK66: =-$C$41*Q66 -> -14178.467 | AL66: =AJ66+AK66 -> 135745.49 | AM66: =-J66*AL66 -> -122170.94 | AN66: =-$C$43*Y66 -> -20082.22 | AO66: =4*$C$45 -> 0 | AP66: =AM66+AN66+AO66 -> -142253.16 | AQ66: =AJ66+AK66+AP66 -> -6507.6712 | AR66: =$C$19+AQ66 -> 23276.877 | AS66: =W66-$W$52 -> 0 | AT66: =Z66-$Z$52 -> 0.10703573 | AU66: =AL66-$AL$52 -> 1575.0761 | AV66: =AR66-$AR$52 -> -78.753805
A67: Effective Tax Rate -- HIGH | B67: Effective Tax Rate | C67: =$C$49 -> 0.01 | D67: =$C$27 -> 0.015 | E67: =$C$28 -> 0.04 | F67: =$C$31 -> 0.075 | G67: =$C$32 -> 0 | H67: =$C$34 -> 0.37 | I67: =$C$35 -> 0.755 | J67: =$C$42 -> 0.9 | K67: =$C$44+C67 -> 0.17 | L67: =$C$11*(1+D67)*(1+G67)*(1+$C$33) -> 229158.38 | M67: =$C$12*(1+E67)*(1+G67)*(1+$C$33) -> 38693.771 | N67: =$C$13*(1+$C$29)*(1+G67)*(1+$C$33) -> 30190.106 | O67: =$C$14*(1+$C$30)*(1+G67)*(1+$C$33) -> 36756.221 | P67: =$C$15*(1+F67)*(1+G67)*(1+$C$33) -> 137817.07 | Q67: =SUM(L67:P67) -> 472615.55 | R67: =SUM(L67:O67) -> 334798.48 | S67: =R67*H67+P67*I67 -> 227927.33 | T67: =Q67-S67 -> 244688.22 | U67: =Q67*$C$37 -> 39227.091 | V67: =Q67*$C$36 -> 31192.626 | W67: =S67-U67-V67 -> 157507.61 | X67: =W67*K67 -> 26776.294 | Y67: =W67-X67 -> 130731.32 | Z67: =Y67/$C$17 -> 8.883966 | AA67: =Q67*$C$16 -> 115550.53 | AB67: =T67*$C$16 -> 59824.216 | AC67: =$C$18*Q67 -> 13841.631 | AD67: =$C$38*(AA67/90) -> 42368.529 | AE67: =$C$39*(AB67/90) -> 6647.1351 | AF67: =$C$40*(AB67/90) -> 76442.054 | AG67: =-(AD67-$C$20) -> -1292.4917 | AH67: =-(AE67-$C$21) -> -332.69995 | AI67: =(AF67-$C$22) -> 3826.0495 | AJ67: =Y67+AC67+AG67+AH67+AI67 -> 146773.8 | AK67: =-$C$41*Q67 -> -14178.467 | AL67: =AJ67+AK67 -> 132595.34 | AM67: =-J67*AL67 -> -119335.8 | AN67: =-$C$43*Y67 -> -19609.697 | AO67: =4*$C$45 -> 0 | AP67: =AM67+AN67+AO67 -> -138945.5 | AQ67: =AJ67+AK67+AP67 -> -6350.1636 | AR67: =$C$19+AQ67 -> 23434.385 | AS67: =W67-$W$52 -> 0 | AT67: =Z67-$Z$52 -> -0.10703573 | AU67: =AL67-$AL$52 -> -1575.0761 | AV67: =AR67-$AR$52 -> 78.753805
A68: OBSERVATIONS (read directly off columns AS:AV above, not asserted): Gross Margin and the revenue-growth drivers (iPhone/Mac/Services/FX) move Operating Income, EPS, Cash, AND Free Cash Flow (Gross Margin has the largest OI impact per point swung, since it applies to the full revenue base rather than one segment). Buyback % moves Cash only (Delta OI = Delta EPS = Delta FCF = $0.00 exactly, columns AS/AT/AU) -- confirms the structural finding in row 5 above. Tax Rate moves EPS/Cash/FCF but NOT Operating Income (Delta OI = $0.00 exactly, column AS) -- tax is applied strictly below the OI line in this model.
A70: STEP 2 -- 2-VARIABLE DATA TABLE: FY2027 Total Net Sales growth % (rows) x Gross Margin % offset (columns) -> Operating Income grid and EPS grid
A71: Row axis: Total FY2027 Net Sales = (sum of the 5 segments' FY2026 Exit Run-Rate anchors) x (1+g), where g ranges around the Base blended growth rate implied by the Base scenario itself (computed below, not assumed). Products:Services revenue MIX is held at Base proportions across the whole row axis (only the total scales) -- distinct from Step 1's per-segment growth-rate isolation, per the simplification documented in row 6.
A72: Column axis: a GM% OFFSET applied equally to Base Products GM% and Base Services GM% (same convention as Step 1's Gross Margin driver). OI(g,m) = ProductsRev(g)*(GMProductsBase+m) + ServicesRev(g)*(GMServicesBase+m) - RD$(g) - SGA$(g), each a real per-cell formula referencing the row's own helper columns (C:G) and the column's own GM-offset header cell. EPS(g,m) = OI(g,m)*(1-TaxBase)/SharesBase -- algebraically exact in this model (Net Income = OI*(1-tax rate), no other below-the-line items, per Task 12's own IS-tab design) -- so the EPS grid reuses the OI grid's own cells rather than recomputing Products/Services revenue a second time.
A74: STEP 2 REFERENCE VALUES
A75: Item | B75: Formula Basis | C75: Value
A76: Total FY2026 Exit Run-Rate anchor (sum of 5 segments) ($M) | B76: sum of C11:C15 | C76: =SUM(C11:C15) -> 458197.97
A77: Base FY2027 Total Net Sales growth % (vs. FY2026 Exit Run-Rate anchor) | B77: Q52/{anchor}-1 | C77: =Q52/$C$76-1 -> 0.031465832
A78: Base Products Revenue share of Total Net Sales | B78: R52/Q52 | C78: =R52/Q52 -> 0.70839497
A79: Base Services Revenue share of Total Net Sales | B79: P52/Q52 | C79: =P52/Q52 -> 0.29160503
A80: Row step size (Revenue growth %, per row, +/-) -- editable input: | C80: 0.01
A81: Column step size (Gross Margin % offset, per column, +/-) -- editable input: | C81: 0.01
A83: Revenue Growth % (rows) \ GM% offset (columns) --> | B83: g (growth rate) | C83: Total Net Sales ($M) | D83: Products Rev ($M) | E83: Services Rev ($M) | F83: R&D $ ($M) | G83: SG&A $ ($M) | I83: OPERATING INCOME GRID ($M) -- GM% offset --> | O83: EPS GRID ($/sh) -- GM% offset -->
A84: Growth Scenario | I84: ="-2pt ("&TEXT($C$34+-2*$C$81,"0.0%")&"/"&TEXT($C$35+-2*$C$81,"0.0%")&")" -> -2pt (35.0%/73.5%) | J84: ="-1pt ("&TEXT($C$34+-1*$C$81,"0.0%")&"/"&TEXT($C$35+-1*$C$81,"0.0%")&")" -> -1pt (36.0%/74.5%) | K84: ="Base ("&TEXT($C$34+0*$C$81,"0.0%")&"/"&TEXT($C$35+0*$C$81,"0.0%")&")" -> Base (37.0%/75.5%) | L84: ="+1pt ("&TEXT($C$34+1*$C$81,"0.0%")&"/"&TEXT($C$35+1*$C$81,"0.0%")&")" -> +1pt (38.0%/76.5%) | M84: ="+2pt ("&TEXT($C$34+2*$C$81,"0.0%")&"/"&TEXT($C$35+2*$C$81,"0.0%")&")" -> +2pt (39.0%/77.5%) | O84: ="-2pt ("&TEXT($C$34+-2*$C$81,"0.0%")&"/"&TEXT($C$35+-2*$C$81,"0.0%")&")" -> -2pt (35.0%/73.5%) | P84: ="-1pt ("&TEXT($C$34+-1*$C$81,"0.0%")&"/"&TEXT($C$35+-1*$C$81,"0.0%")&")" -> -1pt (36.0%/74.5%) | Q84: ="Base ("&TEXT($C$34+0*$C$81,"0.0%")&"/"&TEXT($C$35+0*$C$81,"0.0%")&")" -> Base (37.0%/75.5%) | R84: ="+1pt ("&TEXT($C$34+1*$C$81,"0.0%")&"/"&TEXT($C$35+1*$C$81,"0.0%")&")" -> +1pt (38.0%/76.5%) | S84: ="+2pt ("&TEXT($C$34+2*$C$81,"0.0%")&"/"&TEXT($C$35+2*$C$81,"0.0%")&")" -> +2pt (39.0%/77.5%)
A85: Base -3pt | B85: =$C$77+-3*$C$80 -> 0.0014658324 | C85: =$C$76*(1+B85) -> 458869.61 | D85: =C85*$C$78 -> 325060.93 | E85: =C85*$C$79 -> 133808.69 | F85: =C85*$C$37 -> 38086.178 | G85: =C85*$C$36 -> 30285.394 | I85: =D85*($C$34+-2*$C$81)+E85*($C$35+-2*$C$81)-F85-G85 -> 143749.14 | J85: =D85*($C$34+-1*$C$81)+E85*($C$35+-1*$C$81)-F85-G85 -> 148337.83 | K85: =D85*($C$34+0*$C$81)+E85*($C$35+0*$C$81)-F85-G85 -> 152926.53 | L85: =D85*($C$34+1*$C$81)+E85*($C$35+1*$C$81)-F85-G85 -> 157515.22 | M85: =D85*($C$34+2*$C$81)+E85*($C$35+2*$C$81)-F85-G85 -> 162103.92 | O85: =I85*(1-$C$44)/$C$17 -> 8.2056272 | P85: =J85*(1-$C$44)/$C$17 -> 8.4675636 | Q85: =K85*(1-$C$44)/$C$17 -> 8.7295 | R85: =L85*(1-$C$44)/$C$17 -> 8.9914364 | S85: =M85*(1-$C$44)/$C$17 -> 9.2533728
A86: Base -2pt | B86: =$C$77+-2*$C$80 -> 0.011465832 | C86: =$C$76*(1+B86) -> 463451.59 | D86: =C86*$C$78 -> 328306.78 | E86: =C86*$C$79 -> 135144.82 | F86: =C86*$C$37 -> 38466.482 | G86: =C86*$C$36 -> 30587.805 | I86: =D86*($C$34+-2*$C$81)+E86*($C$35+-2*$C$81)-F86-G86 -> 145184.52 | J86: =D86*($C$34+-1*$C$81)+E86*($C$35+-1*$C$81)-F86-G86 -> 149819.04 | K86: =D86*($C$34+0*$C$81)+E86*($C$35+0*$C$81)-F86-G86 -> 154453.56 | L86: =D86*($C$34+1*$C$81)+E86*($C$35+1*$C$81)-F86-G86 -> 159088.07 | M86: =D86*($C$34+2*$C$81)+E86*($C$35+2*$C$81)-F86-G86 -> 163722.59 | O86: =I86*(1-$C$44)/$C$17 -> 8.2875634 | P86: =J86*(1-$C$44)/$C$17 -> 8.5521153 | Q86: =K86*(1-$C$44)/$C$17 -> 8.8166672 | R86: =L86*(1-$C$44)/$C$17 -> 9.0812192 | S86: =M86*(1-$C$44)/$C$17 -> 9.3457711
A87: Base -1pt | B87: =$C$77+-1*$C$80 -> 0.021465832 | C87: =$C$76*(1+B87) -> 468033.57 | D87: =C87*$C$78 -> 331552.63 | E87: =C87*$C$79 -> 136480.94 | F87: =C87*$C$37 -> 38846.786 | G87: =C87*$C$36 -> 30890.216 | I87: =D87*($C$34+-2*$C$81)+E87*($C$35+-2*$C$81)-F87-G87 -> 146619.91 | J87: =D87*($C$34+-1*$C$81)+E87*($C$35+-1*$C$81)-F87-G87 -> 151300.25 | K87: =D87*($C$34+0*$C$81)+E87*($C$35+0*$C$81)-F87-G87 -> 155980.58 | L87: =D87*($C$34+1*$C$81)+E87*($C$35+1*$C$81)-F87-G87 -> 160660.92 | M87: =D87*($C$34+2*$C$81)+E87*($C$35+2*$C$81)-F87-G87 -> 165341.25 | O87: =I87*(1-$C$44)/$C$17 -> 8.3694996 | P87: =J87*(1-$C$44)/$C$17 -> 8.636667 | Q87: =K87*(1-$C$44)/$C$17 -> 8.9038345 | R87: =L87*(1-$C$44)/$C$17 -> 9.1710019 | S87: =M87*(1-$C$44)/$C$17 -> 9.4381694
A88: Base growth | B88: =$C$77+0*$C$80 -> 0.031465832 | C88: =$C$76*(1+B88) -> 472615.55 | D88: =C88*$C$78 -> 334798.48 | E88: =C88*$C$79 -> 137817.07 | F88: =C88*$C$37 -> 39227.091 | G88: =C88*$C$36 -> 31192.626 | I88: =D88*($C$34+-2*$C$81)+E88*($C$35+-2*$C$81)-F88-G88 -> 148055.3 | J88: =D88*($C$34+-1*$C$81)+E88*($C$35+-1*$C$81)-F88-G88 -> 152781.45 | K88: =D88*($C$34+0*$C$81)+E88*($C$35+0*$C$81)-F88-G88 -> 157507.61 | L88: =D88*($C$34+1*$C$81)+E88*($C$35+1*$C$81)-F88-G88 -> 162233.77 | M88: =D88*($C$34+2*$C$81)+E88*($C$35+2*$C$81)-F88-G88 -> 166959.92 | O88: =I88*(1-$C$44)/$C$17 -> 8.4514357 | P88: =J88*(1-$C$44)/$C$17 -> 8.7212187 | Q88: =K88*(1-$C$44)/$C$17 -> 8.9910017 | R88: =L88*(1-$C$44)/$C$17 -> 9.2607847 | S88: =M88*(1-$C$44)/$C$17 -> 9.5305676
A89: Base +1pt | B89: =$C$77+1*$C$80 -> 0.041465832 | C89: =$C$76*(1+B89) -> 477197.53 | D89: =C89*$C$78 -> 338044.33 | E89: =C89*$C$79 -> 139153.2 | F89: =C89*$C$37 -> 39607.395 | G89: =C89*$C$36 -> 31495.037 | I89: =D89*($C$34+-2*$C$81)+E89*($C$35+-2*$C$81)-F89-G89 -> 149490.69 | J89: =D89*($C$34+-1*$C$81)+E89*($C$35+-1*$C$81)-F89-G89 -> 154262.66 | K89: =D89*($C$34+0*$C$81)+E89*($C$35+0*$C$81)-F89-G89 -> 159034.64 | L89: =D89*($C$34+1*$C$81)+E89*($C$35+1*$C$81)-F89-G89 -> 163806.61 | M89: =D89*($C$34+2*$C$81)+E89*($C$35+2*$C$81)-F89-G89 -> 168578.59 | O89: =I89*(1-$C$44)/$C$17 -> 8.5333719 | P89: =J89*(1-$C$44)/$C$17 -> 8.8057704 | Q89: =K89*(1-$C$44)/$C$17 -> 9.0781689 | R89: =L89*(1-$C$44)/$C$17 -> 9.3505674 | S89: =M89*(1-$C$44)/$C$17 -> 9.6229659
